Workbook

Sheet Summary
A1: 1
B3: Component Details | F3: Database Details | G3: Database Details | K3: Estimation Details
B4: Part No | C4: =BOM!D3 -> FWR10000 | G4: RM Base | I4: 46028 | K4: Estimated on | M4: 46121
B5: Part Rev | C5: =BOM!E3 -> # | G5: Process Base | H5: 43466 | I5: 45954 | K5: Estimated by | M5: Sridhar S
B6: Descrtiption | C6: =BOM!F3 -> Seat - Driver Pneumatic Suspended | G6: OH, Profit & Other Base | H6: 44743 | I6: 44743 | K6: Part type
B8: Cost Head | C8: Direct RM Cost | D8: Allowance cost | E8: BOP cost | F8: Total RM cost | G8: Process Cost | H8: OH | I8: Profit | J8: Total Basic Cost | K8: Amortization | L8: Packing Cost | M8: Total Cost
B9: Amount
B10: Ratio | C10: =C9/$M$9 -> #DIV/0! | D10: =D9/$M$9 -> #DIV/0! | E10: =E9/$M$9 -> #DIV/0! | F10: =F9/$M$9 -> #DIV/0! | G10: =G9/$M$9 -> #DIV/0! | H10: =H9/$M$9 -> #DIV/0! | I10: =I9/$M$9 -> #DIV/0! | J10: =J9/$M$9 -> #DIV/0! | ... L10: =L9/$M$9 -> #DIV/0!
C13: Direct RM Cost | D13: Allowance cost | E13: BOP cost | F13: Total RM cost | G13: Process Cost | H13: OH | I13: Profit | J13: Total Basic Cost | K13: Amortization | L13: Packing Cost | M13: Total Cost
C14: =C9 -> 0 | D14: =C14 -> 0 | E14: =D14+D15 -> 0 | F14: =F9 -> 0 | G14: =F14 -> 0 | H14: =G14+G15 -> 0 | I14: =H14+H15 -> 0 | J14: =J9 -> 0 | K14: =J14 -> 0 | L14: =K14+K15 -> 0 | M14: =M9 -> 0
C15: 0 | D15: =D9 -> 0 | E15: =E9 -> 0 | G15: =G9 -> 0 | H15: =H9 -> 0 | I15: =I9 -> 0 | K15: =K9 -> 0 | L15: =L9 -> 0

Sheet BOM
A1: 1 | K1: =SUMPRODUCT(K3:K9999,$G3:$G9999) -> 5285.0334 | L1: =SUMPRODUCT(L3:L9999,$G3:$G9999) -> 224.59001 | M1: =SUMPRODUCT(M3:M9999,$G3:$G9999) -> 100.50216 | N1: =SUMPRODUCT(N3:N9999,$G3:$G9999) -> 59.82928 | O1: =SUMPRODUCT(O3:O9999,$G3:$G9999) -> 62.73469 | P1: =SUM(P3:P9999) -> 5180.9044 | Q1: =SUM(Q3:Q9999) -> 5732.6896 | T1: Total Weight | U1: =SUM(U3:U999999) -> 36.396 | AA1: =SUMPRODUCT(AA3:AA52,$G3:$G52) -> 224.59001 | AB1: =SUMPRODUCT(AB3:AB52,$G3:$G52) -> 8.68742 | AC1: =SUMPRODUCT(AC3:AC52,$G3:$G52) -> 0 | AD1: =SUMPRODUCT(AD3:AD52,$G3:$G52) -> 7.42932 | AE1: =SUMPRODUCT(AE3:AE52,$G3:$G52) -> 1.93053 | AF1: =SUMPRODUCT(AF3:AF52,$G3:$G52) -> 2.24589 | AG1: =SUMPRODUCT(AG3:AG52,$G3:$G52) -> 8.09347 | AH1: =SUMPRODUCT(AH3:AH52,$G3:$G52) -> 0 | ... AW1: =SUMPRODUCT(AW3:AW52,$G3:$G52) -> 100.50216 | AX1: =SUM(AX3:AX52) -> 5180.9044 | AY1: =SUM(AY3:AY52) -> 5732.6896
A2: S.no | B2: Parent part No. | C2: Level | D2: Part No. | E2: Rev | F2: Parts Description | G2: Qty | H2: Process Type | I2: Scope | J2: Method | K2: Material Cost | L2: Process Cost | M2: Surface finish cost Inhouse | N2: OH & Others | O2: Profit | P2: CPU | Q2: CPA | R2: CPSA | S2: Remarks | T2: Weight | U2: Total Weight | V2: Rate/kg | AA2: Process cost | AB2: ICC on RM | AC2: ICC on Conv | AD2: ICC on BOF | AE2: Rej on RM | AF2: Rej on Conv | AG2: Rej on BOF | AH2: Inspection on RM | AI2: Inspection on Conv | AJ2: Inspection on BOP | AK2: TMC on RM | AL2: TMC on Conv | AM2: TMC on BOF | AN2: Design cost on RM | AO2: Design cost on Conv | AP2: Design cost on BOP | AQ2: OH on RM | AR2: OH on Conv | AS2: OH on BOP | AT2: Profit on RM | AU2: Profit on Conv | AV2: Profit on BOP | AW2: Surface finish cost Inhouse | AX2: CPU | AY2: CPA
A3: 1 | B3: =D3 -> FWR10000 | C3: 1 | D3: FWR10000 | E3: # | F3: Seat - Driver Pneumatic Suspended | G3: 1 | H3: Assembly | I3: Inhouse | J3: CSC | K3: =_xlfn.IFNA(Backend!AN8,"") -> 0 | L3: =IFERROR(AA3,"") -> 0 | M3: =IFERROR(AW3,"") -> 0 | N3: =IF(SUM(AB3:AS3)=0,"",SUM(AB3:AS3)) | O3: =IF(SUM(AT3:AV3)=0,"",SUM(AT3:AV3)) | P3: =IF(K3="","",SUM(K3:O3)) -> 0 | Q3: =IF(P3="","",P3*G3) -> 0 | T3: =_xlfn.IFNA(IF(VLOOKUP(D3,Group!C:I,7,0)=0,"",VLOOKUP(D3,Group!C:I,7,0)),"") | U3: =IFERROR(T3*G3,"") | V3: =IFERROR(AY3/U3,"") | AA3: =_xlfn.IFNA(Backend!AO8,"") -> 0 | AB3: =Backend!AP8 -> 0 | AC3: =Backend!AQ8 -> 0 | AD3: =Backend!AR8 | AE3: =Backend!AS8 -> 0 | AF3: =Backend!AT8 -> 0 | AG3: =Backend!AU8 | AH3: =Backend!AV8 -> 0 | AI3: =Backend!AW8 -> 0 | ... AV3: =Backend!BJ8 | AW3: =_xlfn.IFNA(Backend!O8,"") -> 0 | AX3: =_xlfn.IFNA(IF(D3="","",Backend!BK8),"") -> 0 | AY3: =IF(AX3="","",AX3*G3) -> 0
A4: 2 | B4: =B3 -> FWR10000 | C4: 2 | D4: H 157 01 464 A | E4: 1 | F4: SLIDER KIT ASSY | G4: 1 | H4: Assembly | I4: Inhouse | J4: CSC | K4: =_xlfn.IFNA(Backend!AN9,"") -> 0 | L4: =IFERROR(AA4,"") -> 0 | M4: =IFERROR(AW4,"") -> 0 | N4: =IF(SUM(AB4:AS4)=0,"",SUM(AB4:AS4)) | O4: =IF(SUM(AT4:AV4)=0,"",SUM(AT4:AV4)) | P4: =IF(K4="","",SUM(K4:O4)) -> 0 | Q4: =IF(P4="","",P4*G4) -> 0 | T4: =_xlfn.IFNA(IF(VLOOKUP(D4,Group!C:I,7,0)=0,"",VLOOKUP(D4,Group!C:I,7,0)),"") | U4: =IFERROR(T4*G4,"") | V4: =IFERROR(AY4/U4,"") | AA4: =_xlfn.IFNA(Backend!AO9,"") -> 0 | AB4: =Backend!AP9 -> 0 | AC4: =Backend!AQ9 -> 0 | AD4: =Backend!AR9 | AE4: =Backend!AS9 -> 0 | AF4: =Backend!AT9 -> 0 | AG4: =Backend!AU9 | AH4: =Backend!AV9 -> 0 | AI4: =Backend!AW9 -> 0 | ... AV4: =Backend!BJ9 | AW4: =_xlfn.IFNA(Backend!O9,"") -> 0 | AX4: =_xlfn.IFNA(IF(D4="","",Backend!BK9),"") -> 0 | AY4: =IF(AX4="","",AX4*G4) -> 0
A5: 3 | B5: =B4 -> FWR10000 | C5: 3 | D5: H 157 01 464 A Top Mounting Brkt LH &RH | F5: Top Mounting Brkt LH &RH | G5: 2 | H5: Sheet Metal-B | I5: Inhouse | J5: CSC | K5: =_xlfn.IFNA(Backend!AN10,"") -> 52.18489 | L5: =IFERROR(AA5,"") -> 7.01506 | M5: =IFERROR(AW5,"") -> 10.30773 | N5: =IF(SUM(AB5:AS5)=0,"",SUM(AB5:AS5)) -> 2.48734 | O5: =IF(SUM(AT5:AV5)=0,"",SUM(AT5:AV5)) -> 3.55199 | P5: =IF(K5="","",SUM(K5:O5)) -> 75.54701 | Q5: =IF(P5="","",P5*G5) -> 151.09402 | T5: =_xlfn.IFNA(IF(VLOOKUP(D5,Group!C:I,7,0)=0,"",VLOOKUP(D5,Group!C:I,7,0)),"") -> 0.87 | U5: =IFERROR(T5*G5,"") -> 1.74 | V5: =IFERROR(AY5/U5,"") -> 86.835644 | AA5: =_xlfn.IFNA(Backend!AO10,"") -> 7.01506 | AB5: =Backend!AP10 -> 1.17416 | AC5: =Backend!AQ10 -> 0 | AD5: =Backend!AR10 | AE5: =Backend!AS10 -> 0.26092 | AF5: =Backend!AT10 -> 0.07015 | AG5: =Backend!AU10 | AH5: =Backend!AV10 -> 0 | AI5: =Backend!AW10 -> 0 | ... AV5: =Backend!BJ10 | AW5: =_xlfn.IFNA(Backend!O10,"") -> 10.30773 | AX5: =_xlfn.IFNA(IF(D5="","",Backend!BK10),"") -> 75.54701 | AY5: =IF(AX5="","",AX5*G5) -> 151.09402
A6: 4 | B6: =B5 -> FWR10000 | C6: 3 | D6: H 157 01 464 A M8 weld Nut | F6: M8 weld Nut | G6: 10 | H6: Sheet Metal-B | I6: BOF | J6: Standard | K6: =_xlfn.IFNA(Backend!AN11,"") -> 0.77 | L6: =IFERROR(AA6,"") | M6: =IFERROR(AW6,"") | N6: =IF(SUM(AB6:AS6)=0,"",SUM(AB6:AS6)) -> 0.0154 | O6: =IF(SUM(AT6:AV6)=0,"",SUM(AT6:AV6)) -> 0.0231 | P6: =IF(K6="","",SUM(K6:O6)) -> 0.8085 | Q6: =IF(P6="","",P6*G6) -> 8.085 | T6: =_xlfn.IFNA(IF(VLOOKUP(D6,Group!C:I,7,0)=0,"",VLOOKUP(D6,Group!C:I,7,0)),"") | U6: =IFERROR(T6*G6,"") | V6: =IFERROR(AY6/U6,"") | AA6: =_xlfn.IFNA(Backend!AO11,"") | AB6: =Backend!AP11 | AC6: =Backend!AQ11 | AD6: =Backend!AR11 -> 0.01155 | AE6: =Backend!AS11 | AF6: =Backend!AT11 | AG6: =Backend!AU11 -> 0.00385 | AH6: =Backend!AV11 | AI6: =Backend!AW11 | ... AV6: =Backend!BJ11 -> 0.0231 | AW6: =_xlfn.IFNA(Backend!O11,"") | AX6: =_xlfn.IFNA(IF(D6="","",Backend!BK11),"") -> 0.8085 | AY6: =IF(AX6="","",AX6*G6) -> 8.085
A7: 5 | B7: =B6 -> FWR10000 | C7: 3 | D7: H 157 01 464 A Rear Stopper LH &RH | F7: Rear Stopper LH &RH | G7: 2 | H7: Sheet Metal-B | I7: Inhouse | J7: CSC | K7: =_xlfn.IFNA(Backend!AN12,"") -> 3.66953 | L7: =IFERROR(AA7,"") -> 1.5933 | M7: =IFERROR(AW7,"") -> 1.19427 | N7: =IF(SUM(AB7:AS7)=0,"",SUM(AB7:AS7)) -> 0.33991 | O7: =IF(SUM(AT7:AV7)=0,"",SUM(AT7:AV7)) -> 0.31577 | P7: =IF(K7="","",SUM(K7:O7)) -> 7.11278 | Q7: =IF(P7="","",P7*G7) -> 14.22556 | T7: =_xlfn.IFNA(IF(VLOOKUP(D7,Group!C:I,7,0)=0,"",VLOOKUP(D7,Group!C:I,7,0)),"") -> 0.063 | U7: =IFERROR(T7*G7,"") -> 0.126 | V7: =IFERROR(AY7/U7,"") -> 112.90127 | AA7: =_xlfn.IFNA(Backend!AO12,"") -> 1.5933 | AB7: =Backend!AP12 -> 0.08256 | AC7: =Backend!AQ12 -> 0 | AD7: =Backend!AR12 | AE7: =Backend!AS12 -> 0.01835 | AF7: =Backend!AT12 -> 0.01593 | AG7: =Backend!AU12 | AH7: =Backend!AV12 -> 0 | AI7: =Backend!AW12 -> 0 | ... AV7: =Backend!BJ12 | AW7: =_xlfn.IFNA(Backend!O12,"") -> 1.19427 | AX7: =_xlfn.IFNA(IF(D7="","",Backend!BK12),"") -> 7.11278 | AY7: =IF(AX7="","",AX7*G7) -> 14.22556
A8: 6 | B8: =B7 -> FWR10000 | C8: 3 | D8: H 157 01 464 A Bottom MTG BRKT RH | F8: Bottom MTG BRKT RH | G8: 1 | H8: Sheet Metal-B | I8: Inhouse | J8: CSC | K8: =_xlfn.IFNA(Backend!AN13,"") -> 74.93066 | L8: =IFERROR(AA8,"") -> 11.78049 | M8: =IFERROR(AW8,"") -> 14.88104 | N8: =IF(SUM(AB8:AS8)=0,"",SUM(AB8:AS8)) -> 3.82766 | O8: =IF(SUM(AT8:AV8)=0,"",SUM(AT8:AV8)) -> 5.20267 | P8: =IF(K8="","",SUM(K8:O8)) -> 110.62252 | Q8: =IF(P8="","",P8*G8) -> 110.62252 | T8: =_xlfn.IFNA(IF(VLOOKUP(D8,Group!C:I,7,0)=0,"",VLOOKUP(D8,Group!C:I,7,0)),"") -> 1.256 | U8: =IFERROR(T8*G8,"") -> 1.256 | V8: =IFERROR(AY8/U8,"") -> 88.075255 | AA8: =_xlfn.IFNA(Backend!AO13,"") -> 11.78049 | AB8: =Backend!AP13 -> 1.68594 | AC8: =Backend!AQ13 -> 0 | AD8: =Backend!AR13 | AE8: =Backend!AS13 -> 0.37465 | AF8: =Backend!AT13 -> 0.1178 | AG8: =Backend!AU13 | AH8: =Backend!AV13 -> 0 | AI8: =Backend!AW13 -> 0 | ... AV8: =Backend!BJ13 | AW8: =_xlfn.IFNA(Backend!O13,"") -> 14.88104 | AX8: =_xlfn.IFNA(IF(D8="","",Backend!BK13),"") -> 110.62252 | AY8: =IF(AX8="","",AX8*G8) -> 110.62252
A9: 7 | B9: =B8 -> FWR10000 | C9: 3 | D9: H 157 01 464 A Bottom MTG BRKT REINF | F9: Bottom MTG BRKT REINF | G9: 2 | H9: Sheet Metal-B | I9: Inhouse | J9: CSC | K9: =_xlfn.IFNA(Backend!AN14,"") -> 3.32747 | L9: =IFERROR(AA9,"") -> 0.84451 | M9: =IFERROR(AW9,"") -> 0.41705 | N9: =IF(SUM(AB9:AS9)=0,"",SUM(AB9:AS9)) -> 0.21819 | O9: =IF(SUM(AT9:AV9)=0,"",SUM(AT9:AV9)) -> 0.25032 | P9: =IF(K9="","",SUM(K9:O9)) -> 5.05754 | Q9: =IF(P9="","",P9*G9) -> 10.11508 | T9: =_xlfn.IFNA(IF(VLOOKUP(D9,Group!C:I,7,0)=0,"",VLOOKUP(D9,Group!C:I,7,0)),"") -> 0.044 | U9: =IFERROR(T9*G9,"") -> 0.088 | V9: =IFERROR(AY9/U9,"") -> 114.94409 | AA9: =_xlfn.IFNA(Backend!AO14,"") -> 0.84451 | AB9: =Backend!AP14 -> 0.07487 | AC9: =Backend!AQ14 -> 0 | AD9: =Backend!AR14 | AE9: =Backend!AS14 -> 0.01664 | AF9: =Backend!AT14 -> 0.00845 | AG9: =Backend!AU14 | AH9: =Backend!AV14 -> 0 | AI9: =Backend!AW14 -> 0 | ... AV9: =Backend!BJ14 | AW9: =_xlfn.IFNA(Backend!O14,"") -> 0.41705 | AX9: =_xlfn.IFNA(IF(D9="","",Backend!BK14),"") -> 5.05754 | AY9: =IF(AX9="","",AX9*G9) -> 10.11508
A10: 8 | B10: =B9 -> FWR10000 | C10: 3 | D10: H 157 01 464 A Bottom MTG BRKT Spacer | F10: Bottom MTG BRKT Spacer | G10: 4 | H10: Sheet Metal-B | I10: Inhouse | J10: CSC | K10: =_xlfn.IFNA(Backend!AN15,"") -> 1.2423 | L10: =IFERROR(AA10,"") -> 15.13397 | M10: =IFERROR(AW10,"") -> 0.08846 | N10: =IF(SUM(AB10:AS10)=0,"",SUM(AB10:AS10)) -> 2.30426 | O10: =IF(SUM(AT10:AV10)=0,"",SUM(AT10:AV10)) -> 0.98258 | P10: =IF(K10="","",SUM(K10:O10)) -> 19.75157 | Q10: =IF(P10="","",P10*G10) -> 79.00628 | T10: =_xlfn.IFNA(IF(VLOOKUP(D10,Group!C:I,7,0)=0,"",VLOOKUP(D10,Group!C:I,7,0)),"") -> 0.014 | U10: =IFERROR(T10*G10,"") -> 0.056 | V10: =IFERROR(AY10/U10,"") -> 1410.8264 | AA10: =_xlfn.IFNA(Backend!AO15,"") -> 15.13397 | AB10: =Backend!AP15 -> 0.02795 | AC10: =Backend!AQ15 -> 0 | AD10: =Backend!AR15 | AE10: =Backend!AS15 -> 0.00621 | AF10: =Backend!AT15 -> 0.15134 | AG10: =Backend!AU15 | AH10: =Backend!AV15 -> 0 | AI10: =Backend!AW15 -> 0 | ... AV10: =Backend!BJ15 | AW10: =_xlfn.IFNA(Backend!O15,"") -> 0.08846 | AX10: =_xlfn.IFNA(IF(D10="","",Backend!BK15),"") -> 19.75157 | AY10: =IF(AX10="","",AX10*G10) -> 79.00628
A11: 9 | B11: =B10 -> FWR10000 | C11: 3 | D11: H 157 01 464 A Bottom MTG BRKT LH 1 | F11: Bottom MTG BRKT LH 1 | G11: 1 | H11: Sheet Metal-B | I11: Inhouse | J11: CSC | K11: =_xlfn.IFNA(Backend!AN16,"") -> 13.89634 | L11: =IFERROR(AA11,"") -> 7.33423 | M11: =IFERROR(AW11,"") -> 2.63025 | N11: =IF(SUM(AB11:AS11)=0,"",SUM(AB11:AS11)) -> 1.48228 | O11: =IF(SUM(AT11:AV11)=0,"",SUM(AT11:AV11)) -> 1.27383 | P11: =IF(K11="","",SUM(K11:O11)) -> 26.61693 | Q11: =IF(P11="","",P11*G11) -> 26.61693 | T11: =_xlfn.IFNA(IF(VLOOKUP(D11,Group!C:I,7,0)=0,"",VLOOKUP(D11,Group!C:I,7,0)),"") -> 0.222 | U11: =IFERROR(T11*G11,"") -> 0.222 | V11: =IFERROR(AY11/U11,"") -> 119.89608 | AA11: =_xlfn.IFNA(Backend!AO16,"") -> 7.33423 | AB11: =Backend!AP16 -> 0.31267 | AC11: =Backend!AQ16 -> 0 | AD11: =Backend!AR16 | AE11: =Backend!AS16 -> 0.06948 | AF11: =Backend!AT16 -> 0.07334 | AG11: =Backend!AU16 | AH11: =Backend!AV16 -> 0 | AI11: =Backend!AW16 -> 0 | ... AV11: =Backend!BJ16 | AW11: =_xlfn.IFNA(Backend!O16,"") -> 2.63025 | AX11: =_xlfn.IFNA(IF(D11="","",Backend!BK16),"") -> 26.61693 | AY11: =IF(AX11="","",AX11*G11) -> 26.61693
A12: 10 | B12: =B11 -> FWR10000 | C12: 3 | D12: H 157 01 464 A Bottom MTG BRKT LH 2 | F12: Bottom MTG BRKT LH 2 | G12: 1 | H12: Sheet Metal-B | I12: Inhouse | J12: CSC | K12: =_xlfn.IFNA(Backend!AN17,"") -> 16.69648 | L12: =IFERROR(AA12,"") -> 2.60869 | M12: =IFERROR(AW12,"") -> 3.31743 | N12: =IF(SUM(AB12:AS12)=0,"",SUM(AB12:AS12)) -> 0.85045 | O12: =IF(SUM(AT12:AV12)=0,"",SUM(AT12:AV12)) -> 1.15831 | P12: =IF(K12="","",SUM(K12:O12)) -> 24.63136 | Q12: =IF(P12="","",P12*G12) -> 24.63136 | T12: =_xlfn.IFNA(IF(VLOOKUP(D12,Group!C:I,7,0)=0,"",VLOOKUP(D12,Group!C:I,7,0)),"") -> 0.28 | U12: =IFERROR(T12*G12,"") -> 0.28 | V12: =IFERROR(AY12/U12,"") -> 87.969143 | AA12: =_xlfn.IFNA(Backend!AO17,"") -> 2.60869 | AB12: =Backend!AP17 -> 0.37567 | AC12: =Backend!AQ17 -> 0 | AD12: =Backend!AR17 | AE12: =Backend!AS17 -> 0.08348 | AF12: =Backend!AT17 -> 0.02609 | AG12: =Backend!AU17 | AH12: =Backend!AV17 -> 0 | AI12: =Backend!AW17 -> 0 | ... AV12: =Backend!BJ17 | AW12: =_xlfn.IFNA(Backend!O17,"") -> 3.31743 | AX12: =_xlfn.IFNA(IF(D12="","",Backend!BK17),"") -> 24.63136 | AY12: =IF(AX12="","",AX12*G12) -> 24.63136
A13: 11 | B13: =B12 -> FWR10000 | C13: 3 | D13: H 157 01 464 A Slider Upper Track | F13: Slider Upper Track | G13: 2 | H13: Sheet Metal-B | I13: Inhouse | J13: CSC | K13: =_xlfn.IFNA(Backend!AN18,"") -> 21.32976 | L13: =IFERROR(AA13,"") -> 24.32889 | M13: =IFERROR(AW13,"") -> 9.73113 | N13: =IF(SUM(AB13:AS13)=0,"",SUM(AB13:AS13)) -> 4.23591 | O13: =IF(SUM(AT13:AV13)=0,"",SUM(AT13:AV13)) -> 2.73952 | P13: =IF(K13="","",SUM(K13:O13)) -> 62.36521 | Q13: =IF(P13="","",P13*G13) -> 124.73042 | T13: =_xlfn.IFNA(IF(VLOOKUP(D13,Group!C:I,7,0)=0,"",VLOOKUP(D13,Group!C:I,7,0)),"") -> 0.385 | U13: =IFERROR(T13*G13,"") -> 0.77 | V13: =IFERROR(AY13/U13,"") -> 161.98756 | AA13: =_xlfn.IFNA(Backend!AO18,"") -> 24.32889 | AB13: =Backend!AP18 -> 0.47992 | AC13: =Backend!AQ18 -> 0 | AD13: =Backend!AR18 | AE13: =Backend!AS18 -> 0.10665 | AF13: =Backend!AT18 -> 0.24329 | AG13: =Backend!AU18 | AH13: =Backend!AV18 -> 0 | AI13: =Backend!AW18 -> 0 | ... AV13: =Backend!BJ18 | AW13: =_xlfn.IFNA(Backend!O18,"") -> 9.73113 | AX13: =_xlfn.IFNA(IF(D13="","",Backend!BK18),"") -> 62.36521 | AY13: =IF(AX13="","",AX13*G13) -> 124.73042
A14: 12 | B14: =B13 -> FWR10000 | C14: 3 | D14: H 157 01 464 A Slider Lower Track | F14: Slider Lower Track | G14: 2 | H14: Sheet Metal-B | I14: Inhouse | J14: CSC | K14: =_xlfn.IFNA(Backend!AN19,"") -> 24.41607 | L14: =IFERROR(AA14,"") -> 6.97526 | M14: =IFERROR(AW14,"") -> 11.39932 | N14: =IF(SUM(AB14:AS14)=0,"",SUM(AB14:AS14)) -> 1.71773 | O14: =IF(SUM(AT14:AV14)=0,"",SUM(AT14:AV14)) -> 1.88348 | P14: =IF(K14="","",SUM(K14:O14)) -> 46.39186 | Q14: =IF(P14="","",P14*G14) -> 92.78372 | T14: =_xlfn.IFNA(IF(VLOOKUP(D14,Group!C:I,7,0)=0,"",VLOOKUP(D14,Group!C:I,7,0)),"") -> 0.451 | U14: =IFERROR(T14*G14,"") -> 0.902 | V14: =IFERROR(AY14/U14,"") -> 102.86443 | AA14: =_xlfn.IFNA(Backend!AO19,"") -> 6.97526 | AB14: =Backend!AP19 -> 0.54936 | AC14: =Backend!AQ19 -> 0 | AD14: =Backend!AR19 | AE14: =Backend!AS19 -> 0.12208 | AF14: =Backend!AT19 -> 0.06975 | AG14: =Backend!AU19 | AH14: =Backend!AV19 -> 0 | AI14: =Backend!AW19 -> 0 | ... AV14: =Backend!BJ19 | AW14: =_xlfn.IFNA(Backend!O19,"") -> 11.39932 | AX14: =_xlfn.IFNA(IF(D14="","",Backend!BK19),"") -> 46.39186 | AY14: =IF(AX14="","",AX14*G14) -> 92.78372
A15: 13 | B15: =B14 -> FWR10000 | C15: 3 | D15: H 157 01 464 A Slider Upper Track plate | F15: Slider Upper Track plate | G15: 2 | H15: Sheet Metal-B | I15: Inhouse | J15: CSC | K15: =_xlfn.IFNA(Backend!AN20,"") -> 2.23646 | L15: =IFERROR(AA15,"") -> 23.27794 | M15: =IFERROR(AW15,"") -> 1.36489 | N15: =IF(SUM(AB15:AS15)=0,"",SUM(AB15:AS15)) -> 3.55319 | O15: =IF(SUM(AT15:AV15)=0,"",SUM(AT15:AV15)) -> 1.53087 | P15: =IF(K15="","",SUM(K15:O15)) -> 31.96335 | Q15: =IF(P15="","",P15*G15) -> 63.9267 | T15: =_xlfn.IFNA(IF(VLOOKUP(D15,Group!C:I,7,0)=0,"",VLOOKUP(D15,Group!C:I,7,0)),"") -> 0.036 | U15: =IFERROR(T15*G15,"") -> 0.072 | V15: =IFERROR(AY15/U15,"") -> 887.87083 | AA15: =_xlfn.IFNA(Backend!AO20,"") -> 23.27794 | AB15: =Backend!AP20 -> 0.05032 | AC15: =Backend!AQ20 -> 0 | AD15: =Backend!AR20 | AE15: =Backend!AS20 -> 0.01118 | AF15: =Backend!AT20 -> 0.23278 | AG15: =Backend!AU20 | AH15: =Backend!AV20 -> 0 | AI15: =Backend!AW20 -> 0 | ... AV15: =Backend!BJ20 | AW15: =_xlfn.IFNA(Backend!O20,"") -> 1.36489 | AX15: =_xlfn.IFNA(IF(D15="","",Backend!BK20),"") -> 31.96335 | AY15: =IF(AX15="","",AX15*G15) -> 63.9267
A16: 14 | B16: =B15 -> FWR10000 | C16: 3 | D16: H 157 01 464 A Slider Lower Track REINF | F16: Slider Lower Track REINF | G16: 2 | H16: Sheet Metal-B | I16: Inhouse | J16: CSC | K16: =_xlfn.IFNA(Backend!AN21,"") -> 3.15506 | L16: =IFERROR(AA16,"") -> 1.22199 | M16: =IFERROR(AW16,"") -> 1.31433 | N16: =IF(SUM(AB16:AS16)=0,"",SUM(AB16:AS16)) -> 0.27007 | O16: =IF(SUM(AT16:AV16)=0,"",SUM(AT16:AV16)) -> 0.26262 | P16: =IF(K16="","",SUM(K16:O16)) -> 6.22407 | Q16: =IF(P16="","",P16*G16) -> 12.44814 | T16: =_xlfn.IFNA(IF(VLOOKUP(D16,Group!C:I,7,0)=0,"",VLOOKUP(D16,Group!C:I,7,0)),"") -> 0.052 | U16: =IFERROR(T16*G16,"") -> 0.104 | V16: =IFERROR(AY16/U16,"") -> 119.69365 | AA16: =_xlfn.IFNA(Backend!AO21,"") -> 1.22199 | AB16: =Backend!AP21 -> 0.07099 | AC16: =Backend!AQ21 -> 0 | AD16: =Backend!AR21 | AE16: =Backend!AS21 -> 0.01578 | AF16: =Backend!AT21 -> 0.01222 | AG16: =Backend!AU21 | AH16: =Backend!AV21 -> 0 | AI16: =Backend!AW21 -> 0 | ... AV16: =Backend!BJ21 | AW16: =_xlfn.IFNA(Backend!O21,"") -> 1.31433 | AX16: =_xlfn.IFNA(IF(D16="","",Backend!BK21),"") -> 6.22407 | AY16: =IF(AX16="","",AX16*G16) -> 12.44814
... A24: 22 | B24: =B23 -> FWR10000 | C24: 3 | D24: H 157 01 464 A Slider Rivet Ø6mm | F24: Slider Rivet Ø6mm | G24: 4 | H24: Sheet Metal-B | I24: BOF | J24: Standard | K24: =_xlfn.IFNA(Backend!AN29,"") -> 1.8 | L24: =IFERROR(AA24,"") | M24: =IFERROR(AW24,"") | N24: =IF(SUM(AB24:AS24)=0,"",SUM(AB24:AS24)) -> 0.036 | O24: =IF(SUM(AT24:AV24)=0,"",SUM(AT24:AV24)) -> 0.054 | P24: =IF(K24="","",SUM(K24:O24)) -> 1.89 | Q24: =IF(P24="","",P24*G24) -> 7.56 | T24: =_xlfn.IFNA(IF(VLOOKUP(D24,Group!C:I,7,0)=0,"",VLOOKUP(D24,Group!C:I,7,0)),"") | U24: =IFERROR(T24*G24,"") | V24: =IFERROR(AY24/U24,"") | AA24: =_xlfn.IFNA(Backend!AO29,"") | AB24: =Backend!AP29 | AC24: =Backend!AQ29 | AD24: =Backend!AR29 -> 0.027 | AE24: =Backend!AS29 | AF24: =Backend!AT29 | AG24: =Backend!AU29 -> 0.009 | AH24: =Backend!AV29 | AI24: =Backend!AW29 | ... AV24: =Backend!BJ29 -> 0.054 | AW24: =_xlfn.IFNA(Backend!O29,"") | AX24: =_xlfn.IFNA(IF(D24="","",Backend!BK29),"") -> 1.89 | AY24: =IF(AX24="","",AX24*G24) -> 7.56
A25: 23 | B25: =B24 -> FWR10000 | C25: 2 | D25: H 157 01 465 S | E25: 2 | F25: TETHER BELT BOTTOM BRKT | G25: 1 | H25: Sheet Metal-B | I25: Inhouse | J25: CSC | K25: =_xlfn.IFNA(Backend!AN30,"") -> 26.23889 | L25: =IFERROR(AA25,"") -> 4.38942 | M25: =IFERROR(AW25,"") -> 4.8121 | N25: =IF(SUM(AB25:AS25)=0,"",SUM(AB25:AS25)) -> 1.37997 | O25: =IF(SUM(AT25:AV25)=0,"",SUM(AT25:AV25)) -> 1.8377 | P25: =IF(K25="","",SUM(K25:O25)) -> 38.65808 | Q25: =IF(P25="","",P25*G25) -> 38.65808 | T25: =_xlfn.IFNA(IF(VLOOKUP(D25,Group!C:I,7,0)=0,"",VLOOKUP(D25,Group!C:I,7,0)),"") -> 0.33 | U25: =IFERROR(T25*G25,"") -> 0.33 | V25: =IFERROR(AY25/U25,"") -> 117.1457 | AA25: =_xlfn.IFNA(Backend!AO30,"") -> 4.38942 | AB25: =Backend!AP30 -> 0.59037 | AC25: =Backend!AQ30 -> 0 | AD25: =Backend!AR30 | AE25: =Backend!AS30 -> 0.13119 | AF25: =Backend!AT30 -> 0.04389 | AG25: =Backend!AU30 | AH25: =Backend!AV30 -> 0 | AI25: =Backend!AW30 -> 0 | ... AV25: =Backend!BJ30 | AW25: =_xlfn.IFNA(Backend!O30,"") -> 4.8121 | AX25: =_xlfn.IFNA(IF(D25="","",Backend!BK30),"") -> 38.65808 | AY25: =IF(AX25="","",AX25*G25) -> 38.65808
A26: 24 | B26: =B25 -> FWR10000 | C26: 2 | D26: H 157 01 270 A | E26: 3 | F26: Pnematic suspension CV | G26: 1 | H26: Assembly | I26: Inhouse | J26: CSC | K26: =_xlfn.IFNA(Backend!AN31,"") -> 0 | L26: =IFERROR(AA26,"") -> 0 | M26: =IFERROR(AW26,"") -> 0 | N26: =IF(SUM(AB26:AS26)=0,"",SUM(AB26:AS26)) | O26: =IF(SUM(AT26:AV26)=0,"",SUM(AT26:AV26)) | P26: =IF(K26="","",SUM(K26:O26)) -> 0 | Q26: =IF(P26="","",P26*G26) -> 0 | T26: =_xlfn.IFNA(IF(VLOOKUP(D26,Group!C:I,7,0)=0,"",VLOOKUP(D26,Group!C:I,7,0)),"") | U26: =IFERROR(T26*G26,"") | V26: =IFERROR(AY26/U26,"") | AA26: =_xlfn.IFNA(Backend!AO31,"") -> 0 | AB26: =Backend!AP31 -> 0 | AC26: =Backend!AQ31 -> 0 | AD26: =Backend!AR31 | AE26: =Backend!AS31 -> 0 | AF26: =Backend!AT31 -> 0 | AG26: =Backend!AU31 | AH26: =Backend!AV31 -> 0 | AI26: =Backend!AW31 -> 0 | ... AV26: =Backend!BJ31 | AW26: =_xlfn.IFNA(Backend!O31,"") -> 0 | AX26: =_xlfn.IFNA(IF(D26="","",Backend!BK31),"") -> 0 | AY26: =IF(AX26="","",AX26*G26) -> 0
A27: 25 | B27: =B26 -> FWR10000 | C27: 3 | D27: H 157 01 270 A Botttom Frame | F27: Botttom Frame | G27: 1 | H27: Sheet Metal-B | I27: Inhouse | J27: LPP-Thumbrule | K27: =_xlfn.IFNA(Backend!AN32,"") -> 641.7 | L27: =IFERROR(AA27,"") | M27: =IFERROR(AW27,"") | N27: =IF(SUM(AB27:AS27)=0,"",SUM(AB27:AS27)) | O27: =IF(SUM(AT27:AV27)=0,"",SUM(AT27:AV27)) | P27: =IF(K27="","",SUM(K27:O27)) -> 641.7 | Q27: =IF(P27="","",P27*G27) -> 641.7 | T27: =_xlfn.IFNA(IF(VLOOKUP(D27,Group!C:I,7,0)=0,"",VLOOKUP(D27,Group!C:I,7,0)),"") -> 4.278 | U27: =IFERROR(T27*G27,"") -> 4.278 | V27: =IFERROR(AY27/U27,"") -> 150 | AA27: =_xlfn.IFNA(Backend!AO32,"") | AB27: =Backend!AP32 | AC27: =Backend!AQ32 | AD27: =Backend!AR32 | AE27: =Backend!AS32 | AF27: =Backend!AT32 | AG27: =Backend!AU32 | AH27: =Backend!AV32 | AI27: =Backend!AW32 | ... AV27: =Backend!BJ32 | AW27: =_xlfn.IFNA(Backend!O32,"") | AX27: =_xlfn.IFNA(IF(D27="","",Backend!BK32),"") -> 641.7 | AY27: =IF(AX27="","",AX27*G27) -> 641.7
A28: 26 | B28: =B27 -> FWR10000 | C28: 3 | D28: H 157 01 270 A Outer Roller set | F28: Outer Roller set | G28: 1 | H28: Sheet Metal-B | I28: Inhouse | J28: LPP-Thumbrule | K28: =_xlfn.IFNA(Backend!AN33,"") -> 357.6 | L28: =IFERROR(AA28,"") | M28: =IFERROR(AW28,"") | N28: =IF(SUM(AB28:AS28)=0,"",SUM(AB28:AS28)) | O28: =IF(SUM(AT28:AV28)=0,"",SUM(AT28:AV28)) | P28: =IF(K28="","",SUM(K28:O28)) -> 357.6 | Q28: =IF(P28="","",P28*G28) -> 357.6 | T28: =_xlfn.IFNA(IF(VLOOKUP(D28,Group!C:I,7,0)=0,"",VLOOKUP(D28,Group!C:I,7,0)),"") -> 2.384 | U28: =IFERROR(T28*G28,"") -> 2.384 | V28: =IFERROR(AY28/U28,"") -> 150 | AA28: =_xlfn.IFNA(Backend!AO33,"") | AB28: =Backend!AP33 | AC28: =Backend!AQ33 | AD28: =Backend!AR33 | AE28: =Backend!AS33 | AF28: =Backend!AT33 | AG28: =Backend!AU33 | AH28: =Backend!AV33 | AI28: =Backend!AW33 | ... AV28: =Backend!BJ33 | AW28: =_xlfn.IFNA(Backend!O33,"") | AX28: =_xlfn.IFNA(IF(D28="","",Backend!BK33),"") -> 357.6 | AY28: =IF(AX28="","",AX28*G28) -> 357.6
A29: 27 | B29: =B28 -> FWR10000 | C29: 3 | D29: H 157 01 270 A Inner Roller set | F29: Inner Roller set | G29: 1 | H29: Sheet Metal-B | I29: Inhouse | J29: LPP-Thumbrule | K29: =_xlfn.IFNA(Backend!AN34,"") -> 428.55 | L29: =IFERROR(AA29,"") | M29: =IFERROR(AW29,"") | N29: =IF(SUM(AB29:AS29)=0,"",SUM(AB29:AS29)) | O29: =IF(SUM(AT29:AV29)=0,"",SUM(AT29:AV29)) | P29: =IF(K29="","",SUM(K29:O29)) -> 428.55 | Q29: =IF(P29="","",P29*G29) -> 428.55 | T29: =_xlfn.IFNA(IF(VLOOKUP(D29,Group!C:I,7,0)=0,"",VLOOKUP(D29,Group!C:I,7,0)),"") -> 2.857 | U29: =IFERROR(T29*G29,"") -> 2.857 | V29: =IFERROR(AY29/U29,"") -> 150 | AA29: =_xlfn.IFNA(Backend!AO34,"") | AB29: =Backend!AP34 | AC29: =Backend!AQ34 | AD29: =Backend!AR34 | AE29: =Backend!AS34 | AF29: =Backend!AT34 | AG29: =Backend!AU34 | AH29: =Backend!AV34 | AI29: =Backend!AW34 | ... AV29: =Backend!BJ34 | AW29: =_xlfn.IFNA(Backend!O34,"") | AX29: =_xlfn.IFNA(IF(D29="","",Backend!BK34),"") -> 428.55 | AY29: =IF(AX29="","",AX29*G29) -> 428.55
A30: 28 | B30: =B29 -> FWR10000 | C30: 3 | D30: H 157 01 270 A Outer Roller Bearing case | F30: Outer Roller Bearing case | G30: 2 | H30: Injection Moulding | I30: BOF | J30: CSC | K30: =_xlfn.IFNA(Backend!AN35,"") -> 13.29261 | L30: =IFERROR(AA30,"") | M30: =IFERROR(AW30,"") | N30: =IF(SUM(AB30:AS30)=0,"",SUM(AB30:AS30)) -> 0.69786 | O30: =IF(SUM(AT30:AV30)=0,"",SUM(AT30:AV30)) -> 1.19633 | P30: =IF(K30="","",SUM(K30:O30)) -> 15.1868 | Q30: =IF(P30="","",P30*G30) -> 30.3736 | T30: =_xlfn.IFNA(IF(VLOOKUP(D30,Group!C:I,7,0)=0,"",VLOOKUP(D30,Group!C:I,7,0)),"") -> 0.02 | U30: =IFERROR(T30*G30,"") -> 0.04 | V30: =IFERROR(AY30/U30,"") -> 759.34 | AA30: =_xlfn.IFNA(Backend!AO35,"") | AB30: =Backend!AP35 | AC30: =Backend!AQ35 | AD30: =Backend!AR35 -> 0.29908 | AE30: =Backend!AS35 | AF30: =Backend!AT35 | AG30: =Backend!AU35 -> 0.39878 | AH30: =Backend!AV35 | AI30: =Backend!AW35 | ... AV30: =Backend!BJ35 -> 1.19633 | AW30: =_xlfn.IFNA(Backend!O35,"") | AX30: =_xlfn.IFNA(IF(D30="","",Backend!BK35),"") -> 15.1868 | AY30: =IF(AX30="","",AX30*G30) -> 30.3736
A31: 29 | B31: =B30 -> FWR10000 | C31: 3 | D31: H 157 01 270 A Outer Roller Wheel | F31: Outer Roller Wheel | G31: 2 | H31: Injection Moulding | I31: BOF | J31: CSC | K31: =_xlfn.IFNA(Backend!AN36,"") -> 8.62449 | L31: =IFERROR(AA31,"") | M31: =IFERROR(AW31,"") | N31: =IF(SUM(AB31:AS31)=0,"",SUM(AB31:AS31)) -> 0.45278 | O31: =IF(SUM(AT31:AV31)=0,"",SUM(AT31:AV31)) -> 0.7762 | P31: =IF(K31="","",SUM(K31:O31)) -> 9.85347 | Q31: =IF(P31="","",P31*G31) -> 19.70694 | T31: =_xlfn.IFNA(IF(VLOOKUP(D31,Group!C:I,7,0)=0,"",VLOOKUP(D31,Group!C:I,7,0)),"") -> 0.012 | U31: =IFERROR(T31*G31,"") -> 0.024 | V31: =IFERROR(AY31/U31,"") -> 821.1225 | AA31: =_xlfn.IFNA(Backend!AO36,"") | AB31: =Backend!AP36 | AC31: =Backend!AQ36 | AD31: =Backend!AR36 -> 0.19405 | AE31: =Backend!AS36 | AF31: =Backend!AT36 | AG31: =Backend!AU36 -> 0.25873 | AH31: =Backend!AV36 | AI31: =Backend!AW36 | ... AV31: =Backend!BJ36 -> 0.7762 | AW31: =_xlfn.IFNA(Backend!O36,"") | AX31: =_xlfn.IFNA(IF(D31="","",Backend!BK36),"") -> 9.85347 | AY31: =IF(AX31="","",AX31*G31) -> 19.70694
A32: 30 | B32: =B31 -> FWR10000 | C32: 3 | D32: H 157 01 270 A Inner Roller Bearing case | F32: Inner Roller Bearing case | G32: 2 | H32: Injection Moulding | I32: BOF | J32: CSC | K32: =_xlfn.IFNA(Backend!AN37,"") -> 31.69207 | L32: =IFERROR(AA32,"") | M32: =IFERROR(AW32,"") | N32: =IF(SUM(AB32:AS32)=0,"",SUM(AB32:AS32)) -> 1.66383 | O32: =IF(SUM(AT32:AV32)=0,"",SUM(AT32:AV32)) -> 2.85229 | P32: =IF(K32="","",SUM(K32:O32)) -> 36.20819 | Q32: =IF(P32="","",P32*G32) -> 72.41638 | T32: =_xlfn.IFNA(IF(VLOOKUP(D32,Group!C:I,7,0)=0,"",VLOOKUP(D32,Group!C:I,7,0)),"") -> 0.052 | U32: =IFERROR(T32*G32,"") -> 0.104 | V32: =IFERROR(AY32/U32,"") -> 696.31135 | AA32: =_xlfn.IFNA(Backend!AO37,"") | AB32: =Backend!AP37 | AC32: =Backend!AQ37 | AD32: =Backend!AR37 -> 0.71307 | AE32: =Backend!AS37 | AF32: =Backend!AT37 | AG32: =Backend!AU37 -> 0.95076 | AH32: =Backend!AV37 | AI32: =Backend!AW37 | ... AV32: =Backend!BJ37 -> 2.85229 | AW32: =_xlfn.IFNA(Backend!O37,"") | AX32: =_xlfn.IFNA(IF(D32="","",Backend!BK37),"") -> 36.20819 | AY32: =IF(AX32="","",AX32*G32) -> 72.41638
A33: 31 | B33: =B32 -> FWR10000 | C33: 3 | D33: H 157 01 270 A Inner Roller Wheel | F33: Inner Roller Wheel | G33: 2 | H33: Injection Moulding | I33: BOF | J33: CSC | K33: =_xlfn.IFNA(Backend!AN38,"") -> 8.62449 | L33: =IFERROR(AA33,"") | M33: =IFERROR(AW33,"") | N33: =IF(SUM(AB33:AS33)=0,"",SUM(AB33:AS33)) -> 0.45278 | O33: =IF(SUM(AT33:AV33)=0,"",SUM(AT33:AV33)) -> 0.7762 | P33: =IF(K33="","",SUM(K33:O33)) -> 9.85347 | Q33: =IF(P33="","",P33*G33) -> 19.70694 | T33: =_xlfn.IFNA(IF(VLOOKUP(D33,Group!C:I,7,0)=0,"",VLOOKUP(D33,Group!C:I,7,0)),"") -> 0.012 | U33: =IFERROR(T33*G33,"") -> 0.024 | V33: =IFERROR(AY33/U33,"") -> 821.1225 | AA33: =_xlfn.IFNA(Backend!AO38,"") | AB33: =Backend!AP38 | AC33: =Backend!AQ38 | AD33: =Backend!AR38 -> 0.19405 | AE33: =Backend!AS38 | AF33: =Backend!AT38 | AG33: =Backend!AU38 -> 0.25873 | AH33: =Backend!AV38 | AI33: =Backend!AW38 | ... AV33: =Backend!BJ38 -> 0.7762 | AW33: =_xlfn.IFNA(Backend!O38,"") | AX33: =_xlfn.IFNA(IF(D33="","",Backend!BK38),"") -> 9.85347 | AY33: =IF(AX33="","",AX33*G33) -> 19.70694
A34: 32 | B34: =B33 -> FWR10000 | C34: 3 | D34: H 157 01 270 A Rail Brkt Front | F34: Rail Brkt Front | G34: 1 | H34: Sheet Metal-B | I34: Inhouse | J34: LPP-Thumbrule | K34: =_xlfn.IFNA(Backend!AN39,"") -> 361.95 | L34: =IFERROR(AA34,"") | M34: =IFERROR(AW34,"") | N34: =IF(SUM(AB34:AS34)=0,"",SUM(AB34:AS34)) | O34: =IF(SUM(AT34:AV34)=0,"",SUM(AT34:AV34)) | P34: =IF(K34="","",SUM(K34:O34)) -> 361.95 | Q34: =IF(P34="","",P34*G34) -> 361.95 | T34: =_xlfn.IFNA(IF(VLOOKUP(D34,Group!C:I,7,0)=0,"",VLOOKUP(D34,Group!C:I,7,0)),"") -> 2.413 | U34: =IFERROR(T34*G34,"") -> 2.413 | V34: =IFERROR(AY34/U34,"") -> 150 | AA34: =_xlfn.IFNA(Backend!AO39,"") | AB34: =Backend!AP39 | AC34: =Backend!AQ39 | AD34: =Backend!AR39 | AE34: =Backend!AS39 | AF34: =Backend!AT39 | AG34: =Backend!AU39 | AH34: =Backend!AV39 | AI34: =Backend!AW39 | ... AV34: =Backend!BJ39 | AW34: =_xlfn.IFNA(Backend!O39,"") | AX34: =_xlfn.IFNA(IF(D34="","",Backend!BK39),"") -> 361.95 | AY34: =IF(AX34="","",AX34*G34) -> 361.95
A35: 33 | B35: =B34 -> FWR10000 | C35: 3 | D35: H 157 01 270 A Rail Brkt Rear | F35: Rail Brkt Rear | G35: 1 | H35: Sheet Metal-B | I35: Inhouse | J35: LPP-Thumbrule | K35: =_xlfn.IFNA(Backend!AN40,"") -> 154.2 | L35: =IFERROR(AA35,"") | M35: =IFERROR(AW35,"") | N35: =IF(SUM(AB35:AS35)=0,"",SUM(AB35:AS35)) | O35: =IF(SUM(AT35:AV35)=0,"",SUM(AT35:AV35)) | P35: =IF(K35="","",SUM(K35:O35)) -> 154.2 | Q35: =IF(P35="","",P35*G35) -> 154.2 | T35: =_xlfn.IFNA(IF(VLOOKUP(D35,Group!C:I,7,0)=0,"",VLOOKUP(D35,Group!C:I,7,0)),"") -> 1.028 | U35: =IFERROR(T35*G35,"") -> 1.028 | V35: =IFERROR(AY35/U35,"") -> 150 | AA35: =_xlfn.IFNA(Backend!AO40,"") | AB35: =Backend!AP40 | AC35: =Backend!AQ40 | AD35: =Backend!AR40 | AE35: =Backend!AS40 | AF35: =Backend!AT40 | AG35: =Backend!AU40 | AH35: =Backend!AV40 | AI35: =Backend!AW40 | ... AV35: =Backend!BJ40 | AW35: =_xlfn.IFNA(Backend!O40,"") | AX35: =_xlfn.IFNA(IF(D35="","",Backend!BK40),"") -> 154.2 | AY35: =IF(AX35="","",AX35*G35) -> 154.2
A36: 34 | B36: =B35 -> FWR10000 | C36: 3 | D36: H 157 01 270 A Bellow | F36: Bellow | G36: 1 | H36: Compression Moulding | I36: BOF | J36: CSC | K36: =_xlfn.IFNA(Backend!AN41,"") -> 519.25848 | L36: =IFERROR(AA36,"") | M36: =IFERROR(AW36,"") | N36: =IF(SUM(AB36:AS36)=0,"",SUM(AB36:AS36)) | O36: =IF(SUM(AT36:AV36)=0,"",SUM(AT36:AV36)) | P36: =IF(K36="","",SUM(K36:O36)) -> 519.25848 | Q36: =IF(P36="","",P36*G36) -> 519.25848 | T36: =_xlfn.IFNA(IF(VLOOKUP(D36,Group!C:I,7,0)=0,"",VLOOKUP(D36,Group!C:I,7,0)),"") -> 1.536 | U36: =IFERROR(T36*G36,"") -> 1.536 | V36: =IFERROR(AY36/U36,"") -> 338.05891 | AA36: =_xlfn.IFNA(Backend!AO41,"") | AB36: =Backend!AP41 | AC36: =Backend!AQ41 | AD36: =Backend!AR41 -> 0 | AE36: =Backend!AS41 | AF36: =Backend!AT41 | AG36: =Backend!AU41 -> 0 | AH36: =Backend!AV41 | AI36: =Backend!AW41 | ... AV36: =Backend!BJ41 -> 0 | AW36: =_xlfn.IFNA(Backend!O41,"") | AX36: =_xlfn.IFNA(IF(D36="","",Backend!BK41),"") -> 519.25848 | AY36: =IF(AX36="","",AX36*G36) -> 519.25848
A37: 35 | B37: =B36 -> FWR10000 | C37: 3 | D37: H 157 01 270 A M8*20 Screw Hex socket head | F37: M8*20 Screw Hex socket head | G37: 4 | H37: Sheet Metal-B | I37: BOF | J37: Reference | K37: =_xlfn.IFNA(Backend!AN42,"") -> 3.42 | L37: =IFERROR(AA37,"") | M37: =IFERROR(AW37,"") | N37: =IF(SUM(AB37:AS37)=0,"",SUM(AB37:AS37)) -> 0.0684 | O37: =IF(SUM(AT37:AV37)=0,"",SUM(AT37:AV37)) -> 0.1026 | P37: =IF(K37="","",SUM(K37:O37)) -> 3.591 | Q37: =IF(P37="","",P37*G37) -> 14.364 | T37: =_xlfn.IFNA(IF(VLOOKUP(D37,Group!C:I,7,0)=0,"",VLOOKUP(D37,Group!C:I,7,0)),"") | U37: =IFERROR(T37*G37,"") | V37: =IFERROR(AY37/U37,"") | AA37: =_xlfn.IFNA(Backend!AO42,"") | AB37: =Backend!AP42 | AC37: =Backend!AQ42 | AD37: =Backend!AR42 -> 0.0513 | AE37: =Backend!AS42 | AF37: =Backend!AT42 | AG37: =Backend!AU42 -> 0.0171 | AH37: =Backend!AV42 | AI37: =Backend!AW42 | ... AV37: =Backend!BJ42 -> 0.1026 | AW37: =_xlfn.IFNA(Backend!O42,"") | AX37: =_xlfn.IFNA(IF(D37="","",Backend!BK42),"") -> 3.591 | AY37: =IF(AX37="","",AX37*G37) -> 14.364
A38: 36 | B38: =B37 -> FWR10000 | C38: 3 | D38: H 157 01 270 A Bellow MtG Srip | F38: Bellow MtG Srip | G38: 1 | H38: Sheet Metal-B | I38: Inhouse | J38: LPP-Thumbrule | K38: =_xlfn.IFNA(Backend!AN43,"") -> 4.5 | L38: =IFERROR(AA38,"") | M38: =IFERROR(AW38,"") | N38: =IF(SUM(AB38:AS38)=0,"",SUM(AB38:AS38)) | O38: =IF(SUM(AT38:AV38)=0,"",SUM(AT38:AV38)) | P38: =IF(K38="","",SUM(K38:O38)) -> 4.5 | Q38: =IF(P38="","",P38*G38) -> 4.5 | T38: =_xlfn.IFNA(IF(VLOOKUP(D38,Group!C:I,7,0)=0,"",VLOOKUP(D38,Group!C:I,7,0)),"") -> 0.03 | U38: =IFERROR(T38*G38,"") -> 0.03 | V38: =IFERROR(AY38/U38,"") -> 150 | AA38: =_xlfn.IFNA(Backend!AO43,"") | AB38: =Backend!AP43 | AC38: =Backend!AQ43 | AD38: =Backend!AR43 | AE38: =Backend!AS43 | AF38: =Backend!AT43 | AG38: =Backend!AU43 | AH38: =Backend!AV43 | AI38: =Backend!AW43 | ... AV38: =Backend!BJ43 | AW38: =_xlfn.IFNA(Backend!O43,"") | AX38: =_xlfn.IFNA(IF(D38="","",Backend!BK43),"") -> 4.5 | AY38: =IF(AX38="","",AX38*G38) -> 4.5
A39: 37 | B39: =B38 -> FWR10000 | C39: 2 | D39: L 122 19 009 Q | E39: 7 | F39: Switch - Pneumatic height adj | G39: 1 | K39: =_xlfn.IFNA(Backend!AN44,"") | L39: =IFERROR(AA39,"") | M39: =IFERROR(AW39,"") | N39: =IF(SUM(AB39:AS39)=0,"",SUM(AB39:AS39)) | O39: =IF(SUM(AT39:AV39)=0,"",SUM(AT39:AV39)) | P39: =IF(K39="","",SUM(K39:O39)) | Q39: =IF(P39="","",P39*G39) | T39: =_xlfn.IFNA(IF(VLOOKUP(D39,Group!C:I,7,0)=0,"",VLOOKUP(D39,Group!C:I,7,0)),"") | U39: =IFERROR(T39*G39,"") | V39: =IFERROR(AY39/U39,"") | AA39: =_xlfn.IFNA(Backend!AO44,"") | AB39: =Backend!AP44 | AC39: =Backend!AQ44 | AD39: =Backend!AR44 | AE39: =Backend!AS44 | AF39: =Backend!AT44 | AG39: =Backend!AU44 | AH39: =Backend!AV44 | AI39: =Backend!AW44 | ... AV39: =Backend!BJ44 | AW39: =_xlfn.IFNA(Backend!O44,"") | AX39: =_xlfn.IFNA(IF(D39="","",Backend!BK44),"") -> 0 | AY39: =IF(AX39="","",AX39*G39) -> 0
A40: 38 | B40: =B39 -> FWR10000 | C40: 2 | D40: H 157 01 466 P | E40: 4 | F40: Side valance cover RH | G40: 1 | H40: Injection Moulding | I40: BOF | J40: CSC | K40: =_xlfn.IFNA(Backend!AN45,"") -> 49.9855 | L40: =IFERROR(AA40,"") | M40: =IFERROR(AW40,"") | N40: =IF(SUM(AB40:AS40)=0,"",SUM(AB40:AS40)) -> 2.62423 | O40: =IF(SUM(AT40:AV40)=0,"",SUM(AT40:AV40)) -> 4.49869 | P40: =IF(K40="","",SUM(K40:O40)) -> 57.10842 | Q40: =IF(P40="","",P40*G40) -> 57.10842 | T40: =_xlfn.IFNA(IF(VLOOKUP(D40,Group!C:I,7,0)=0,"",VLOOKUP(D40,Group!C:I,7,0)),"") -> 0.3 | U40: =IFERROR(T40*G40,"") -> 0.3 | V40: =IFERROR(AY40/U40,"") -> 190.3614 | AA40: =_xlfn.IFNA(Backend!AO45,"") | AB40: =Backend!AP45 | AC40: =Backend!AQ45 | AD40: =Backend!AR45 -> 1.12467 | AE40: =Backend!AS45 | AF40: =Backend!AT45 | AG40: =Backend!AU45 -> 1.49956 | AH40: =Backend!AV45 | AI40: =Backend!AW45 | ... AV40: =Backend!BJ45 -> 4.49869 | AW40: =_xlfn.IFNA(Backend!O45,"") | AX40: =_xlfn.IFNA(IF(D40="","",Backend!BK45),"") -> 57.10842 | AY40: =IF(AX40="","",AX40*G40) -> 57.10842
A41: 39 | B41: =B40 -> FWR10000 | C41: 2 | D41: H 157 01 467 P | E41: 5 | F41: Side valance cover LH | G41: 1 | H41: Injection Moulding | I41: BOF | J41: CSC | K41: =_xlfn.IFNA(Backend!AN46,"") -> 49.9855 | L41: =IFERROR(AA41,"") | M41: =IFERROR(AW41,"") | N41: =IF(SUM(AB41:AS41)=0,"",SUM(AB41:AS41)) -> 2.62423 | O41: =IF(SUM(AT41:AV41)=0,"",SUM(AT41:AV41)) -> 4.49869 | P41: =IF(K41="","",SUM(K41:O41)) -> 57.10842 | Q41: =IF(P41="","",P41*G41) -> 57.10842 | T41: =_xlfn.IFNA(IF(VLOOKUP(D41,Group!C:I,7,0)=0,"",VLOOKUP(D41,Group!C:I,7,0)),"") -> 0.3 | U41: =IFERROR(T41*G41,"") -> 0.3 | V41: =IFERROR(AY41/U41,"") -> 190.3614 | AA41: =_xlfn.IFNA(Backend!AO46,"") | AB41: =Backend!AP46 | AC41: =Backend!AQ46 | AD41: =Backend!AR46 -> 1.12467 | AE41: =Backend!AS46 | AF41: =Backend!AT46 | AG41: =Backend!AU46 -> 1.49956 | AH41: =Backend!AV46 | AI41: =Backend!AW46 | ... AV41: =Backend!BJ46 -> 4.49869 | AW41: =_xlfn.IFNA(Backend!O46,"") | AX41: =_xlfn.IFNA(IF(D41="","",Backend!BK46),"") -> 57.10842 | AY41: =IF(AX41="","",AX41*G41) -> 57.10842
A42: 40 | B42: =B41 -> FWR10000 | C42: 2 | D42: H 157 01 142 P | E42: 6 | F42: Front cover | G42: 1 | H42: Injection Moulding | I42: BOF | J42: CSC | K42: =_xlfn.IFNA(Backend!AN47,"") -> 13.10595 | L42: =IFERROR(AA42,"") | M42: =IFERROR(AW42,"") | N42: =IF(SUM(AB42:AS42)=0,"",SUM(AB42:AS42)) -> 0.68806 | O42: =IF(SUM(AT42:AV42)=0,"",SUM(AT42:AV42)) -> 1.17954 | P42: =IF(K42="","",SUM(K42:O42)) -> 14.97355 | Q42: =IF(P42="","",P42*G42) -> 14.97355 | T42: =_xlfn.IFNA(IF(VLOOKUP(D42,Group!C:I,7,0)=0,"",VLOOKUP(D42,Group!C:I,7,0)),"") -> 0.072 | U42: =IFERROR(T42*G42,"") -> 0.072 | V42: =IFERROR(AY42/U42,"") -> 207.96597 | AA42: =_xlfn.IFNA(Backend!AO47,"") | AB42: =Backend!AP47 | AC42: =Backend!AQ47 | AD42: =Backend!AR47 -> 0.29488 | AE42: =Backend!AS47 | AF42: =Backend!AT47 | AG42: =Backend!AU47 -> 0.39318 | AH42: =Backend!AV47 | AI42: =Backend!AW47 | ... AV42: =Backend!BJ47 -> 1.17954 | AW42: =_xlfn.IFNA(Backend!O47,"") | AX42: =_xlfn.IFNA(IF(D42="","",Backend!BK47),"") -> 14.97355 | AY42: =IF(AX42="","",AX42*G42) -> 14.97355
A43: 41 | B43: =B42 -> FWR10000 | C43: 2 | D43: H 157 01 468 P | E43: 8 | F43: Recliner handle | G43: 1 | H43: Injection Moulding | I43: BOF | J43: CSC | K43: =_xlfn.IFNA(Backend!AN48,"") -> 12.1023 | L43: =IFERROR(AA43,"") | M43: =IFERROR(AW43,"") | N43: =IF(SUM(AB43:AS43)=0,"",SUM(AB43:AS43)) -> 0.63537 | O43: =IF(SUM(AT43:AV43)=0,"",SUM(AT43:AV43)) -> 1.08921 | P43: =IF(K43="","",SUM(K43:O43)) -> 13.82688 | Q43: =IF(P43="","",P43*G43) -> 13.82688 | T43: =_xlfn.IFNA(IF(VLOOKUP(D43,Group!C:I,7,0)=0,"",VLOOKUP(D43,Group!C:I,7,0)),"") -> 0.038 | U43: =IFERROR(T43*G43,"") -> 0.038 | V43: =IFERROR(AY43/U43,"") -> 363.86526 | AA43: =_xlfn.IFNA(Backend!AO48,"") | AB43: =Backend!AP48 | AC43: =Backend!AQ48 | AD43: =Backend!AR48 -> 0.2723 | AE43: =Backend!AS48 | AF43: =Backend!AT48 | AG43: =Backend!AU48 -> 0.36307 | AH43: =Backend!AV48 | AI43: =Backend!AW48 | ... AV43: =Backend!BJ48 -> 1.08921 | AW43: =_xlfn.IFNA(Backend!O48,"") | AX43: =_xlfn.IFNA(IF(D43="","",Backend!BK48),"") -> 13.82688 | AY43: =IF(AX43="","",AX43*G43) -> 13.82688
A44: 42 | B44: =B43 -> FWR10000 | C44: 2 | D44: H 157 01 014 D | E44: 9 | F44: ASSY Backrest complete | G44: 1 | H44: Sheet Metal-B | I44: Inhouse | J44: LPP-Thumbrule | K44: =_xlfn.IFNA(Backend!AN49,"") -> 1030.05 | L44: =IFERROR(AA44,"") | M44: =IFERROR(AW44,"") | N44: =IF(SUM(AB44:AS44)=0,"",SUM(AB44:AS44)) | O44: =IF(SUM(AT44:AV44)=0,"",SUM(AT44:AV44)) | P44: =IF(K44="","",SUM(K44:O44)) -> 1030.05 | Q44: =IF(P44="","",P44*G44) -> 1030.05 | T44: =_xlfn.IFNA(IF(VLOOKUP(D44,Group!C:I,7,0)=0,"",VLOOKUP(D44,Group!C:I,7,0)),"") -> 6.867 | U44: =IFERROR(T44*G44,"") -> 6.867 | V44: =IFERROR(AY44/U44,"") -> 150 | AA44: =_xlfn.IFNA(Backend!AO49,"") | AB44: =Backend!AP49 | AC44: =Backend!AQ49 | AD44: =Backend!AR49 | AE44: =Backend!AS49 | AF44: =Backend!AT49 | AG44: =Backend!AU49 | AH44: =Backend!AV49 | AI44: =Backend!AW49 | ... AV44: =Backend!BJ49 | AW44: =_xlfn.IFNA(Backend!O49,"") | AX44: =_xlfn.IFNA(IF(D44="","",Backend!BK49),"") -> 1030.05 | AY44: =IF(AX44="","",AX44*G44) -> 1030.05
A45: 43 | B45: =B44 -> FWR10000 | C45: 2 | D45: H 157 01 473 D | E45: 10 | F45: ASSY seat base frame | G45: 1 | H45: Sheet Metal-B | I45: Inhouse | J45: LPP-Thumbrule | K45: =_xlfn.IFNA(Backend!AN50,"") -> 603.45 | L45: =IFERROR(AA45,"") | M45: =IFERROR(AW45,"") | N45: =IF(SUM(AB45:AS45)=0,"",SUM(AB45:AS45)) | O45: =IF(SUM(AT45:AV45)=0,"",SUM(AT45:AV45)) | P45: =IF(K45="","",SUM(K45:O45)) -> 603.45 | Q45: =IF(P45="","",P45*G45) -> 603.45 | T45: =_xlfn.IFNA(IF(VLOOKUP(D45,Group!C:I,7,0)=0,"",VLOOKUP(D45,Group!C:I,7,0)),"") -> 4.023 | U45: =IFERROR(T45*G45,"") -> 4.023 | V45: =IFERROR(AY45/U45,"") -> 150 | AA45: =_xlfn.IFNA(Backend!AO50,"") | AB45: =Backend!AP50 | AC45: =Backend!AQ50 | AD45: =Backend!AR50 | AE45: =Backend!AS50 | AF45: =Backend!AT50 | AG45: =Backend!AU50 | AH45: =Backend!AV50 | AI45: =Backend!AW50 | ... AV45: =Backend!BJ50 | AW45: =_xlfn.IFNA(Backend!O50,"") | AX45: =_xlfn.IFNA(IF(D45="","",Backend!BK50),"") -> 603.45 | AY45: =IF(AX45="","",AX45*G45) -> 603.45
A46: 44 | B46: =B45 -> FWR10000 | C46: 2 | D46: H 157 01 414 W | E46: 11 | F46: Sprial Spring 30deg | G46: 2 | H46: Sheet Metal-B | I46: Inhouse | J46: LPP-Thumbrule | K46: =_xlfn.IFNA(Backend!AN51,"") -> 10.35 | L46: =IFERROR(AA46,"") | M46: =IFERROR(AW46,"") | N46: =IF(SUM(AB46:AS46)=0,"",SUM(AB46:AS46)) | O46: =IF(SUM(AT46:AV46)=0,"",SUM(AT46:AV46)) | P46: =IF(K46="","",SUM(K46:O46)) -> 10.35 | Q46: =IF(P46="","",P46*G46) -> 20.7 | T46: =_xlfn.IFNA(IF(VLOOKUP(D46,Group!C:I,7,0)=0,"",VLOOKUP(D46,Group!C:I,7,0)),"") -> 0.069 | U46: =IFERROR(T46*G46,"") -> 0.138 | V46: =IFERROR(AY46/U46,"") -> 150 | AA46: =_xlfn.IFNA(Backend!AO51,"") | AB46: =Backend!AP51 | AC46: =Backend!AQ51 | AD46: =Backend!AR51 | AE46: =Backend!AS51 | AF46: =Backend!AT51 | AG46: =Backend!AU51 | AH46: =Backend!AV51 | AI46: =Backend!AW51 | ... AV46: =Backend!BJ51 | AW46: =_xlfn.IFNA(Backend!O51,"") | AX46: =_xlfn.IFNA(IF(D46="","",Backend!BK51),"") -> 10.35 | AY46: =IF(AX46="","",AX46*G46) -> 20.7
A47: 45 | B47: =B46 -> FWR10000 | C47: 2 | D47: H 157 01 030 P | E47: 12 | F47: Belt exit Guide | G47: 1 | H47: Injection Moulding | I47: BOF | J47: CSC | K47: =_xlfn.IFNA(Backend!AN52,"") -> 0 | L47: =IFERROR(AA47,"") | M47: =IFERROR(AW47,"") | N47: =IF(SUM(AB47:AS47)=0,"",SUM(AB47:AS47)) | O47: =IF(SUM(AT47:AV47)=0,"",SUM(AT47:AV47)) | P47: =IF(K47="","",SUM(K47:O47)) -> 0 | Q47: =IF(P47="","",P47*G47) -> 0 | T47: =_xlfn.IFNA(IF(VLOOKUP(D47,Group!C:I,7,0)=0,"",VLOOKUP(D47,Group!C:I,7,0)),"") | U47: =IFERROR(T47*G47,"") | V47: =IFERROR(AY47/U47,"") | AA47: =_xlfn.IFNA(Backend!AO52,"") | AB47: =Backend!AP52 | AC47: =Backend!AQ52 | AD47: =Backend!AR52 -> 0 | AE47: =Backend!AS52 | AF47: =Backend!AT52 | AG47: =Backend!AU52 -> 0 | AH47: =Backend!AV52 | AI47: =Backend!AW52 | ... AV47: =Backend!BJ52 -> 0 | AW47: =_xlfn.IFNA(Backend!O52,"") | AX47: =_xlfn.IFNA(IF(D47="","",Backend!BK52),"") -> 0 | AY47: =IF(AX47="","",AX47*G47) -> 0
A48: 46 | B48: =B47 -> FWR10000 | C48: 2 | D48: H 157 01 034 S | E48: 18 | F48: SEATBASE PAN | G48: 1 | H48: Sheet Metal-B | I48: Inhouse | J48: LPP-Thumbrule | K48: =_xlfn.IFNA(Backend!AN53,"") -> 273 | L48: =IFERROR(AA48,"") | M48: =IFERROR(AW48,"") | N48: =IF(SUM(AB48:AS48)=0,"",SUM(AB48:AS48)) | O48: =IF(SUM(AT48:AV48)=0,"",SUM(AT48:AV48)) | P48: =IF(K48="","",SUM(K48:O48)) -> 273 | Q48: =IF(P48="","",P48*G48) -> 273 | T48: =_xlfn.IFNA(IF(VLOOKUP(D48,Group!C:I,7,0)=0,"",VLOOKUP(D48,Group!C:I,7,0)),"") -> 1.82 | U48: =IFERROR(T48*G48,"") -> 1.82 | V48: =IFERROR(AY48/U48,"") -> 150 | AA48: =_xlfn.IFNA(Backend!AO53,"") | AB48: =Backend!AP53 | AC48: =Backend!AQ53 | AD48: =Backend!AR53 | AE48: =Backend!AS53 | AF48: =Backend!AT53 | AG48: =Backend!AU53 | AH48: =Backend!AV53 | AI48: =Backend!AW53 | ... AV48: =Backend!BJ53 | AW48: =_xlfn.IFNA(Backend!O53,"") | AX48: =_xlfn.IFNA(IF(D48="","",Backend!BK53),"") -> 273 | AY48: =IF(AX48="","",AX48*G48) -> 273
A49: 47 | B49: =B48 -> FWR10000 | C49: 2 | D49: A 176 01 118 F | E49: 22 | F49: M6X10 HD SOC CAP SCREW | G49: 4 | H49: Sheet Metal-B | I49: BOF | J49: Reference | K49: =_xlfn.IFNA(Backend!AN54,"") -> 2.4 | L49: =IFERROR(AA49,"") | M49: =IFERROR(AW49,"") | N49: =IF(SUM(AB49:AS49)=0,"",SUM(AB49:AS49)) -> 0.048 | O49: =IF(SUM(AT49:AV49)=0,"",SUM(AT49:AV49)) -> 0.072 | P49: =IF(K49="","",SUM(K49:O49)) -> 2.52 | Q49: =IF(P49="","",P49*G49) -> 10.08 | T49: =_xlfn.IFNA(IF(VLOOKUP(D49,Group!C:I,7,0)=0,"",VLOOKUP(D49,Group!C:I,7,0)),"") | U49: =IFERROR(T49*G49,"") | V49: =IFERROR(AY49/U49,"") | AA49: =_xlfn.IFNA(Backend!AO54,"") | AB49: =Backend!AP54 | AC49: =Backend!AQ54 | AD49: =Backend!AR54 -> 0.036 | AE49: =Backend!AS54 | AF49: =Backend!AT54 | AG49: =Backend!AU54 -> 0.012 | AH49: =Backend!AV54 | AI49: =Backend!AW54 | ... AV49: =Backend!BJ54 -> 0.072 | AW49: =_xlfn.IFNA(Backend!O54,"") | AX49: =_xlfn.IFNA(IF(D49="","",Backend!BK54),"") -> 2.52 | AY49: =IF(AX49="","",AX49*G49) -> 10.08
A50: 48 | B50: =B49 -> FWR10000 | C50: 2 | D50: H 157 01 053 S | E50: 23 | F50: TETHERING BELT MNT TOP BRKT | G50: 2 | H50: Sheet Metal-B | I50: Inhouse | J50: LPP-Thumbrule | K50: =_xlfn.IFNA(Backend!AN55,"") -> 7.5 | L50: =IFERROR(AA50,"") | M50: =IFERROR(AW50,"") | N50: =IF(SUM(AB50:AS50)=0,"",SUM(AB50:AS50)) | O50: =IF(SUM(AT50:AV50)=0,"",SUM(AT50:AV50)) | P50: =IF(K50="","",SUM(K50:O50)) -> 7.5 | Q50: =IF(P50="","",P50*G50) -> 15 | T50: =_xlfn.IFNA(IF(VLOOKUP(D50,Group!C:I,7,0)=0,"",VLOOKUP(D50,Group!C:I,7,0)),"") -> 0.05 | U50: =IFERROR(T50*G50,"") -> 0.1 | V50: =IFERROR(AY50/U50,"") -> 150 | AA50: =_xlfn.IFNA(Backend!AO55,"") | AB50: =Backend!AP55 | AC50: =Backend!AQ55 | AD50: =Backend!AR55 | AE50: =Backend!AS55 | AF50: =Backend!AT55 | AG50: =Backend!AU55 | AH50: =Backend!AV55 | AI50: =Backend!AW55 | ... AV50: =Backend!BJ55 | AW50: =_xlfn.IFNA(Backend!O55,"") | AX50: =_xlfn.IFNA(IF(D50="","",Backend!BK55),"") -> 7.5 | AY50: =IF(AX50="","",AX50*G50) -> 15
A51: 49 | B51: =B50 -> FWR10000 | C51: 2 | D51: E 171 08 107 F | E51: 25 | F51: M8X20 HEX SOC HD CSK SCREW | G51: 12 | H51: Sheet Metal-B | I51: BOF | J51: Reference | K51: =_xlfn.IFNA(Backend!AN56,"") -> 3.42 | L51: =IFERROR(AA51,"") | M51: =IFERROR(AW51,"") | N51: =IF(SUM(AB51:AS51)=0,"",SUM(AB51:AS51)) -> 0.0684 | O51: =IF(SUM(AT51:AV51)=0,"",SUM(AT51:AV51)) -> 0.1026 | P51: =IF(K51="","",SUM(K51:O51)) -> 3.591 | Q51: =IF(P51="","",P51*G51) -> 43.092 | T51: =_xlfn.IFNA(IF(VLOOKUP(D51,Group!C:I,7,0)=0,"",VLOOKUP(D51,Group!C:I,7,0)),"") | U51: =IFERROR(T51*G51,"") | V51: =IFERROR(AY51/U51,"") | AA51: =_xlfn.IFNA(Backend!AO56,"") | AB51: =Backend!AP56 | AC51: =Backend!AQ56 | AD51: =Backend!AR56 -> 0.0513 | AE51: =Backend!AS56 | AF51: =Backend!AT56 | AG51: =Backend!AU56 -> 0.0171 | AH51: =Backend!AV56 | AI51: =Backend!AW56 | ... AV51: =Backend!BJ56 -> 0.1026 | AW51: =_xlfn.IFNA(Backend!O56,"") | AX51: =_xlfn.IFNA(IF(D51="","",Backend!BK56),"") -> 3.591 | AY51: =IF(AX51="","",AX51*G51) -> 43.092
A52: 50 | B52: =B51 -> FWR10000 | C52: 2 | D52: K 182 19 005 F | E52: 21 | F52: HEX HD BOLT M10X20 - PLATED | G52: 4 | H52: Sheet Metal-B | I52: BOF | J52: Reference | K52: =_xlfn.IFNA(Backend!AN57,"") -> 2.7 | L52: =IFERROR(AA52,"") | M52: =IFERROR(AW52,"") | N52: =IF(SUM(AB52:AS52)=0,"",SUM(AB52:AS52)) -> 0.054 | O52: =IF(SUM(AT52:AV52)=0,"",SUM(AT52:AV52)) -> 0.081 | P52: =IF(K52="","",SUM(K52:O52)) -> 2.835 | Q52: =IF(P52="","",P52*G52) -> 11.34 | T52: =_xlfn.IFNA(IF(VLOOKUP(D52,Group!C:I,7,0)=0,"",VLOOKUP(D52,Group!C:I,7,0)),"") | U52: =IFERROR(T52*G52,"") | V52: =IFERROR(AY52/U52,"") | AA52: =_xlfn.IFNA(Backend!AO57,"") | AB52: =Backend!AP57 | AC52: =Backend!AQ57 | AD52: =Backend!AR57 -> 0.0405 | AE52: =Backend!AS57 | AF52: =Backend!AT57 | AG52: =Backend!AU57 -> 0.0135 | AH52: =Backend!AV57 | AI52: =Backend!AW57 | ... AV52: =Backend!BJ57 -> 0.081 | AW52: =_xlfn.IFNA(Backend!O57,"") | AX52: =_xlfn.IFNA(IF(D52="","",Backend!BK57),"") -> 2.835 | AY52: =IF(AX52="","",AX52*G52) -> 11.34
A53: 51 | B53: =B52 -> FWR10000 | C53: 2 | D53: H 157 01 470 L | E53: 14 | F53: BACKREST CUSION | G53: 1 | K53: =_xlfn.IFNA(Backend!AN58,"") | L53: =IFERROR(AA53,"") | M53: =IFERROR(AW53,"") | N53: =IF(SUM(AB53:AS53)=0,"",SUM(AB53:AS53)) | O53: =IF(SUM(AT53:AV53)=0,"",SUM(AT53:AV53)) | P53: =IF(K53="","",SUM(K53:O53)) | Q53: =IF(P53="","",P53*G53) | T53: =_xlfn.IFNA(IF(VLOOKUP(D53,Group!C:I,7,0)=0,"",VLOOKUP(D53,Group!C:I,7,0)),"") | U53: =IFERROR(T53*G53,"") | V53: =IFERROR(AY53/U53,"") | AA53: =_xlfn.IFNA(Backend!AO58,"") | AB53: =Backend!AP58 | AC53: =Backend!AQ58 | AD53: =Backend!AR58 | AE53: =Backend!AS58 | AF53: =Backend!AT58 | AG53: =Backend!AU58 | AH53: =Backend!AV58 | AI53: =Backend!AW58 | ... AV53: =Backend!BJ58 | AW53: =_xlfn.IFNA(Backend!O58,"") | AX53: =_xlfn.IFNA(IF(D53="","",Backend!BK58),"") -> 0 | AY53: =IF(AX53="","",AX53*G53) -> 0
A54: 52 | B54: =B53 -> FWR10000 | C54: 2 | D54: H 157 01 096 S | E54: 15 | F54: BELT EXIT COVER HOLDER RH | G54: 1 | K54: =_xlfn.IFNA(Backend!AN59,"") | L54: =IFERROR(AA54,"") | M54: =IFERROR(AW54,"") | N54: =IF(SUM(AB54:AS54)=0,"",SUM(AB54:AS54)) | O54: =IF(SUM(AT54:AV54)=0,"",SUM(AT54:AV54)) | P54: =IF(K54="","",SUM(K54:O54)) | Q54: =IF(P54="","",P54*G54) | T54: =_xlfn.IFNA(IF(VLOOKUP(D54,Group!C:I,7,0)=0,"",VLOOKUP(D54,Group!C:I,7,0)),"") | U54: =IFERROR(T54*G54,"") | V54: =IFERROR(AY54/U54,"") | AA54: =_xlfn.IFNA(Backend!AO59,"") | AB54: =Backend!AP59 | AC54: =Backend!AQ59 | AD54: =Backend!AR59 | AE54: =Backend!AS59 | AF54: =Backend!AT59 | AG54: =Backend!AU59 | AH54: =Backend!AV59 | AI54: =Backend!AW59 | ... AV54: =Backend!BJ59 | AW54: =_xlfn.IFNA(Backend!O59,"") | AX54: =_xlfn.IFNA(IF(D54="","",Backend!BK59),"") -> 0 | AY54: =IF(AX54="","",AX54*G54) -> 0
A55: 53 | B55: =B54 -> FWR10000 | C55: 2 | D55: H 157 01 092 P | E55: 16 | F55: BELT EXIT COVER RH | G55: 1 | K55: =_xlfn.IFNA(Backend!AN60,"") | L55: =IFERROR(AA55,"") | M55: =IFERROR(AW55,"") | N55: =IF(SUM(AB55:AS55)=0,"",SUM(AB55:AS55)) | O55: =IF(SUM(AT55:AV55)=0,"",SUM(AT55:AV55)) | P55: =IF(K55="","",SUM(K55:O55)) | Q55: =IF(P55="","",P55*G55) | T55: =_xlfn.IFNA(IF(VLOOKUP(D55,Group!C:I,7,0)=0,"",VLOOKUP(D55,Group!C:I,7,0)),"") | U55: =IFERROR(T55*G55,"") | V55: =IFERROR(AY55/U55,"") | AA55: =_xlfn.IFNA(Backend!AO60,"") | AB55: =Backend!AP60 | AC55: =Backend!AQ60 | AD55: =Backend!AR60 | AE55: =Backend!AS60 | AF55: =Backend!AT60 | AG55: =Backend!AU60 | AH55: =Backend!AV60 | AI55: =Backend!AW60 | ... AV55: =Backend!BJ60 | AW55: =_xlfn.IFNA(Backend!O60,"") | AX55: =_xlfn.IFNA(IF(D55="","",Backend!BK60),"") -> 0 | AY55: =IF(AX55="","",AX55*G55) -> 0
A56: 54 | B56: =B55 -> FWR10000 | C56: 2 | D56: H 157 01 471 L | E56: 17 | F56: SEAT BASE CUSION | G56: 1 | K56: =_xlfn.IFNA(Backend!AN61,"") | L56: =IFERROR(AA56,"") | M56: =IFERROR(AW56,"") | N56: =IF(SUM(AB56:AS56)=0,"",SUM(AB56:AS56)) | O56: =IF(SUM(AT56:AV56)=0,"",SUM(AT56:AV56)) | P56: =IF(K56="","",SUM(K56:O56)) | Q56: =IF(P56="","",P56*G56) | T56: =_xlfn.IFNA(IF(VLOOKUP(D56,Group!C:I,7,0)=0,"",VLOOKUP(D56,Group!C:I,7,0)),"") | U56: =IFERROR(T56*G56,"") | V56: =IFERROR(AY56/U56,"") | AA56: =_xlfn.IFNA(Backend!AO61,"") | AB56: =Backend!AP61 | AC56: =Backend!AQ61 | AD56: =Backend!AR61 | AE56: =Backend!AS61 | AF56: =Backend!AT61 | AG56: =Backend!AU61 | AH56: =Backend!AV61 | AI56: =Backend!AW61 | ... AV56: =Backend!BJ61 | AW56: =_xlfn.IFNA(Backend!O61,"") | AX56: =_xlfn.IFNA(IF(D56="","",Backend!BK61),"") -> 0 | AY56: =IF(AX56="","",AX56*G56) -> 0
A57: 55 | B57: =B56 -> FWR10000 | C57: 2 | D57: H 157 01 034 S | E57: 20 | F57: CARDBOARD BACKREST | G57: 1 | K57: =_xlfn.IFNA(Backend!AN62,"") | L57: =IFERROR(AA57,"") | M57: =IFERROR(AW57,"") | N57: =IF(SUM(AB57:AS57)=0,"",SUM(AB57:AS57)) | O57: =IF(SUM(AT57:AV57)=0,"",SUM(AT57:AV57)) | P57: =IF(K57="","",SUM(K57:O57)) | Q57: =IF(P57="","",P57*G57) | T57: =_xlfn.IFNA(IF(VLOOKUP(D57,Group!C:I,7,0)=0,"",VLOOKUP(D57,Group!C:I,7,0)),"") -> 1.82 | U57: =IFERROR(T57*G57,"") -> 1.82 | V57: =IFERROR(AY57/U57,"") -> 0 | AA57: =_xlfn.IFNA(Backend!AO62,"") | AB57: =Backend!AP62 | AC57: =Backend!AQ62 | AD57: =Backend!AR62 | AE57: =Backend!AS62 | AF57: =Backend!AT62 | AG57: =Backend!AU62 | AH57: =Backend!AV62 | AI57: =Backend!AW62 | ... AV57: =Backend!BJ62 | AW57: =_xlfn.IFNA(Backend!O62,"") | AX57: =_xlfn.IFNA(IF(D57="","",Backend!BK62),"") -> 0 | AY57: =IF(AX57="","",AX57*G57) -> 0
A58: 56 | B58: =B57 -> FWR10000 | C58: 2 | D58: H 157 01 344 U | E58: 24 | F58: TETHER BELT | G58: 2 | K58: =_xlfn.IFNA(Backend!AN63,"") | L58: =IFERROR(AA58,"") | M58: =IFERROR(AW58,"") | N58: =IF(SUM(AB58:AS58)=0,"",SUM(AB58:AS58)) | O58: =IF(SUM(AT58:AV58)=0,"",SUM(AT58:AV58)) | P58: =IF(K58="","",SUM(K58:O58)) | Q58: =IF(P58="","",P58*G58) | T58: =_xlfn.IFNA(IF(VLOOKUP(D58,Group!C:I,7,0)=0,"",VLOOKUP(D58,Group!C:I,7,0)),"") | U58: =IFERROR(T58*G58,"") | V58: =IFERROR(AY58/U58,"") | AA58: =_xlfn.IFNA(Backend!AO63,"") | AB58: =Backend!AP63 | AC58: =Backend!AQ63 | AD58: =Backend!AR63 | AE58: =Backend!AS63 | AF58: =Backend!AT63 | AG58: =Backend!AU63 | AH58: =Backend!AV63 | AI58: =Backend!AW63 | ... AV58: =Backend!BJ63 | AW58: =_xlfn.IFNA(Backend!O63,"") | AX58: =_xlfn.IFNA(IF(D58="","",Backend!BK63),"") -> 0 | AY58: =IF(AX58="","",AX58*G58) -> 0
A59: 57 | B59: =B58 -> FWR10000 | C59: 2 | D59: H 157 01 215 Q | E59: 19 | F59: ASSY SEAT BELT LH PPL | G59: 1 | K59: =_xlfn.IFNA(Backend!AN64,"") | L59: =IFERROR(AA59,"") | M59: =IFERROR(AW59,"") | N59: =IF(SUM(AB59:AS59)=0,"",SUM(AB59:AS59)) | O59: =IF(SUM(AT59:AV59)=0,"",SUM(AT59:AV59)) | P59: =IF(K59="","",SUM(K59:O59)) | Q59: =IF(P59="","",P59*G59) | T59: =_xlfn.IFNA(IF(VLOOKUP(D59,Group!C:I,7,0)=0,"",VLOOKUP(D59,Group!C:I,7,0)),"") | U59: =IFERROR(T59*G59,"") | V59: =IFERROR(AY59/U59,"") | AA59: =_xlfn.IFNA(Backend!AO64,"") | AB59: =Backend!AP64 | AC59: =Backend!AQ64 | AD59: =Backend!AR64 | AE59: =Backend!AS64 | AF59: =Backend!AT64 | AG59: =Backend!AU64 | AH59: =Backend!AV64 | AI59: =Backend!AW64 | ... AV59: =Backend!BJ64 | AW59: =_xlfn.IFNA(Backend!O64,"") | AX59: =_xlfn.IFNA(IF(D59="","",Backend!BK64),"") -> 0 | AY59: =IF(AX59="","",AX59*G59) -> 0
A60: 58 | B60: =B59 -> FWR10000 | C60: 2 | D60: H 157 01 475 U | E60: 26 | F60: BACKREST UPHOLSTERY-VINYL | G60: 1 | K60: =_xlfn.IFNA(Backend!AN65,"") | L60: =IFERROR(AA60,"") | M60: =IFERROR(AW60,"") | N60: =IF(SUM(AB60:AS60)=0,"",SUM(AB60:AS60)) | O60: =IF(SUM(AT60:AV60)=0,"",SUM(AT60:AV60)) | P60: =IF(K60="","",SUM(K60:O60)) | Q60: =IF(P60="","",P60*G60) | T60: =_xlfn.IFNA(IF(VLOOKUP(D60,Group!C:I,7,0)=0,"",VLOOKUP(D60,Group!C:I,7,0)),"") | U60: =IFERROR(T60*G60,"") | V60: =IFERROR(AY60/U60,"") | AA60: =_xlfn.IFNA(Backend!AO65,"") | AB60: =Backend!AP65 | AC60: =Backend!AQ65 | AD60: =Backend!AR65 | AE60: =Backend!AS65 | AF60: =Backend!AT65 | AG60: =Backend!AU65 | AH60: =Backend!AV65 | AI60: =Backend!AW65 | ... AV60: =Backend!BJ65 | AW60: =_xlfn.IFNA(Backend!O65,"") | AX60: =_xlfn.IFNA(IF(D60="","",Backend!BK65),"") -> 0 | AY60: =IF(AX60="","",AX60*G60) -> 0
A61: 59 | B61: =B60 -> FWR10000 | C61: 2 | D61: H 157 01 476 U | E61: 27 | F61: SEATBASE UPHOLSTERY-VINYL | G61: 1 | H61: Castings | K61: =_xlfn.IFNA(Backend!AN66,"") | L61: =IFERROR(AA61,"") | M61: =IFERROR(AW61,"") | N61: =IF(SUM(AB61:AS61)=0,"",SUM(AB61:AS61)) | O61: =IF(SUM(AT61:AV61)=0,"",SUM(AT61:AV61)) | P61: =IF(K61="","",SUM(K61:O61)) | Q61: =IF(P61="","",P61*G61) | T61: =_xlfn.IFNA(IF(VLOOKUP(D61,Group!C:I,7,0)=0,"",VLOOKUP(D61,Group!C:I,7,0)),"") | U61: =IFERROR(T61*G61,"") | V61: =IFERROR(AY61/U61,"") | AA61: =_xlfn.IFNA(Backend!AO66,"") | AB61: =Backend!AP66 | AC61: =Backend!AQ66 | AD61: =Backend!AR66 | AE61: =Backend!AS66 | AF61: =Backend!AT66 | AG61: =Backend!AU66 | AH61: =Backend!AV66 | AI61: =Backend!AW66 | ... AV61: =Backend!BJ66 | AW61: =_xlfn.IFNA(Backend!O66,"") | AX61: =_xlfn.IFNA(IF(D61="","",Backend!BK66),"") -> 0 | AY61: =IF(AX61="","",AX61*G61) -> 0
A62: 60 | B62: =B61 -> FWR10000 | K62: =_xlfn.IFNA(Backend!AN67,"") | L62: =IFERROR(AA62,"") | M62: =IFERROR(AW62,"") | N62: =IF(SUM(AB62:AS62)=0,"",SUM(AB62:AS62)) | O62: =IF(SUM(AT62:AV62)=0,"",SUM(AT62:AV62)) | P62: =IF(K62="","",SUM(K62:O62)) | Q62: =IF(P62="","",P62*G62) | T62: =_xlfn.IFNA(IF(VLOOKUP(D62,Group!C:I,7,0)=0,"",VLOOKUP(D62,Group!C:I,7,0)),"") | U62: =IFERROR(T62*G62,"") | V62: =IFERROR(AY62/U62,"") | AA62: =_xlfn.IFNA(Backend!AO67,"") | AB62: =Backend!AP67 | AC62: =Backend!AQ67 | AD62: =Backend!AR67 | AE62: =Backend!AS67 | AF62: =Backend!AT67 | AG62: =Backend!AU67 | AH62: =Backend!AV67 | AI62: =Backend!AW67 | ... AV62: =Backend!BJ67 | AW62: =_xlfn.IFNA(Backend!O67,"") | AX62: =_xlfn.IFNA(IF(D62="","",Backend!BK67),"") | AY62: =IF(AX62="","",AX62*G62)
A63: 61 | B63: =B62 -> FWR10000 | K63: =_xlfn.IFNA(Backend!AN68,"") | L63: =IFERROR(AA63,"") | M63: =IFERROR(AW63,"") | N63: =IF(SUM(AB63:AS63)=0,"",SUM(AB63:AS63)) | O63: =IF(SUM(AT63:AV63)=0,"",SUM(AT63:AV63)) | P63: =IF(K63="","",SUM(K63:O63)) | Q63: =IF(P63="","",P63*G63) | T63: =_xlfn.IFNA(IF(VLOOKUP(D63,Group!C:I,7,0)=0,"",VLOOKUP(D63,Group!C:I,7,0)),"") | U63: =IFERROR(T63*G63,"") | V63: =IFERROR(AY63/U63,"") | AA63: =_xlfn.IFNA(Backend!AO68,"") | AB63: =Backend!AP68 | AC63: =Backend!AQ68 | AD63: =Backend!AR68 | AE63: =Backend!AS68 | AF63: =Backend!AT68 | AG63: =Backend!AU68 | AH63: =Backend!AV68 | AI63: =Backend!AW68 | ... AV63: =Backend!BJ68 | AW63: =_xlfn.IFNA(Backend!O68,"") | AX63: =_xlfn.IFNA(IF(D63="","",Backend!BK68),"") | AY63: =IF(AX63="","",AX63*G63)
A64: 62 | B64: =B63 -> FWR10000 | K64: =_xlfn.IFNA(Backend!AN69,"") | L64: =IFERROR(AA64,"") | M64: =IFERROR(AW64,"") | N64: =IF(SUM(AB64:AS64)=0,"",SUM(AB64:AS64)) | O64: =IF(SUM(AT64:AV64)=0,"",SUM(AT64:AV64)) | P64: =IF(K64="","",SUM(K64:O64)) | Q64: =IF(P64="","",P64*G64) | T64: =_xlfn.IFNA(IF(VLOOKUP(D64,Group!C:I,7,0)=0,"",VLOOKUP(D64,Group!C:I,7,0)),"") | U64: =IFERROR(T64*G64,"") | V64: =IFERROR(AY64/U64,"") | AA64: =_xlfn.IFNA(Backend!AO69,"") | AB64: =Backend!AP69 | AC64: =Backend!AQ69 | AD64: =Backend!AR69 | AE64: =Backend!AS69 | AF64: =Backend!AT69 | AG64: =Backend!AU69 | AH64: =Backend!AV69 | AI64: =Backend!AW69 | ... AV64: =Backend!BJ69 | AW64: =_xlfn.IFNA(Backend!O69,"") | AX64: =_xlfn.IFNA(IF(D64="","",Backend!BK69),"") | AY64: =IF(AX64="","",AX64*G64)
A65: 63 | B65: =B64 -> FWR10000 | K65: =_xlfn.IFNA(Backend!AN70,"") | L65: =IFERROR(AA65,"") | M65: =IFERROR(AW65,"") | N65: =IF(SUM(AB65:AS65)=0,"",SUM(AB65:AS65)) | O65: =IF(SUM(AT65:AV65)=0,"",SUM(AT65:AV65)) | P65: =IF(K65="","",SUM(K65:O65)) | Q65: =IF(P65="","",P65*G65) | T65: =_xlfn.IFNA(IF(VLOOKUP(D65,Group!C:I,7,0)=0,"",VLOOKUP(D65,Group!C:I,7,0)),"") | U65: =IFERROR(T65*G65,"") | V65: =IFERROR(AY65/U65,"") | AA65: =_xlfn.IFNA(Backend!AO70,"") | AB65: =Backend!AP70 | AC65: =Backend!AQ70 | AD65: =Backend!AR70 | AE65: =Backend!AS70 | AF65: =Backend!AT70 | AG65: =Backend!AU70 | AH65: =Backend!AV70 | AI65: =Backend!AW70 | ... AV65: =Backend!BJ70 | AW65: =_xlfn.IFNA(Backend!O70,"") | AX65: =_xlfn.IFNA(IF(D65="","",Backend!BK70),"") | AY65: =IF(AX65="","",AX65*G65)
A66: 64 | B66: =B65 -> FWR10000 | K66: =_xlfn.IFNA(Backend!AN71,"") | L66: =IFERROR(AA66,"") | M66: =IFERROR(AW66,"") | N66: =IF(SUM(AB66:AS66)=0,"",SUM(AB66:AS66)) | O66: =IF(SUM(AT66:AV66)=0,"",SUM(AT66:AV66)) | P66: =IF(K66="","",SUM(K66:O66)) | Q66: =IF(P66="","",P66*G66) | T66: =_xlfn.IFNA(IF(VLOOKUP(D66,Group!C:I,7,0)=0,"",VLOOKUP(D66,Group!C:I,7,0)),"") | U66: =IFERROR(T66*G66,"") | V66: =IFERROR(AY66/U66,"") | AA66: =_xlfn.IFNA(Backend!AO71,"") | AB66: =Backend!AP71 | AC66: =Backend!AQ71 | AD66: =Backend!AR71 | AE66: =Backend!AS71 | AF66: =Backend!AT71 | AG66: =Backend!AU71 | AH66: =Backend!AV71 | AI66: =Backend!AW71 | ... AV66: =Backend!BJ71 | AW66: =_xlfn.IFNA(Backend!O71,"") | AX66: =_xlfn.IFNA(IF(D66="","",Backend!BK71),"") | AY66: =IF(AX66="","",AX66*G66)
A67: 65 | B67: =B66 -> FWR10000 | K67: =_xlfn.IFNA(Backend!AN72,"") | L67: =IFERROR(AA67,"") | M67: =IFERROR(AW67,"") | N67: =IF(SUM(AB67:AS67)=0,"",SUM(AB67:AS67)) | O67: =IF(SUM(AT67:AV67)=0,"",SUM(AT67:AV67)) | P67: =IF(K67="","",SUM(K67:O67)) | Q67: =IF(P67="","",P67*G67) | T67: =_xlfn.IFNA(IF(VLOOKUP(D67,Group!C:I,7,0)=0,"",VLOOKUP(D67,Group!C:I,7,0)),"") | U67: =IFERROR(T67*G67,"") | V67: =IFERROR(AY67/U67,"") | AA67: =_xlfn.IFNA(Backend!AO72,"") | AB67: =Backend!AP72 | AC67: =Backend!AQ72 | AD67: =Backend!AR72 | AE67: =Backend!AS72 | AF67: =Backend!AT72 | AG67: =Backend!AU72 | AH67: =Backend!AV72 | AI67: =Backend!AW72 | ... AV67: =Backend!BJ72 | AW67: =_xlfn.IFNA(Backend!O72,"") | AX67: =_xlfn.IFNA(IF(D67="","",Backend!BK72),"") | AY67: =IF(AX67="","",AX67*G67)
A68: 66 | B68: =B67 -> FWR10000 | K68: =_xlfn.IFNA(Backend!AN73,"") | L68: =IFERROR(AA68,"") | M68: =IFERROR(AW68,"") | N68: =IF(SUM(AB68:AS68)=0,"",SUM(AB68:AS68)) | O68: =IF(SUM(AT68:AV68)=0,"",SUM(AT68:AV68)) | P68: =IF(K68="","",SUM(K68:O68)) | Q68: =IF(P68="","",P68*G68) | T68: =_xlfn.IFNA(IF(VLOOKUP(D68,Group!C:I,7,0)=0,"",VLOOKUP(D68,Group!C:I,7,0)),"") | U68: =IFERROR(T68*G68,"") | V68: =IFERROR(AY68/U68,"") | AA68: =_xlfn.IFNA(Backend!AO73,"") | AB68: =Backend!AP73 | AC68: =Backend!AQ73 | AD68: =Backend!AR73 | AE68: =Backend!AS73 | AF68: =Backend!AT73 | AG68: =Backend!AU73 | AH68: =Backend!AV73 | AI68: =Backend!AW73 | ... AV68: =Backend!BJ73 | AW68: =_xlfn.IFNA(Backend!O73,"") | AX68: =_xlfn.IFNA(IF(D68="","",Backend!BK73),"") | AY68: =IF(AX68="","",AX68*G68)
A69: 67 | B69: =B68 -> FWR10000 | K69: =_xlfn.IFNA(Backend!AN74,"") | L69: =IFERROR(AA69,"") | M69: =IFERROR(AW69,"") | N69: =IF(SUM(AB69:AS69)=0,"",SUM(AB69:AS69)) | O69: =IF(SUM(AT69:AV69)=0,"",SUM(AT69:AV69)) | P69: =IF(K69="","",SUM(K69:O69)) | Q69: =IF(P69="","",P69*G69) | T69: =_xlfn.IFNA(IF(VLOOKUP(D69,Group!C:I,7,0)=0,"",VLOOKUP(D69,Group!C:I,7,0)),"") | U69: =IFERROR(T69*G69,"") | V69: =IFERROR(AY69/U69,"") | AA69: =_xlfn.IFNA(Backend!AO74,"") | AB69: =Backend!AP74 | AC69: =Backend!AQ74 | AD69: =Backend!AR74 | AE69: =Backend!AS74 | AF69: =Backend!AT74 | AG69: =Backend!AU74 | AH69: =Backend!AV74 | AI69: =Backend!AW74 | ... AV69: =Backend!BJ74 | AW69: =_xlfn.IFNA(Backend!O74,"") | AX69: =_xlfn.IFNA(IF(D69="","",Backend!BK74),"") | AY69: =IF(AX69="","",AX69*G69)
A70: 68 | B70: =B69 -> FWR10000 | K70: =_xlfn.IFNA(Backend!AN75,"") | L70: =IFERROR(AA70,"") | M70: =IFERROR(AW70,"") | N70: =IF(SUM(AB70:AS70)=0,"",SUM(AB70:AS70)) | O70: =IF(SUM(AT70:AV70)=0,"",SUM(AT70:AV70)) | P70: =IF(K70="","",SUM(K70:O70)) | Q70: =IF(P70="","",P70*G70) | T70: =_xlfn.IFNA(IF(VLOOKUP(D70,Group!C:I,7,0)=0,"",VLOOKUP(D70,Group!C:I,7,0)),"") | U70: =IFERROR(T70*G70,"") | V70: =IFERROR(AY70/U70,"") | AA70: =_xlfn.IFNA(Backend!AO75,"") | AB70: =Backend!AP75 | AC70: =Backend!AQ75 | AD70: =Backend!AR75 | AE70: =Backend!AS75 | AF70: =Backend!AT75 | AG70: =Backend!AU75 | AH70: =Backend!AV75 | AI70: =Backend!AW75 | ... AV70: =Backend!BJ75 | AW70: =_xlfn.IFNA(Backend!O75,"") | AX70: =_xlfn.IFNA(IF(D70="","",Backend!BK75),"") | AY70: =IF(AX70="","",AX70*G70)
A71: 69 | B71: =B70 -> FWR10000 | K71: =_xlfn.IFNA(Backend!AN76,"") | L71: =IFERROR(AA71,"") | M71: =IFERROR(AW71,"") | N71: =IF(SUM(AB71:AS71)=0,"",SUM(AB71:AS71)) | O71: =IF(SUM(AT71:AV71)=0,"",SUM(AT71:AV71)) | P71: =IF(K71="","",SUM(K71:O71)) | Q71: =IF(P71="","",P71*G71) | T71: =_xlfn.IFNA(IF(VLOOKUP(D71,Group!C:I,7,0)=0,"",VLOOKUP(D71,Group!C:I,7,0)),"") | U71: =IFERROR(T71*G71,"") | V71: =IFERROR(AY71/U71,"") | AA71: =_xlfn.IFNA(Backend!AO76,"") | AB71: =Backend!AP76 | AC71: =Backend!AQ76 | AD71: =Backend!AR76 | AE71: =Backend!AS76 | AF71: =Backend!AT76 | AG71: =Backend!AU76 | AH71: =Backend!AV76 | AI71: =Backend!AW76 | ... AV71: =Backend!BJ76 | AW71: =_xlfn.IFNA(Backend!O76,"") | AX71: =_xlfn.IFNA(IF(D71="","",Backend!BK76),"") | AY71: =IF(AX71="","",AX71*G71)
A72: 70 | B72: =B71 -> FWR10000 | K72: =_xlfn.IFNA(Backend!AN77,"") | L72: =IFERROR(AA72,"") | M72: =IFERROR(AW72,"") | N72: =IF(SUM(AB72:AS72)=0,"",SUM(AB72:AS72)) | O72: =IF(SUM(AT72:AV72)=0,"",SUM(AT72:AV72)) | P72: =IF(K72="","",SUM(K72:O72)) | Q72: =IF(P72="","",P72*G72) | T72: =_xlfn.IFNA(IF(VLOOKUP(D72,Group!C:I,7,0)=0,"",VLOOKUP(D72,Group!C:I,7,0)),"") | U72: =IFERROR(T72*G72,"") | V72: =IFERROR(AY72/U72,"") | AA72: =_xlfn.IFNA(Backend!AO77,"") | AB72: =Backend!AP77 | AC72: =Backend!AQ77 | AD72: =Backend!AR77 | AE72: =Backend!AS77 | AF72: =Backend!AT77 | AG72: =Backend!AU77 | AH72: =Backend!AV77 | AI72: =Backend!AW77 | ... AV72: =Backend!BJ77 | AW72: =_xlfn.IFNA(Backend!O77,"") | AX72: =_xlfn.IFNA(IF(D72="","",Backend!BK77),"") | AY72: =IF(AX72="","",AX72*G72)
A73: 71 | B73: =B72 -> FWR10000 | K73: =_xlfn.IFNA(Backend!AN78,"") | L73: =IFERROR(AA73,"") | M73: =IFERROR(AW73,"") | N73: =IF(SUM(AB73:AS73)=0,"",SUM(AB73:AS73)) | O73: =IF(SUM(AT73:AV73)=0,"",SUM(AT73:AV73)) | P73: =IF(K73="","",SUM(K73:O73)) | Q73: =IF(P73="","",P73*G73) | T73: =_xlfn.IFNA(IF(VLOOKUP(D73,Group!C:I,7,0)=0,"",VLOOKUP(D73,Group!C:I,7,0)),"") | U73: =IFERROR(T73*G73,"") | V73: =IFERROR(AY73/U73,"") | AA73: =_xlfn.IFNA(Backend!AO78,"") | AB73: =Backend!AP78 | AC73: =Backend!AQ78 | AD73: =Backend!AR78 | AE73: =Backend!AS78 | AF73: =Backend!AT78 | AG73: =Backend!AU78 | AH73: =Backend!AV78 | AI73: =Backend!AW78 | ... AV73: =Backend!BJ78 | AW73: =_xlfn.IFNA(Backend!O78,"") | AX73: =_xlfn.IFNA(IF(D73="","",Backend!BK78),"") | AY73: =IF(AX73="","",AX73*G73)
... A102: 100 | B102: =B101 -> FWR10000 | K102: =_xlfn.IFNA(Backend!AN107,"") | L102: =IFERROR(AA102,"") | M102: =IFERROR(AW102,"") | N102: =IF(SUM(AB102:AS102)=0,"",SUM(AB102:AS102)) | O102: =IF(SUM(AT102:AV102)=0,"",SUM(AT102:AV102)) | P102: =IF(K102="","",SUM(K102:O102)) | Q102: =IF(P102="","",P102*G102) | T102: =_xlfn.IFNA(IF(VLOOKUP(D102,Group!C:I,7,0)=0,"",VLOOKUP(D102,Group!C:I,7,0)),"") | U102: =IFERROR(T102*G102,"") | V102: =IFERROR(AY102/U102,"") | AA102: =_xlfn.IFNA(Backend!AO107,"") | AB102: =Backend!AP107 | AC102: =Backend!AQ107 | AD102: =Backend!AR107 | AE102: =Backend!AS107 | AF102: =Backend!AT107 | AG102: =Backend!AU107 | AH102: =Backend!AV107 | AI102: =Backend!AW107 | ... AV102: =Backend!BJ107 | AW102: =_xlfn.IFNA(Backend!O107,"") | AX102: =_xlfn.IFNA(IF(D102="","",Backend!BK107),"") | AY102: =IF(AX102="","",AX102*G102)

Sheet Assy_Cost
A1: Assembly(If norms available)
B3: Part No | C3: Process Type | D3: Part Description | E3: PROCESS DESCRIPTION | G3: Assy Type | H3: UOM | I3: No. of Opn. As per UOM | J3: PARTS PER CYCLE | K3: Norms | L3: Process cost/Unit
C4: =_xlfn.IFNA(IF(E4="Surface protection","Surface Protection",IF(VLOOKUP(B4,BOM!$D$1:$I$10000,6,0)="Inhouse","Process-Inhouse",IF(VLOOKUP(B4,BOM!$D$1:$I$10000,6,0)="Inhouse","Process-Inhouse",IF(VLOOKUP(B4,BOM!$D$1:$I$10000,6,0)="BOF","Process-outsourced",IF(VLOOKUP(B4,BOM!$D$1:$I$10000,6,0)="BOSF","Process-Inhouse"))))),"") | D4: =_xlfn.IFNA(VLOOKUP(B4,BOM!D:F,3,0),"") | H4: =_xlfn.IFNA(VLOOKUP(G4,'Process Base'!D:G,4,0),"") | J4: 1 | K4: =_xlfn.IFNA(VLOOKUP(G4,'Process Base'!D:F,3,0),"") | L4: =IFERROR((K4/J4)*I4,"")
C5: =_xlfn.IFNA(IF(E5="Surface protection","Surface Protection",IF(VLOOKUP(B5,BOM!$D$1:$I$10000,6,0)="Inhouse","Process-Inhouse",IF(VLOOKUP(B5,BOM!$D$1:$I$10000,6,0)="Inhouse","Process-Inhouse",IF(VLOOKUP(B5,BOM!$D$1:$I$10000,6,0)="BOF","Process-outsourced",IF(VLOOKUP(B5,BOM!$D$1:$I$10000,6,0)="BOSF","Process-Inhouse"))))),"") | D5: =_xlfn.IFNA(VLOOKUP(B5,BOM!D:F,3,0),"") | H5: =_xlfn.IFNA(VLOOKUP(G5,'Process Base'!D:G,4,0),"") | J5: 1 | K5: =_xlfn.IFNA(VLOOKUP(G5,'Process Base'!D:F,3,0),"") | L5: =IFERROR((K5/J5)*I5,"")
C6: =_xlfn.IFNA(IF(E6="Surface protection","Surface Protection",IF(VLOOKUP(B6,BOM!$D$1:$I$10000,6,0)="Inhouse","Process-Inhouse",IF(VLOOKUP(B6,BOM!$D$1:$I$10000,6,0)="Inhouse","Process-Inhouse",IF(VLOOKUP(B6,BOM!$D$1:$I$10000,6,0)="BOF","Process-outsourced",IF(VLOOKUP(B6,BOM!$D$1:$I$10000,6,0)="BOSF","Process-Inhouse"))))),"") | D6: =_xlfn.IFNA(VLOOKUP(B6,BOM!D:F,3,0),"") | H6: =_xlfn.IFNA(VLOOKUP(G6,'Process Base'!D:G,4,0),"") | J6: 1 | K6: =_xlfn.IFNA(VLOOKUP(G6,'Process Base'!D:F,3,0),"") | L6: =IFERROR((K6/J6)*I6,"")
C7: =_xlfn.IFNA(IF(E7="Surface protection","Surface Protection",IF(VLOOKUP(B7,BOM!$D$1:$I$10000,6,0)="Inhouse","Process-Inhouse",IF(VLOOKUP(B7,BOM!$D$1:$I$10000,6,0)="Inhouse","Process-Inhouse",IF(VLOOKUP(B7,BOM!$D$1:$I$10000,6,0)="BOF","Process-outsourced",IF(VLOOKUP(B7,BOM!$D$1:$I$10000,6,0)="BOSF","Process-Inhouse"))))),"") | D7: =_xlfn.IFNA(VLOOKUP(B7,BOM!D:F,3,0),"") | H7: =_xlfn.IFNA(VLOOKUP(G7,'Process Base'!D:G,4,0),"") | J7: 1 | K7: =_xlfn.IFNA(VLOOKUP(G7,'Process Base'!D:F,3,0),"") | L7: =IFERROR((K7/J7)*I7,"")
C8: =_xlfn.IFNA(IF(E8="Surface protection","Surface Protection",IF(VLOOKUP(B8,BOM!$D$1:$I$10000,6,0)="Inhouse","Process-Inhouse",IF(VLOOKUP(B8,BOM!$D$1:$I$10000,6,0)="Inhouse","Process-Inhouse",IF(VLOOKUP(B8,BOM!$D$1:$I$10000,6,0)="BOF","Process-outsourced",IF(VLOOKUP(B8,BOM!$D$1:$I$10000,6,0)="BOSF","Process-Inhouse"))))),"") | D8: =_xlfn.IFNA(VLOOKUP(B8,BOM!D:F,3,0),"") | H8: =_xlfn.IFNA(VLOOKUP(G8,'Process Base'!D:G,4,0),"") | J8: 1 | K8: =_xlfn.IFNA(VLOOKUP(G8,'Process Base'!D:F,3,0),"") | L8: =IFERROR((K8/J8)*I8,"")
A15: Assembly(If norms not available)
B17: Part No. | C17: Process Type | D17: Part Description | E17: Process Description | F17: Cycle time(Sec) | G17: MHR | H17: Machine rate | I17: No. of Labour | J17: Labour type | K17: Labour rate | L17: Assy cost
B18: =Group!AF2 -> FWR10000 | C18: =_xlfn.IFNA(IF(E18="Surface protection","Surface Protection",IF(VLOOKUP(B18,BOM!$D$1:$I$10000,6,0)="Inhouse","Process-Inhouse",IF(VLOOKUP(B18,BOM!$D$1:$I$10000,6,0)="Inhouse","Process-Inhouse",IF(VLOOKUP(B18,BOM!$D$1:$I$10000,6,0)="BOF","Process-outsourced",IF(VLOOKUP(B18,BOM!$D$1:$I$10000,6,0)="BOSF","Process-Inhouse"))))),"") -> Process-Inhouse | D18: =_xlfn.IFNA(VLOOKUP(B18,BOM!D:F,3,0),"") -> Seat - Driver Pneumatic Suspended | H18: =F18*G18/3600 -> 0 | K18: =I18*IF(J18="Skilled",120,IF(J18="Semi-skilled",100,IF(J18="Unskilled",80,0)))*F18/3600 -> 0 | L18: =H18+K18 -> 0
B19: =Group!AF3 -> H 157 01 464 A | C19: =_xlfn.IFNA(IF(E19="Surface protection","Surface Protection",IF(VLOOKUP(B19,BOM!$D$1:$I$10000,6,0)="Inhouse","Process-Inhouse",IF(VLOOKUP(B19,BOM!$D$1:$I$10000,6,0)="Inhouse","Process-Inhouse",IF(VLOOKUP(B19,BOM!$D$1:$I$10000,6,0)="BOF","Process-outsourced",IF(VLOOKUP(B19,BOM!$D$1:$I$10000,6,0)="BOSF","Process-Inhouse"))))),"") -> Process-Inhouse | D19: =_xlfn.IFNA(VLOOKUP(B19,BOM!D:F,3,0),"") -> SLIDER KIT ASSY | H19: =F19*G19/3600 -> 0 | K19: =I19*IF(J19="Skilled",120,IF(J19="Semi-skilled",100,IF(J19="Unskilled",80,0)))*F19/3600 -> 0 | L19: =H19+K19 -> 0
B20: =Group!AF4 -> H 157 01 270 A | C20: =_xlfn.IFNA(IF(E20="Surface protection","Surface Protection",IF(VLOOKUP(B20,BOM!$D$1:$I$10000,6,0)="Inhouse","Process-Inhouse",IF(VLOOKUP(B20,BOM!$D$1:$I$10000,6,0)="Inhouse","Process-Inhouse",IF(VLOOKUP(B20,BOM!$D$1:$I$10000,6,0)="BOF","Process-outsourced",IF(VLOOKUP(B20,BOM!$D$1:$I$10000,6,0)="BOSF","Process-Inhouse"))))),"") -> Process-Inhouse | D20: =_xlfn.IFNA(VLOOKUP(B20,BOM!D:F,3,0),"") -> Pnematic suspension CV | H20: =F20*G20/3600 -> 0 | K20: =I20*IF(J20="Skilled",120,IF(J20="Semi-skilled",100,IF(J20="Unskilled",80,0)))*F20/3600 -> 0 | L20: =H20+K20 -> 0
B21: =Group!AF5 -> 0 | C21: =_xlfn.IFNA(IF(E21="Surface protection","Surface Protection",IF(VLOOKUP(B21,BOM!$D$1:$I$10000,6,0)="Inhouse","Process-Inhouse",IF(VLOOKUP(B21,BOM!$D$1:$I$10000,6,0)="Inhouse","Process-Inhouse",IF(VLOOKUP(B21,BOM!$D$1:$I$10000,6,0)="BOF","Process-outsourced",IF(VLOOKUP(B21,BOM!$D$1:$I$10000,6,0)="BOSF","Process-Inhouse"))))),"") | D21: =_xlfn.IFNA(VLOOKUP(B21,BOM!D:F,3,0),"") | H21: =F21*G21/3600 -> 0 | K21: =I21*IF(J21="Skilled",120,IF(J21="Semi-skilled",100,IF(J21="Unskilled",80,0)))*F21/3600 -> 0 | L21: =H21+K21 -> 0
B22: =Group!AF6 -> 0 | C22: =_xlfn.IFNA(IF(E22="Surface protection","Surface Protection",IF(VLOOKUP(B22,BOM!$D$1:$I$10000,6,0)="Inhouse","Process-Inhouse",IF(VLOOKUP(B22,BOM!$D$1:$I$10000,6,0)="Inhouse","Process-Inhouse",IF(VLOOKUP(B22,BOM!$D$1:$I$10000,6,0)="BOF","Process-outsourced",IF(VLOOKUP(B22,BOM!$D$1:$I$10000,6,0)="BOSF","Process-Inhouse"))))),"") | D22: =_xlfn.IFNA(VLOOKUP(B22,BOM!D:F,3,0),"") | H22: =F22*G22/3600 -> 0 | K22: =I22*IF(J22="Skilled",120,IF(J22="Semi-skilled",100,IF(J22="Unskilled",80,0)))*F22/3600 -> 0 | L22: =H22+K22 -> 0
B23: =Group!AF7 -> 0 | C23: =_xlfn.IFNA(IF(E23="Surface protection","Surface Protection",IF(VLOOKUP(B23,BOM!$D$1:$I$10000,6,0)="Inhouse","Process-Inhouse",IF(VLOOKUP(B23,BOM!$D$1:$I$10000,6,0)="Inhouse","Process-Inhouse",IF(VLOOKUP(B23,BOM!$D$1:$I$10000,6,0)="BOF","Process-outsourced",IF(VLOOKUP(B23,BOM!$D$1:$I$10000,6,0)="BOSF","Process-Inhouse"))))),"") | D23: =_xlfn.IFNA(VLOOKUP(B23,BOM!D:F,3,0),"") | H23: =F23*G23/3600 -> 0 | K23: =I23*IF(J23="Skilled",120,IF(J23="Semi-skilled",100,IF(J23="Unskilled",80,0)))*F23/3600 -> 0 | L23: =H23+K23 -> 0
B24: =Group!AF8 -> 0 | C24: =_xlfn.IFNA(IF(E24="Surface protection","Surface Protection",IF(VLOOKUP(B24,BOM!$D$1:$I$10000,6,0)="Inhouse","Process-Inhouse",IF(VLOOKUP(B24,BOM!$D$1:$I$10000,6,0)="Inhouse","Process-Inhouse",IF(VLOOKUP(B24,BOM!$D$1:$I$10000,6,0)="BOF","Process-outsourced",IF(VLOOKUP(B24,BOM!$D$1:$I$10000,6,0)="BOSF","Process-Inhouse"))))),"") | D24: =_xlfn.IFNA(VLOOKUP(B24,BOM!D:F,3,0),"") | H24: =F24*G24/3600 -> 0 | K24: =I24*IF(J24="Skilled",120,IF(J24="Semi-skilled",100,IF(J24="Unskilled",80,0)))*F24/3600 -> 0 | L24: =H24+K24 -> 0

Sheet Machining_Process
A1: 1
M2: Cutting speed M/Min
K3: Operation | L3: Steel | M3: SG Iron | N3: Cast Iron | O3: Aluminium | P3: Stainless Steel | Q3: Brass | R3: Bronze | S3: Copper | T3: Copper | U3: Copper
L4: 2 | M4: 3 | N4: 4 | O4: 5 | P4: 6 | Q4: 7 | R4: 8 | S4: 9 | T4: 9 | U4: 9
K5: Drilling | L5: 25 | M5: 50 | N5: 80 | O5: 100 | P5: 20 | Q5: 50 | R5: 35 | S5: 20 | T5: 20 | U5: 20
K6: Face Milling | L6: 100 | M6: 160 | N6: 200 | O6: 350 | P6: 80 | Q6: 190 | R6: 155 | S6: 62 | T6: 62 | U6: 62 | W6: cylinderal grinding | X6: 30-40m/min
K7: Pocket milling | L7: =L6/2 -> 50 | M7: =M6/2 -> 80 | N7: =N6/2 -> 100 | O7: =O6/2 -> 175 | P7: =P6/2 -> 40 | Q7: =Q6/2 -> 95 | R7: =R6/2 -> 77.5 | S7: =S6/2 -> 31 | ... U7: =U6/2 -> 31
K8: Turning | L8: 110 | M8: 150 | N8: 190 | O8: 350 | P8: 100 | Q8: 190 | R8: 155 | S8: 62 | T8: 62 | U8: 62
K9: Tapping | L9: =L5/5 -> 5 | M9: =M5/5 -> 10 | N9: =N5/5 -> 16 | O9: =O5/5 -> 20 | P9: =P5/5 -> 4 | Q9: =Q5/5 -> 10 | R9: =R5/5 -> 7 | S9: =S5/5 -> 4 | ... U9: =U5/5 -> 4
K10: Boring | L10: 110 | M10: 150 | N10: 190 | O10: 350 | P10: 100 | Q10: 190 | R10: 155 | S10: 62 | T10: 62 | U10: 62
K11: Hobbing | L11: 100 | M11: 160 | N11: 200 | O11: 350 | P11: 80 | Q11: 190 | R11: 155 | S11: 62 | T11: 62 | U11: 62 | W11: Reference for Cutting speed for grinding
K12: Gear Grinding | L12: 2500 | W12: https://www.abrasiveengineering.com/speeds.htm
K13: Internal Grinding | L13: 2500
K14: External Grinding | L14: 2500
K15: Surface grinding | L15: 1500
K16: Chamfering
B17: Cycle Time Calculation Master | K17: Spot facing
Q18: <-- Select material type from dropdown list
Q19: <-- Manual input
Q20: <-- Manual entry
T21: Total Machining time | V21: Machining cost | EF21: Table reciprocating speed 30 M/min (500mm/s) considered
F22: Material | T22: =SUMIF(B25:$B$9955,B22,X25:$X$9955) -> 0 | V22: =SUMIF(B25:$B$9955,B22,V25:$V$9955) -> 0 | DM22: Considered grinding allowance 0.3 & Depth of cut 0.025mm -12 pass | DT22: Considered grinding allowance 0.3 & Depth of cut 0.025mm -12 pass | EF22: Considered grinding allowance 0.2 mm & 4 roughing cut 1 finish cut
B23: Part Details | H23: Machining Details | K23: Machining Parameters | Y23: Drilling | AH23: Face Milling | AT23: Pocket Milling | BF23: Turning | BP23: Tapping | BY23: Boring | CI23: Hobbing | CV23: Gear Grinding | DH23: Internal Grinding | DS23: External Grinding | EE23: Surface Grinding
B24: Part No | C24: Process Type | D24: Machining Type | E24: PROCESS DESCRIPTION | F24: QTY | H24: Machine | I24: MHR | J24: Operation | K24: Diameter (Tool/Job) | L24: Length | M24: Width of job | N24: No of pass | O24: No of inserts | P24: Pitch in mm (Tapping) | Q24: No. of teeth (Gears) | R24: Height of teeth (Gears) | S24: Module (Gears) | T24: Time in Sec | U24: Cost /part | V24: TOTAL VALUE ADD | W24: REMARKS | X24: Total Time in Sec | Y24: Final Drill Ø | Z24: Depth | AA24: CS | AB24: RPM | AC24: Feed mm/rev | AD24: Time | AE24: Rapid movement + TC time | AF24: Total Drilling Time | AH24: Cutter Ø | AI24: Length | AJ24: Width | AK24: No of pass | AL24: No of insert | AM24: CS | AN24: RPM | AO24: Feed mm/rev | AP24: Time | AQ24: Rapid movement + TC time | AR24: Total Milling Time | AT24: Cutter Ø | AU24: Length | AV24: Width | AW24: No of pass | AX24: No of insert | AY24: CS | AZ24: RPM | BA24: Feed mm/rev | BB24: Time | BC24: Rapid movement + TC time | BD24: Total Milling Time | BF24: Work Ø | BG24: Turning Length | BH24: No of pass | BI24: CS | BJ24: RPM | BK24: Feed mm/rev | BL24: Time | BM24: Rapid movement + TC time | BN24: Total Turning Time | BP24: Nominal Ø of the thread | BQ24: Tapping Depth | BR24: Pitch in mm | BS24: CS | BT24: RPM | BU24: Time | BV24: Rapid movement + TC time | BW24: Total Tapping Time | BY24: Hole Ø | BZ24: Hole Length | CA24: No of pass | CB24: CS | CC24: RPM | CD24: Feed mm/rev | CE24: Time | CF24: Rapid movement + TC time | CG24: Total Boring Time | CI24: Blank dia. | CJ24: length of job | CK24: Height of teeth | CL24: CS | CM24: RPM | CN24: No. of teeth | CO24: Module | CP24: Hob Dia. | CQ24: Feed mm/rev | CR24: Time | CS24: Rapid movement + TC time | CT24: Total Hobbing Time | CV24: Gear dia. | CW24: length of job | CX24: Height of teeth | CY24: Cutting speed | CZ24: RPM of wheel | DA24: Diameter of the wheel | DB24: No. of teeth | DC24: Feed mm/rev | DD24: Time | DE24: Rapid movement + TC time | DF24: Total Grinding Time | DH24: Diameter of job | DI24: Length of job | DJ24: Pass | DK24: Width of wheel | DL24: CS for workpiece | DM24: Work RPM | DN24: Feed mm/rev | DO24: Time | DP24: Rapid movement + TC time | DQ24: Total Grinding Time | DS24: Diameter of job | DT24: Length of job | DU24: Pass | DV24: Width of wheel | DW24: CS | DX24: Work RPM | DY24: Feed mm/rev | DZ24: Time | EA24: Rapid movement + TC time | EB24: Total Grinding Time | EE24: Length of job | EF24: Width of job | EG24: Width of wheel | EH24: Time | EI24: Rapid movement + TC time | EJ24: Total Grinding Time
B25: =B22 -> 0 | C25: =_xlfn.IFNA(VLOOKUP(B25,BOM!$D$1:$H$10000,5,0),"") | E25: Loading to the machine | F25: 1 | T25: =IF(J25="Drilling",AF25,IF(J25="Face Milling",AR25,IF(J25="Pocket Milling",BD25,IF(J25="Turning",BN25,IF(J25="Tapping",BW25,IF(J25="Boring",CG25,IF(J25="Chamfering",5,IF(J25="Spot facing",10,IF(J25="Hobbing",CT25,IF(J25="Gear grinding",DF25,IF(J25="Internal Grinding",DQ25,IF(J25="External Grinding",EB25,IF(J25="Surface grinding",EJ25,0))))))))))))) -> 0 | U25: =I25/3600*T25 -> 0 | V25: =U25*F25 -> 0 | X25: =T25*F25 -> 0 | Y25: =K25 -> 0 | Z25: =L25+Y25*0.3 -> 0 | AA25: =VLOOKUP(Y$23,$K$3:$S$17,HLOOKUP(VLOOKUP(B25,B:H,7,0),$3:$4,2,0),0) -> #N/A | AB25: =MIN(IFERROR(AA25*1000/(PI()*Y25),0),5000) -> 0 | AC25: =IF(K25<15,0.05,0.1) -> 0.05 | AD25: =IFERROR((Z25+3)/(AB25*AC25/60),0) -> 0 | AE25: 5 | AF25: =AD25+AE25 -> 5 | AH25: =K25 -> 0 | AI25: =L25 -> 0 | AJ25: =M25 -> 0 | AK25: =N25 -> 0 | AL25: =O25 -> 0 | AM25: =VLOOKUP(AH$23,$K$3:$S$17,HLOOKUP(VLOOKUP(B25,B:H,7,0),$3:$4,2,0),0) -> #N/A | AN25: =MIN(IFERROR((AM25*1000/(PI()*AH25)),0),5000) -> 0 | AO25: =0.05*AL25 -> 0 | AP25: =IFERROR(((AI25+(AH25+10)+IF(AJ25<AH25,0,((CEILING(AJ25/AH25,1)-1)*AI25)+((CEILING(AJ25/AH25,1)-1)*AH25)))/(AO25*AN25/60)),0)*AK25 -> 0 | AQ25: 5 | AR25: =AP25+AQ25 -> 5 | AT25: =K25 -> 0 | AU25: =L25 -> 0 | AV25: =M25 -> 0 | AW25: =N25 -> 0 | AX25: =O25 -> 0 | AY25: =VLOOKUP(AT$23,$K$3:$S$17,HLOOKUP(VLOOKUP(B25,B:H,7,0),$3:$4,2,0),0) -> #N/A | AZ25: =MIN(IFERROR((AY25*1000/(PI()*AT25)),0),5000) -> 0 | BA25: =0.03*AX25 -> 0 | BB25: =IFERROR(((AU25+(AT25+10)+IF(AV25<AT25,0,((CEILING(AV25/AT25,1)-1)*AU25)+((CEILING(AV25/AT25,1)-1)*AT25)))/(BA25*AZ25/60)),0)*AW25 -> 0 | BC25: 5 | BD25: =BB25+BC25 -> 5 | BF25: =K25 -> 0 | BG25: =L25 -> 0 | BH25: =N25 -> 0 | BI25: =VLOOKUP(BF$23,$K$3:$S$17,HLOOKUP(VLOOKUP(B25,B:H,7,0),$3:$4,2,0),0) -> #N/A | BJ25: =MIN(IFERROR(BI25*1000/(PI()*BF25),0),5000) -> 0 | BK25: 0.1 | BL25: =IFERROR((BG25+3)/(BJ25*BK25/60),0)*BH25 -> 0 | BM25: 2 | BN25: =BL25+BM25 -> 2 | BP25: =K25 -> 0 | BQ25: =L25 -> 0 | BR25: =P25 -> 0 | BS25: =VLOOKUP(BP$23,$K$3:$S$17,HLOOKUP(VLOOKUP(B25,B:H,7,0),$3:$4,2,0),0) -> #N/A | BT25: =MIN(IFERROR(BS25*1000/(PI()*BP25),0),400) -> 0 | BU25: =IFERROR((BQ25+3)/(BT25*BR25/60),0)*2 -> 0 | BV25: 5 | BW25: =BU25+BV25 -> 5 | BY25: =K25 -> 0 | BZ25: =L25 -> 0 | CA25: =N25 -> 0 | CB25: =VLOOKUP(BY$23,$K$3:$S$17,HLOOKUP(VLOOKUP(B25,B:H,7,0),$3:$4,2,0),0) -> #N/A | CC25: =MIN(IFERROR(CB25*1000/(PI()*BY25),0),5000) -> 0 | CD25: 0.05 | CE25: =IFERROR((BZ25+3)/(CC25*CD25/60),0)*CA25 -> 0 | CF25: 5 | CG25: =CE25+CF25 -> 5 | CI25: =K25 -> 0 | CJ25: =L25 -> 0 | CK25: =R25 -> 0 | CL25: =VLOOKUP(CI$23,$K$3:$S$17,HLOOKUP(VLOOKUP(B25,B:H,7,0),$3:$4,2,0),0) -> #N/A | CM25: =MIN(IFERROR(CL25*1000/(PI()*CP25),0),5000) -> 0 | CN25: =Q25 -> 0 | CO25: =S25 -> 0 | CP25: =9.7903*CO25+41.578 -> 41.578 | CQ25: 1.5 | CR25: =IFERROR((((SQRT((CP25*CK25-CK25^2))+CJ25+5)*CN25)/(CM25*CQ25))*60,0) -> 0 | CS25: 5 | CT25: =CR25+CS25 -> 5 | CV25: =K25 -> 0 | CW25: =L25 -> 0 | CX25: =R25 -> 0 | CY25: =VLOOKUP(CV$23,$K$3:$S$17,HLOOKUP(VLOOKUP(B25,B:H,7,0),$3:$4,2,0),0) -> #N/A | CZ25: =MIN(IFERROR(CY25*1000/(PI()*DA25),0),5000) -> 0 | DA25: 300 | DB25: =Q25 -> 0 | DC25: 0.4 | DD25: =IFERROR((((SQRT((DA25*CX25-CX25^2))+CW25+5)*DB25)/(DC25*CZ25))*60,0) -> 0 | DE25: 5 | DF25: =DD25+DE25 -> 5 | DH25: =K25 -> 0 | DI25: =L25 -> 0 | DJ25: 12 | DK25: 30 | DL25: 15 | DM25: =MIN(IFERROR(DL25*1000/(PI()*DH25),0),5000) -> 0 | DN25: =DK25/2 -> 15 | DO25: =IFERROR(((DI25+DK25)*2)/(DM25*DN25/60),0)*DJ25 -> 0 | DP25: 5 | DQ25: =DO25+DP25 -> 5 | DS25: =K25 -> 0 | DT25: =L25 -> 0 | DU25: 12 | DV25: 30 | DW25: 15 | DX25: =MIN(IFERROR(DW25*1000/(PI()*DS25),0),5000) -> 0 | DY25: =DV25/2 -> 15 | DZ25: =IFERROR(((DT25+DV25)*2)/(DX25*DY25/60),0)*DU25 -> 0 | EA25: 5 | EB25: =DZ25+EA25 -> 5 | EE25: =L25 -> 0 | EF25: =M25 -> 0 | EG25: 30 | EH25: =(EE25+30)/500*CEILING((EF25+EG25+3)/(EG25/6),INT(EG25/6))*4+(EE25+30)/500*CEILING((EF25+EG25+3)/(EG25/10),INT(EG25/10)) -> 3.12 | EI25: 3 | EJ25: =EH25+EI25 -> 6.12
B26: =B25 -> 0 | C26: =_xlfn.IFNA(VLOOKUP(B26,BOM!$D$1:$H$10000,5,0),"") | T26: =IF(J26="Drilling",AF26,IF(J26="Face Milling",AR26,IF(J26="Pocket Milling",BD26,IF(J26="Turning",BN26,IF(J26="Tapping",BW26,IF(J26="Boring",CG26,IF(J26="Chamfering",5,IF(J26="Spot facing",10,IF(J26="Hobbing",CT26,IF(J26="Gear grinding",DF26,IF(J26="Internal Grinding",DQ26,IF(J26="External Grinding",EB26,IF(J26="Surface grinding",EJ26,0))))))))))))) -> 0 | U26: =I26/3600*T26 -> 0 | V26: =U26*F26 -> 0 | X26: =T26*F26 -> 0 | Y26: =K26 -> 0 | Z26: =L26+Y26*0.3 -> 0 | AA26: =VLOOKUP(Y$23,$K$3:$S$17,HLOOKUP(VLOOKUP(B26,B:H,7,0),$3:$4,2,0),0) -> #N/A | AB26: =MIN(IFERROR(AA26*1000/(PI()*Y26),0),5000) -> 0 | AC26: =IF(K26<15,0.05,0.1) -> 0.05 | AD26: =IFERROR((Z26+3)/(AB26*AC26/60),0) -> 0 | AE26: 5 | AF26: =AD26+AE26 -> 5 | AH26: =K26 -> 0 | AI26: =L26 -> 0 | AJ26: =M26 -> 0 | AK26: =N26 -> 0 | AL26: =O26 -> 0 | AM26: =VLOOKUP(AH$23,$K$3:$S$17,HLOOKUP(VLOOKUP(B26,B:H,7,0),$3:$4,2,0),0) -> #N/A | AN26: =MIN(IFERROR((AM26*1000/(PI()*AH26)),0),5000) -> 0 | AO26: =0.05*AL26 -> 0 | AP26: =IFERROR(((AI26+(AH26+10)+IF(AJ26<AH26,0,((CEILING(AJ26/AH26,1)-1)*AI26)+((CEILING(AJ26/AH26,1)-1)*AH26)))/(AO26*AN26/60)),0)*AK26 -> 0 | AQ26: 5 | AR26: =AP26+AQ26 -> 5 | AT26: =K26 -> 0 | AU26: =L26 -> 0 | AV26: =M26 -> 0 | AW26: =N26 -> 0 | AX26: =O26 -> 0 | AY26: =VLOOKUP(AT$23,$K$3:$S$17,HLOOKUP(VLOOKUP(B26,B:H,7,0),$3:$4,2,0),0) -> #N/A | AZ26: =MIN(IFERROR((AY26*1000/(PI()*AT26)),0),5000) -> 0 | BA26: =0.03*AX26 -> 0 | BB26: =IFERROR(((AU26+(AT26+10)+IF(AV26<AT26,0,((CEILING(AV26/AT26,1)-1)*AU26)+((CEILING(AV26/AT26,1)-1)*AT26)))/(BA26*AZ26/60)),0)*AW26 -> 0 | BC26: 5 | BD26: =BB26+BC26 -> 5 | BF26: =K26 -> 0 | BG26: =L26 -> 0 | BH26: =N26 -> 0 | BI26: =VLOOKUP(BF$23,$K$3:$S$17,HLOOKUP(VLOOKUP(B26,B:H,7,0),$3:$4,2,0),0) -> #N/A | BJ26: =MIN(IFERROR(BI26*1000/(PI()*BF26),0),5000) -> 0 | BK26: 0.1 | BL26: =IFERROR((BG26+3)/(BJ26*BK26/60),0)*BH26 -> 0 | BM26: 2 | BN26: =BL26+BM26 -> 2 | BP26: =K26 -> 0 | BQ26: =L26 -> 0 | BR26: =P26 -> 0 | BS26: =VLOOKUP(BP$23,$K$3:$S$17,HLOOKUP(VLOOKUP(B26,B:H,7,0),$3:$4,2,0),0) -> #N/A | BT26: =MIN(IFERROR(BS26*1000/(PI()*BP26),0),400) -> 0 | BU26: =IFERROR((BQ26+3)/(BT26*BR26/60),0)*2 -> 0 | BV26: 5 | BW26: =BU26+BV26 -> 5 | BY26: =K26 -> 0 | BZ26: =L26 -> 0 | CA26: =N26 -> 0 | CB26: =VLOOKUP(BY$23,$K$3:$S$17,HLOOKUP(VLOOKUP(B26,B:H,7,0),$3:$4,2,0),0) -> #N/A | CC26: =MIN(IFERROR(CB26*1000/(PI()*BY26),0),5000) -> 0 | CD26: 0.05 | CE26: =IFERROR((BZ26+3)/(CC26*CD26/60),0)*CA26 -> 0 | CF26: 5 | CG26: =CE26+CF26 -> 5 | CI26: =K26 -> 0 | CJ26: =L26 -> 0 | CK26: =R26 -> 0 | CL26: =VLOOKUP(CI$23,$K$3:$S$17,HLOOKUP(VLOOKUP(B26,B:H,7,0),$3:$4,2,0),0) -> #N/A | CM26: =MIN(IFERROR(CL26*1000/(PI()*CP26),0),5000) -> 0 | CN26: =Q26 -> 0 | CO26: =S26 -> 0 | CP26: =9.7903*CO26+41.578 -> 41.578 | CQ26: 1.5 | CR26: =IFERROR((((SQRT((CP26*CK26-CK26^2))+CJ26+5)*CN26)/(CM26*CQ26))*60,0) -> 0 | CS26: 5 | CT26: =CR26+CS26 -> 5 | CV26: =K26 -> 0 | CW26: =L26 -> 0 | CX26: =R26 -> 0 | CY26: =VLOOKUP(CV$23,$K$3:$S$17,HLOOKUP(VLOOKUP(B26,B:H,7,0),$3:$4,2,0),0) -> #N/A | CZ26: =MIN(IFERROR(CY26*1000/(PI()*DA26),0),5000) -> 0 | DA26: 300 | DB26: =Q26 -> 0 | DC26: 0.4 | DD26: =IFERROR((((SQRT((DA26*CX26-CX26^2))+CW26+5)*DB26)/(DC26*CZ26))*60,0) -> 0 | DE26: 5 | DF26: =DD26+DE26 -> 5 | DH26: =K26 -> 0 | DI26: =L26 -> 0 | DJ26: 12 | DK26: 30 | DL26: 15 | DM26: =MIN(IFERROR(DL26*1000/(PI()*DH26),0),5000) -> 0 | DN26: =DK26/2 -> 15 | DO26: =IFERROR(((DI26+DK26)*2)/(DM26*DN26/60),0)*DJ26 -> 0 | DP26: 5 | DQ26: =DO26+DP26 -> 5 | DS26: =K26 -> 0 | DT26: =L26 -> 0 | DU26: 12 | DV26: 30 | DW26: 15 | DX26: =MIN(IFERROR(DW26*1000/(PI()*DS26),0),5000) -> 0 | DY26: =DV26/2 -> 15 | DZ26: =IFERROR(((DT26+DV26)*2)/(DX26*DY26/60),0)*DU26 -> 0 | EA26: 5 | EB26: =DZ26+EA26 -> 5 | EE26: =L26 -> 0 | EF26: =M26 -> 0 | EG26: 30 | EH26: =(EE26+30)/500*CEILING((EF26+EG26+3)/(EG26/6),INT(EG26/6))*4+(EE26+30)/500*CEILING((EF26+EG26+3)/(EG26/10),INT(EG26/10)) -> 3.12 | EI26: 3 | EJ26: =EH26+EI26 -> 6.12
B27: =B26 -> 0 | C27: =_xlfn.IFNA(VLOOKUP(B27,BOM!$D$1:$H$10000,5,0),"") | T27: =IF(J27="Drilling",AF27,IF(J27="Face Milling",AR27,IF(J27="Pocket Milling",BD27,IF(J27="Turning",BN27,IF(J27="Tapping",BW27,IF(J27="Boring",CG27,IF(J27="Chamfering",5,IF(J27="Spot facing",10,IF(J27="Hobbing",CT27,IF(J27="Gear grinding",DF27,IF(J27="Internal Grinding",DQ27,IF(J27="External Grinding",EB27,IF(J27="Surface grinding",EJ27,0))))))))))))) -> 0 | U27: =I27/3600*T27 -> 0 | V27: =U27*F27 -> 0 | X27: =T27*F27 -> 0 | Y27: =K27 -> 0 | Z27: =L27+Y27*0.3 -> 0 | AA27: =VLOOKUP(Y$23,$K$3:$S$17,HLOOKUP(VLOOKUP(B27,B:H,7,0),$3:$4,2,0),0) -> #N/A | AB27: =MIN(IFERROR(AA27*1000/(PI()*Y27),0),5000) -> 0 | AC27: =IF(K27<15,0.05,0.1) -> 0.05 | AD27: =IFERROR((Z27+3)/(AB27*AC27/60),0) -> 0 | AE27: 5 | AF27: =AD27+AE27 -> 5 | AH27: =K27 -> 0 | AI27: =L27 -> 0 | AJ27: =M27 -> 0 | AK27: =N27 -> 0 | AL27: =O27 -> 0 | AM27: =VLOOKUP(AH$23,$K$3:$S$17,HLOOKUP(VLOOKUP(B27,B:H,7,0),$3:$4,2,0),0) -> #N/A | AN27: =MIN(IFERROR((AM27*1000/(PI()*AH27)),0),5000) -> 0 | AO27: =0.05*AL27 -> 0 | AP27: =IFERROR(((AI27+(AH27+10)+IF(AJ27<AH27,0,((CEILING(AJ27/AH27,1)-1)*AI27)+((CEILING(AJ27/AH27,1)-1)*AH27)))/(AO27*AN27/60)),0)*AK27 -> 0 | AQ27: 5 | AR27: =AP27+AQ27 -> 5 | AT27: =K27 -> 0 | AU27: =L27 -> 0 | AV27: =M27 -> 0 | AW27: =N27 -> 0 | AX27: =O27 -> 0 | AY27: =VLOOKUP(AT$23,$K$3:$S$17,HLOOKUP(VLOOKUP(B27,B:H,7,0),$3:$4,2,0),0) -> #N/A | AZ27: =MIN(IFERROR((AY27*1000/(PI()*AT27)),0),5000) -> 0 | BA27: =0.03*AX27 -> 0 | BB27: =IFERROR(((AU27+(AT27+10)+IF(AV27<AT27,0,((CEILING(AV27/AT27,1)-1)*AU27)+((CEILING(AV27/AT27,1)-1)*AT27)))/(BA27*AZ27/60)),0)*AW27 -> 0 | BC27: 5 | BD27: =BB27+BC27 -> 5 | BF27: =K27 -> 0 | BG27: =L27 -> 0 | BH27: =N27 -> 0 | BI27: =VLOOKUP(BF$23,$K$3:$S$17,HLOOKUP(VLOOKUP(B27,B:H,7,0),$3:$4,2,0),0) -> #N/A | BJ27: =MIN(IFERROR(BI27*1000/(PI()*BF27),0),5000) -> 0 | BK27: 0.1 | BL27: =IFERROR((BG27+3)/(BJ27*BK27/60),0)*BH27 -> 0 | BM27: 2 | BN27: =BL27+BM27 -> 2 | BP27: =K27 -> 0 | BQ27: =L27 -> 0 | BR27: =P27 -> 0 | BS27: =VLOOKUP(BP$23,$K$3:$S$17,HLOOKUP(VLOOKUP(B27,B:H,7,0),$3:$4,2,0),0) -> #N/A | BT27: =MIN(IFERROR(BS27*1000/(PI()*BP27),0),400) -> 0 | BU27: =IFERROR((BQ27+3)/(BT27*BR27/60),0)*2 -> 0 | BV27: 5 | BW27: =BU27+BV27 -> 5 | BY27: =K27 -> 0 | BZ27: =L27 -> 0 | CA27: =N27 -> 0 | CB27: =VLOOKUP(BY$23,$K$3:$S$17,HLOOKUP(VLOOKUP(B27,B:H,7,0),$3:$4,2,0),0) -> #N/A | CC27: =MIN(IFERROR(CB27*1000/(PI()*BY27),0),5000) -> 0 | CD27: 0.05 | CE27: =IFERROR((BZ27+3)/(CC27*CD27/60),0)*CA27 -> 0 | CF27: 5 | CG27: =CE27+CF27 -> 5 | CI27: =K27 -> 0 | CJ27: =L27 -> 0 | CK27: =R27 -> 0 | CL27: =VLOOKUP(CI$23,$K$3:$S$17,HLOOKUP(VLOOKUP(B27,B:H,7,0),$3:$4,2,0),0) -> #N/A | CM27: =MIN(IFERROR(CL27*1000/(PI()*CP27),0),5000) -> 0 | CN27: =Q27 -> 0 | CO27: =S27 -> 0 | CP27: =9.7903*CO27+41.578 -> 41.578 | CQ27: 1.5 | CR27: =IFERROR((((SQRT((CP27*CK27-CK27^2))+CJ27+5)*CN27)/(CM27*CQ27))*60,0) -> 0 | CS27: 5 | CT27: =CR27+CS27 -> 5 | CV27: =K27 -> 0 | CW27: =L27 -> 0 | CX27: =R27 -> 0 | CY27: =VLOOKUP(CV$23,$K$3:$S$17,HLOOKUP(VLOOKUP(B27,B:H,7,0),$3:$4,2,0),0) -> #N/A | CZ27: =MIN(IFERROR(CY27*1000/(PI()*DA27),0),5000) -> 0 | DA27: 300 | DB27: =Q27 -> 0 | DC27: 0.4 | DD27: =IFERROR((((SQRT((DA27*CX27-CX27^2))+CW27+5)*DB27)/(DC27*CZ27))*60,0) -> 0 | DE27: 5 | DF27: =DD27+DE27 -> 5 | DH27: =K27 -> 0 | DI27: =L27 -> 0 | DJ27: 12 | DK27: 30 | DL27: 15 | DM27: =MIN(IFERROR(DL27*1000/(PI()*DH27),0),5000) -> 0 | DN27: =DK27/2 -> 15 | DO27: =IFERROR(((DI27+DK27)*2)/(DM27*DN27/60),0)*DJ27 -> 0 | DP27: 5 | DQ27: =DO27+DP27 -> 5 | DS27: =K27 -> 0 | DT27: =L27 -> 0 | DU27: 12 | DV27: 30 | DW27: 15 | DX27: =MIN(IFERROR(DW27*1000/(PI()*DS27),0),5000) -> 0 | DY27: =DV27/2 -> 15 | DZ27: =IFERROR(((DT27+DV27)*2)/(DX27*DY27/60),0)*DU27 -> 0 | EA27: 5 | EB27: =DZ27+EA27 -> 5 | EE27: =L27 -> 0 | EF27: =M27 -> 0 | EG27: 30 | EH27: =(EE27+30)/500*CEILING((EF27+EG27+3)/(EG27/6),INT(EG27/6))*4+(EE27+30)/500*CEILING((EF27+EG27+3)/(EG27/10),INT(EG27/10)) -> 3.12 | EI27: 3 | EJ27: =EH27+EI27 -> 6.12
B28: =B27 -> 0 | C28: =_xlfn.IFNA(VLOOKUP(B28,BOM!$D$1:$H$10000,5,0),"") | T28: =IF(J28="Drilling",AF28,IF(J28="Face Milling",AR28,IF(J28="Pocket Milling",BD28,IF(J28="Turning",BN28,IF(J28="Tapping",BW28,IF(J28="Boring",CG28,IF(J28="Chamfering",5,IF(J28="Spot facing",10,IF(J28="Hobbing",CT28,IF(J28="Gear grinding",DF28,IF(J28="Internal Grinding",DQ28,IF(J28="External Grinding",EB28,IF(J28="Surface grinding",EJ28,0))))))))))))) -> 0 | U28: =I28/3600*T28 -> 0 | V28: =U28*F28 -> 0 | X28: =T28*F28 -> 0 | Y28: =K28 -> 0 | Z28: =L28+Y28*0.3 -> 0 | AA28: =VLOOKUP(Y$23,$K$3:$S$17,HLOOKUP(VLOOKUP(B28,B:H,7,0),$3:$4,2,0),0) -> #N/A | AB28: =MIN(IFERROR(AA28*1000/(PI()*Y28),0),5000) -> 0 | AC28: =IF(K28<15,0.05,0.1) -> 0.05 | AD28: =IFERROR((Z28+3)/(AB28*AC28/60),0) -> 0 | AE28: 5 | AF28: =AD28+AE28 -> 5 | AH28: =K28 -> 0 | AI28: =L28 -> 0 | AJ28: =M28 -> 0 | AK28: =N28 -> 0 | AL28: =O28 -> 0 | AM28: =VLOOKUP(AH$23,$K$3:$S$17,HLOOKUP(VLOOKUP(B28,B:H,7,0),$3:$4,2,0),0) -> #N/A | AN28: =MIN(IFERROR((AM28*1000/(PI()*AH28)),0),5000) -> 0 | AO28: =0.05*AL28 -> 0 | AP28: =IFERROR(((AI28+(AH28+10)+IF(AJ28<AH28,0,((CEILING(AJ28/AH28,1)-1)*AI28)+((CEILING(AJ28/AH28,1)-1)*AH28)))/(AO28*AN28/60)),0)*AK28 -> 0 | AQ28: 5 | AR28: =AP28+AQ28 -> 5 | AT28: =K28 -> 0 | AU28: =L28 -> 0 | AV28: =M28 -> 0 | AW28: =N28 -> 0 | AX28: =O28 -> 0 | AY28: =VLOOKUP(AT$23,$K$3:$S$17,HLOOKUP(VLOOKUP(B28,B:H,7,0),$3:$4,2,0),0) -> #N/A | AZ28: =MIN(IFERROR((AY28*1000/(PI()*AT28)),0),5000) -> 0 | BA28: =0.03*AX28 -> 0 | BB28: =IFERROR(((AU28+(AT28+10)+IF(AV28<AT28,0,((CEILING(AV28/AT28,1)-1)*AU28)+((CEILING(AV28/AT28,1)-1)*AT28)))/(BA28*AZ28/60)),0)*AW28 -> 0 | BC28: 5 | BD28: =BB28+BC28 -> 5 | BF28: =K28 -> 0 | BG28: =L28 -> 0 | BH28: =N28 -> 0 | BI28: =VLOOKUP(BF$23,$K$3:$S$17,HLOOKUP(VLOOKUP(B28,B:H,7,0),$3:$4,2,0),0) -> #N/A | BJ28: =MIN(IFERROR(BI28*1000/(PI()*BF28),0),5000) -> 0 | BK28: 0.1 | BL28: =IFERROR((BG28+3)/(BJ28*BK28/60),0)*BH28 -> 0 | BM28: 2 | BN28: =BL28+BM28 -> 2 | BP28: =K28 -> 0 | BQ28: =L28 -> 0 | BR28: =P28 -> 0 | BS28: =VLOOKUP(BP$23,$K$3:$S$17,HLOOKUP(VLOOKUP(B28,B:H,7,0),$3:$4,2,0),0) -> #N/A | BT28: =MIN(IFERROR(BS28*1000/(PI()*BP28),0),400) -> 0 | BU28: =IFERROR((BQ28+3)/(BT28*BR28/60),0)*2 -> 0 | BV28: 5 | BW28: =BU28+BV28 -> 5 | BY28: =K28 -> 0 | BZ28: =L28 -> 0 | CA28: =N28 -> 0 | CB28: =VLOOKUP(BY$23,$K$3:$S$17,HLOOKUP(VLOOKUP(B28,B:H,7,0),$3:$4,2,0),0) -> #N/A | CC28: =MIN(IFERROR(CB28*1000/(PI()*BY28),0),5000) -> 0 | CD28: 0.05 | CE28: =IFERROR((BZ28+3)/(CC28*CD28/60),0)*CA28 -> 0 | CF28: 5 | CG28: =CE28+CF28 -> 5 | CI28: =K28 -> 0 | CJ28: =L28 -> 0 | CK28: =R28 -> 0 | CL28: =VLOOKUP(CI$23,$K$3:$S$17,HLOOKUP(VLOOKUP(B28,B:H,7,0),$3:$4,2,0),0) -> #N/A | CM28: =MIN(IFERROR(CL28*1000/(PI()*CP28),0),5000) -> 0 | CN28: =Q28 -> 0 | CO28: =S28 -> 0 | CP28: =9.7903*CO28+41.578 -> 41.578 | CQ28: 1.5 | CR28: =IFERROR((((SQRT((CP28*CK28-CK28^2))+CJ28+5)*CN28)/(CM28*CQ28))*60,0) -> 0 | CS28: 5 | CT28: =CR28+CS28 -> 5 | CV28: =K28 -> 0 | CW28: =L28 -> 0 | CX28: =R28 -> 0 | CY28: =VLOOKUP(CV$23,$K$3:$S$17,HLOOKUP(VLOOKUP(B28,B:H,7,0),$3:$4,2,0),0) -> #N/A | CZ28: =MIN(IFERROR(CY28*1000/(PI()*DA28),0),5000) -> 0 | DA28: 300 | DB28: =Q28 -> 0 | DC28: 0.4 | DD28: =IFERROR((((SQRT((DA28*CX28-CX28^2))+CW28+5)*DB28)/(DC28*CZ28))*60,0) -> 0 | DE28: 5 | DF28: =DD28+DE28 -> 5 | DH28: =K28 -> 0 | DI28: =L28 -> 0 | DJ28: 12 | DK28: 30 | DL28: 15 | DM28: =MIN(IFERROR(DL28*1000/(PI()*DH28),0),5000) -> 0 | DN28: =DK28/2 -> 15 | DO28: =IFERROR(((DI28+DK28)*2)/(DM28*DN28/60),0)*DJ28 -> 0 | DP28: 5 | DQ28: =DO28+DP28 -> 5 | DS28: =K28 -> 0 | DT28: =L28 -> 0 | DU28: 12 | DV28: 30 | DW28: 15 | DX28: =MIN(IFERROR(DW28*1000/(PI()*DS28),0),5000) -> 0 | DY28: =DV28/2 -> 15 | DZ28: =IFERROR(((DT28+DV28)*2)/(DX28*DY28/60),0)*DU28 -> 0 | EA28: 5 | EB28: =DZ28+EA28 -> 5 | EE28: =L28 -> 0 | EF28: =M28 -> 0 | EG28: 30 | EH28: =(EE28+30)/500*CEILING((EF28+EG28+3)/(EG28/6),INT(EG28/6))*4+(EE28+30)/500*CEILING((EF28+EG28+3)/(EG28/10),INT(EG28/10)) -> 3.12 | EI28: 3 | EJ28: =EH28+EI28 -> 6.12
B29: =B28 -> 0 | C29: =_xlfn.IFNA(VLOOKUP(B29,BOM!$D$1:$H$10000,5,0),"") | T29: =IF(J29="Drilling",AF29,IF(J29="Face Milling",AR29,IF(J29="Pocket Milling",BD29,IF(J29="Turning",BN29,IF(J29="Tapping",BW29,IF(J29="Boring",CG29,IF(J29="Chamfering",5,IF(J29="Spot facing",10,IF(J29="Hobbing",CT29,IF(J29="Gear grinding",DF29,IF(J29="Internal Grinding",DQ29,IF(J29="External Grinding",EB29,IF(J29="Surface grinding",EJ29,0))))))))))))) -> 0 | U29: =I29/3600*T29 -> 0 | V29: =U29*F29 -> 0 | X29: =T29*F29 -> 0 | Y29: =K29 -> 0 | Z29: =L29+Y29*0.3 -> 0 | AA29: =VLOOKUP(Y$23,$K$3:$S$17,HLOOKUP(VLOOKUP(B29,B:H,7,0),$3:$4,2,0),0) -> #N/A | AB29: =MIN(IFERROR(AA29*1000/(PI()*Y29),0),5000) -> 0 | AC29: =IF(K29<15,0.05,0.1) -> 0.05 | AD29: =IFERROR((Z29+3)/(AB29*AC29/60),0) -> 0 | AE29: 5 | AF29: =AD29+AE29 -> 5 | AH29: =K29 -> 0 | AI29: =L29 -> 0 | AJ29: =M29 -> 0 | AK29: =N29 -> 0 | AL29: =O29 -> 0 | AM29: =VLOOKUP(AH$23,$K$3:$S$17,HLOOKUP(VLOOKUP(B29,B:H,7,0),$3:$4,2,0),0) -> #N/A | AN29: =MIN(IFERROR((AM29*1000/(PI()*AH29)),0),5000) -> 0 | AO29: =0.05*AL29 -> 0 | AP29: =IFERROR(((AI29+(AH29+10)+IF(AJ29<AH29,0,((CEILING(AJ29/AH29,1)-1)*AI29)+((CEILING(AJ29/AH29,1)-1)*AH29)))/(AO29*AN29/60)),0)*AK29 -> 0 | AQ29: 5 | AR29: =AP29+AQ29 -> 5 | AT29: =K29 -> 0 | AU29: =L29 -> 0 | AV29: =M29 -> 0 | AW29: =N29 -> 0 | AX29: =O29 -> 0 | AY29: =VLOOKUP(AT$23,$K$3:$S$17,HLOOKUP(VLOOKUP(B29,B:H,7,0),$3:$4,2,0),0) -> #N/A | AZ29: =MIN(IFERROR((AY29*1000/(PI()*AT29)),0),5000) -> 0 | BA29: =0.03*AX29 -> 0 | BB29: =IFERROR(((AU29+(AT29+10)+IF(AV29<AT29,0,((CEILING(AV29/AT29,1)-1)*AU29)+((CEILING(AV29/AT29,1)-1)*AT29)))/(BA29*AZ29/60)),0)*AW29 -> 0 | BC29: 5 | BD29: =BB29+BC29 -> 5 | BF29: =K29 -> 0 | BG29: =L29 -> 0 | BH29: =N29 -> 0 | BI29: =VLOOKUP(BF$23,$K$3:$S$17,HLOOKUP(VLOOKUP(B29,B:H,7,0),$3:$4,2,0),0) -> #N/A | BJ29: =MIN(IFERROR(BI29*1000/(PI()*BF29),0),5000) -> 0 | BK29: 0.1 | BL29: =IFERROR((BG29+3)/(BJ29*BK29/60),0)*BH29 -> 0 | BM29: 2 | BN29: =BL29+BM29 -> 2 | BP29: =K29 -> 0 | BQ29: =L29 -> 0 | BR29: =P29 -> 0 | BS29: =VLOOKUP(BP$23,$K$3:$S$17,HLOOKUP(VLOOKUP(B29,B:H,7,0),$3:$4,2,0),0) -> #N/A | BT29: =MIN(IFERROR(BS29*1000/(PI()*BP29),0),400) -> 0 | BU29: =IFERROR((BQ29+3)/(BT29*BR29/60),0)*2 -> 0 | BV29: 5 | BW29: =BU29+BV29 -> 5 | BY29: =K29 -> 0 | BZ29: =L29 -> 0 | CA29: =N29 -> 0 | CB29: =VLOOKUP(BY$23,$K$3:$S$17,HLOOKUP(VLOOKUP(B29,B:H,7,0),$3:$4,2,0),0) -> #N/A | CC29: =MIN(IFERROR(CB29*1000/(PI()*BY29),0),5000) -> 0 | CD29: 0.05 | CE29: =IFERROR((BZ29+3)/(CC29*CD29/60),0)*CA29 -> 0 | CF29: 5 | CG29: =CE29+CF29 -> 5 | CI29: =K29 -> 0 | CJ29: =L29 -> 0 | CK29: =R29 -> 0 | CL29: =VLOOKUP(CI$23,$K$3:$S$17,HLOOKUP(VLOOKUP(B29,B:H,7,0),$3:$4,2,0),0) -> #N/A | CM29: =MIN(IFERROR(CL29*1000/(PI()*CP29),0),5000) -> 0 | CN29: =Q29 -> 0 | CO29: =S29 -> 0 | CP29: =9.7903*CO29+41.578 -> 41.578 | CQ29: 1.5 | CR29: =IFERROR((((SQRT((CP29*CK29-CK29^2))+CJ29+5)*CN29)/(CM29*CQ29))*60,0) -> 0 | CS29: 5 | CT29: =CR29+CS29 -> 5 | CV29: =K29 -> 0 | CW29: =L29 -> 0 | CX29: =R29 -> 0 | CY29: =VLOOKUP(CV$23,$K$3:$S$17,HLOOKUP(VLOOKUP(B29,B:H,7,0),$3:$4,2,0),0) -> #N/A | CZ29: =MIN(IFERROR(CY29*1000/(PI()*DA29),0),5000) -> 0 | DA29: 300 | DB29: =Q29 -> 0 | DC29: 0.4 | DD29: =IFERROR((((SQRT((DA29*CX29-CX29^2))+CW29+5)*DB29)/(DC29*CZ29))*60,0) -> 0 | DE29: 5 | DF29: =DD29+DE29 -> 5 | DH29: =K29 -> 0 | DI29: =L29 -> 0 | DJ29: 12 | DK29: 30 | DL29: 15 | DM29: =MIN(IFERROR(DL29*1000/(PI()*DH29),0),5000) -> 0 | DN29: =DK29/2 -> 15 | DO29: =IFERROR(((DI29+DK29)*2)/(DM29*DN29/60),0)*DJ29 -> 0 | DP29: 5 | DQ29: =DO29+DP29 -> 5 | DS29: =K29 -> 0 | DT29: =L29 -> 0 | DU29: 12 | DV29: 30 | DW29: 15 | DX29: =MIN(IFERROR(DW29*1000/(PI()*DS29),0),5000) -> 0 | DY29: =DV29/2 -> 15 | DZ29: =IFERROR(((DT29+DV29)*2)/(DX29*DY29/60),0)*DU29 -> 0 | EA29: 5 | EB29: =DZ29+EA29 -> 5 | EE29: =L29 -> 0 | EF29: =M29 -> 0 | EG29: 30 | EH29: =(EE29+30)/500*CEILING((EF29+EG29+3)/(EG29/6),INT(EG29/6))*4+(EE29+30)/500*CEILING((EF29+EG29+3)/(EG29/10),INT(EG29/10)) -> 3.12 | EI29: 3 | EJ29: =EH29+EI29 -> 6.12
B30: =B29 -> 0 | C30: =_xlfn.IFNA(VLOOKUP(B30,BOM!$D$1:$H$10000,5,0),"") | T30: =IF(J30="Drilling",AF30,IF(J30="Face Milling",AR30,IF(J30="Pocket Milling",BD30,IF(J30="Turning",BN30,IF(J30="Tapping",BW30,IF(J30="Boring",CG30,IF(J30="Chamfering",5,IF(J30="Spot facing",10,IF(J30="Hobbing",CT30,IF(J30="Gear grinding",DF30,IF(J30="Internal Grinding",DQ30,IF(J30="External Grinding",EB30,IF(J30="Surface grinding",EJ30,0))))))))))))) -> 0 | U30: =I30/3600*T30 -> 0 | V30: =U30*F30 -> 0 | X30: =T30*F30 -> 0 | Y30: =K30 -> 0 | Z30: =L30+Y30*0.3 -> 0 | AA30: =VLOOKUP(Y$23,$K$3:$S$17,HLOOKUP(VLOOKUP(B30,B:H,7,0),$3:$4,2,0),0) -> #N/A | AB30: =MIN(IFERROR(AA30*1000/(PI()*Y30),0),5000) -> 0 | AC30: =IF(K30<15,0.05,0.1) -> 0.05 | AD30: =IFERROR((Z30+3)/(AB30*AC30/60),0) -> 0 | AE30: 5 | AF30: =AD30+AE30 -> 5 | AH30: =K30 -> 0 | AI30: =L30 -> 0 | AJ30: =M30 -> 0 | AK30: =N30 -> 0 | AL30: =O30 -> 0 | AM30: =VLOOKUP(AH$23,$K$3:$S$17,HLOOKUP(VLOOKUP(B30,B:H,7,0),$3:$4,2,0),0) -> #N/A | AN30: =MIN(IFERROR((AM30*1000/(PI()*AH30)),0),5000) -> 0 | AO30: =0.05*AL30 -> 0 | AP30: =IFERROR(((AI30+(AH30+10)+IF(AJ30<AH30,0,((CEILING(AJ30/AH30,1)-1)*AI30)+((CEILING(AJ30/AH30,1)-1)*AH30)))/(AO30*AN30/60)),0)*AK30 -> 0 | AQ30: 5 | AR30: =AP30+AQ30 -> 5 | AT30: =K30 -> 0 | AU30: =L30 -> 0 | AV30: =M30 -> 0 | AW30: =N30 -> 0 | AX30: =O30 -> 0 | AY30: =VLOOKUP(AT$23,$K$3:$S$17,HLOOKUP(VLOOKUP(B30,B:H,7,0),$3:$4,2,0),0) -> #N/A | AZ30: =MIN(IFERROR((AY30*1000/(PI()*AT30)),0),5000) -> 0 | BA30: =0.03*AX30 -> 0 | BB30: =IFERROR(((AU30+(AT30+10)+IF(AV30<AT30,0,((CEILING(AV30/AT30,1)-1)*AU30)+((CEILING(AV30/AT30,1)-1)*AT30)))/(BA30*AZ30/60)),0)*AW30 -> 0 | BC30: 5 | BD30: =BB30+BC30 -> 5 | BF30: =K30 -> 0 | BG30: =L30 -> 0 | BH30: =N30 -> 0 | BI30: =VLOOKUP(BF$23,$K$3:$S$17,HLOOKUP(VLOOKUP(B30,B:H,7,0),$3:$4,2,0),0) -> #N/A | BJ30: =MIN(IFERROR(BI30*1000/(PI()*BF30),0),5000) -> 0 | BK30: 0.1 | BL30: =IFERROR((BG30+3)/(BJ30*BK30/60),0)*BH30 -> 0 | BM30: 2 | BN30: =BL30+BM30 -> 2 | BP30: =K30 -> 0 | BQ30: =L30 -> 0 | BR30: =P30 -> 0 | BS30: =VLOOKUP(BP$23,$K$3:$S$17,HLOOKUP(VLOOKUP(B30,B:H,7,0),$3:$4,2,0),0) -> #N/A | BT30: =MIN(IFERROR(BS30*1000/(PI()*BP30),0),400) -> 0 | BU30: =IFERROR((BQ30+3)/(BT30*BR30/60),0)*2 -> 0 | BV30: 5 | BW30: =BU30+BV30 -> 5 | BY30: =K30 -> 0 | BZ30: =L30 -> 0 | CA30: =N30 -> 0 | CB30: =VLOOKUP(BY$23,$K$3:$S$17,HLOOKUP(VLOOKUP(B30,B:H,7,0),$3:$4,2,0),0) -> #N/A | CC30: =MIN(IFERROR(CB30*1000/(PI()*BY30),0),5000) -> 0 | CD30: 0.05 | CE30: =IFERROR((BZ30+3)/(CC30*CD30/60),0)*CA30 -> 0 | CF30: 5 | CG30: =CE30+CF30 -> 5 | CI30: =K30 -> 0 | CJ30: =L30 -> 0 | CK30: =R30 -> 0 | CL30: =VLOOKUP(CI$23,$K$3:$S$17,HLOOKUP(VLOOKUP(B30,B:H,7,0),$3:$4,2,0),0) -> #N/A | CM30: =MIN(IFERROR(CL30*1000/(PI()*CP30),0),5000) -> 0 | CN30: =Q30 -> 0 | CO30: =S30 -> 0 | CP30: =9.7903*CO30+41.578 -> 41.578 | CQ30: 1.5 | CR30: =IFERROR((((SQRT((CP30*CK30-CK30^2))+CJ30+5)*CN30)/(CM30*CQ30))*60,0) -> 0 | CS30: 5 | CT30: =CR30+CS30 -> 5 | CV30: =K30 -> 0 | CW30: =L30 -> 0 | CX30: =R30 -> 0 | CY30: =VLOOKUP(CV$23,$K$3:$S$17,HLOOKUP(VLOOKUP(B30,B:H,7,0),$3:$4,2,0),0) -> #N/A | CZ30: =MIN(IFERROR(CY30*1000/(PI()*DA30),0),5000) -> 0 | DA30: 300 | DB30: =Q30 -> 0 | DC30: 0.4 | DD30: =IFERROR((((SQRT((DA30*CX30-CX30^2))+CW30+5)*DB30)/(DC30*CZ30))*60,0) -> 0 | DE30: 5 | DF30: =DD30+DE30 -> 5 | DH30: =K30 -> 0 | DI30: =L30 -> 0 | DJ30: 12 | DK30: 30 | DL30: 15 | DM30: =MIN(IFERROR(DL30*1000/(PI()*DH30),0),5000) -> 0 | DN30: =DK30/2 -> 15 | DO30: =IFERROR(((DI30+DK30)*2)/(DM30*DN30/60),0)*DJ30 -> 0 | DP30: 5 | DQ30: =DO30+DP30 -> 5 | DS30: =K30 -> 0 | DT30: =L30 -> 0 | DU30: 12 | DV30: 30 | DW30: 15 | DX30: =MIN(IFERROR(DW30*1000/(PI()*DS30),0),5000) -> 0 | DY30: =DV30/2 -> 15 | DZ30: =IFERROR(((DT30+DV30)*2)/(DX30*DY30/60),0)*DU30 -> 0 | EA30: 5 | EB30: =DZ30+EA30 -> 5 | EE30: =L30 -> 0 | EF30: =M30 -> 0 | EG30: 30 | EH30: =(EE30+30)/500*CEILING((EF30+EG30+3)/(EG30/6),INT(EG30/6))*4+(EE30+30)/500*CEILING((EF30+EG30+3)/(EG30/10),INT(EG30/10)) -> 3.12 | EI30: 3 | EJ30: =EH30+EI30 -> 6.12
B31: =B30 -> 0 | C31: =_xlfn.IFNA(VLOOKUP(B31,BOM!$D$1:$H$10000,5,0),"") | E31: Unloading from the machine | F31: 1 | T31: =IF(J31="Drilling",AF31,IF(J31="Face Milling",AR31,IF(J31="Pocket Milling",BD31,IF(J31="Turning",BN31,IF(J31="Tapping",BW31,IF(J31="Boring",CG31,IF(J31="Chamfering",5,IF(J31="Spot facing",10,IF(J31="Hobbing",CT31,IF(J31="Gear grinding",DF31,IF(J31="Internal Grinding",DQ31,IF(J31="External Grinding",EB31,IF(J31="Surface grinding",EJ31,0))))))))))))) -> 0 | U31: =I31/3600*T31 -> 0 | V31: =U31*F31 -> 0 | X31: =T31*F31 -> 0 | Y31: =K31 -> 0 | Z31: =L31+Y31*0.3 -> 0 | AA31: =VLOOKUP(Y$23,$K$3:$S$17,HLOOKUP(VLOOKUP(B31,B:H,7,0),$3:$4,2,0),0) -> #N/A | AB31: =MIN(IFERROR(AA31*1000/(PI()*Y31),0),5000) -> 0 | AC31: =IF(K31<15,0.05,0.1) -> 0.05 | AD31: =IFERROR((Z31+3)/(AB31*AC31/60),0) -> 0 | AE31: 5 | AF31: =AD31+AE31 -> 5 | AH31: =K31 -> 0 | AI31: =L31 -> 0 | AJ31: =M31 -> 0 | AK31: =N31 -> 0 | AL31: =O31 -> 0 | AM31: =VLOOKUP(AH$23,$K$3:$S$17,HLOOKUP(VLOOKUP(B31,B:H,7,0),$3:$4,2,0),0) -> #N/A | AN31: =MIN(IFERROR((AM31*1000/(PI()*AH31)),0),5000) -> 0 | AO31: =0.05*AL31 -> 0 | AP31: =IFERROR(((AI31+(AH31+10)+IF(AJ31<AH31,0,((CEILING(AJ31/AH31,1)-1)*AI31)+((CEILING(AJ31/AH31,1)-1)*AH31)))/(AO31*AN31/60)),0)*AK31 -> 0 | AQ31: 5 | AR31: =AP31+AQ31 -> 5 | AT31: =K31 -> 0 | AU31: =L31 -> 0 | AV31: =M31 -> 0 | AW31: =N31 -> 0 | AX31: =O31 -> 0 | AY31: =VLOOKUP(AT$23,$K$3:$S$17,HLOOKUP(VLOOKUP(B31,B:H,7,0),$3:$4,2,0),0) -> #N/A | AZ31: =MIN(IFERROR((AY31*1000/(PI()*AT31)),0),5000) -> 0 | BA31: =0.03*AX31 -> 0 | BB31: =IFERROR(((AU31+(AT31+10)+IF(AV31<AT31,0,((CEILING(AV31/AT31,1)-1)*AU31)+((CEILING(AV31/AT31,1)-1)*AT31)))/(BA31*AZ31/60)),0)*AW31 -> 0 | BC31: 5 | BD31: =BB31+BC31 -> 5 | BF31: =K31 -> 0 | BG31: =L31 -> 0 | BH31: =N31 -> 0 | BI31: =VLOOKUP(BF$23,$K$3:$S$17,HLOOKUP(VLOOKUP(B31,B:H,7,0),$3:$4,2,0),0) -> #N/A | BJ31: =MIN(IFERROR(BI31*1000/(PI()*BF31),0),5000) -> 0 | BK31: 0.1 | BL31: =IFERROR((BG31+3)/(BJ31*BK31/60),0)*BH31 -> 0 | BM31: 2 | BN31: =BL31+BM31 -> 2 | BP31: =K31 -> 0 | BQ31: =L31 -> 0 | BR31: =P31 -> 0 | BS31: =VLOOKUP(BP$23,$K$3:$S$17,HLOOKUP(VLOOKUP(B31,B:H,7,0),$3:$4,2,0),0) -> #N/A | BT31: =MIN(IFERROR(BS31*1000/(PI()*BP31),0),400) -> 0 | BU31: =IFERROR((BQ31+3)/(BT31*BR31/60),0)*2 -> 0 | BV31: 5 | BW31: =BU31+BV31 -> 5 | BY31: =K31 -> 0 | BZ31: =L31 -> 0 | CA31: =N31 -> 0 | CB31: =VLOOKUP(BY$23,$K$3:$S$17,HLOOKUP(VLOOKUP(B31,B:H,7,0),$3:$4,2,0),0) -> #N/A | CC31: =MIN(IFERROR(CB31*1000/(PI()*BY31),0),5000) -> 0 | CD31: 0.05 | CE31: =IFERROR((BZ31+3)/(CC31*CD31/60),0)*CA31 -> 0 | CF31: 5 | CG31: =CE31+CF31 -> 5 | CI31: =K31 -> 0 | CJ31: =L31 -> 0 | CK31: =R31 -> 0 | CL31: =VLOOKUP(CI$23,$K$3:$S$17,HLOOKUP(VLOOKUP(B31,B:H,7,0),$3:$4,2,0),0) -> #N/A | CM31: =MIN(IFERROR(CL31*1000/(PI()*CP31),0),5000) -> 0 | CN31: =Q31 -> 0 | CO31: =S31 -> 0 | CP31: =9.7903*CO31+41.578 -> 41.578 | CQ31: 1.5 | CR31: =IFERROR((((SQRT((CP31*CK31-CK31^2))+CJ31+5)*CN31)/(CM31*CQ31))*60,0) -> 0 | CS31: 5 | CT31: =CR31+CS31 -> 5 | CV31: =K31 -> 0 | CW31: =L31 -> 0 | CX31: =R31 -> 0 | CY31: =VLOOKUP(CV$23,$K$3:$S$17,HLOOKUP(VLOOKUP(B31,B:H,7,0),$3:$4,2,0),0) -> #N/A | CZ31: =MIN(IFERROR(CY31*1000/(PI()*DA31),0),5000) -> 0 | DA31: 300 | DB31: =Q31 -> 0 | DC31: 0.4 | DD31: =IFERROR((((SQRT((DA31*CX31-CX31^2))+CW31+5)*DB31)/(DC31*CZ31))*60,0) -> 0 | DE31: 5 | DF31: =DD31+DE31 -> 5 | DH31: =K31 -> 0 | DI31: =L31 -> 0 | DJ31: 12 | DK31: 30 | DL31: 15 | DM31: =MIN(IFERROR(DL31*1000/(PI()*DH31),0),5000) -> 0 | DN31: =DK31/2 -> 15 | DO31: =IFERROR(((DI31+DK31)*2)/(DM31*DN31/60),0)*DJ31 -> 0 | DP31: 5 | DQ31: =DO31+DP31 -> 5 | DS31: =K31 -> 0 | DT31: =L31 -> 0 | DU31: 12 | DV31: 30 | DW31: 15 | DX31: =MIN(IFERROR(DW31*1000/(PI()*DS31),0),5000) -> 0 | DY31: =DV31/2 -> 15 | DZ31: =IFERROR(((DT31+DV31)*2)/(DX31*DY31/60),0)*DU31 -> 0 | EA31: 5 | EB31: =DZ31+EA31 -> 5 | EE31: =L31 -> 0 | EF31: =M31 -> 0 | EG31: 30 | EH31: =(EE31+30)/500*CEILING((EF31+EG31+3)/(EG31/6),INT(EG31/6))*4+(EE31+30)/500*CEILING((EF31+EG31+3)/(EG31/10),INT(EG31/10)) -> 3.12 | EI31: 3 | EJ31: =EH31+EI31 -> 6.12
B32: =B31 -> 0 | C32: =_xlfn.IFNA(VLOOKUP(B32,BOM!$D$1:$H$10000,5,0),"") | E32: Dressing | H32: Manual Process | V32: =IF(F32="","Please enter finished weight in qty column",IF(F32<1,1,F32*1)) -> Please enter finished weight in qty column | X32: =T32*F32 -> 0 | Y32: =K32 -> 0 | Z32: =L32+Y32*0.3 -> 0 | AA32: =VLOOKUP(Y$23,$K$3:$S$17,HLOOKUP(VLOOKUP(B32,B:H,7,0),$3:$4,2,0),0) -> #N/A | AB32: =MIN(IFERROR(AA32*1000/(PI()*Y32),0),5000) -> 0 | AC32: =IF(K32<15,0.05,0.1) -> 0.05 | AD32: =IFERROR((Z32+3)/(AB32*AC32/60),0) -> 0 | AE32: 5 | AF32: =AD32+AE32 -> 5 | AH32: =K32 -> 0 | AI32: =L32 -> 0 | AJ32: =M32 -> 0 | AK32: =N32 -> 0 | AL32: =O32 -> 0 | AM32: =VLOOKUP(AH$23,$K$3:$S$17,HLOOKUP(VLOOKUP(B32,B:H,7,0),$3:$4,2,0),0) -> #N/A | AN32: =MIN(IFERROR((AM32*1000/(PI()*AH32)),0),5000) -> 0 | AO32: =0.05*AL32 -> 0 | AP32: =IFERROR(((AI32+(AH32+10)+IF(AJ32<AH32,0,((CEILING(AJ32/AH32,1)-1)*AI32)+((CEILING(AJ32/AH32,1)-1)*AH32)))/(AO32*AN32/60)),0)*AK32 -> 0 | AQ32: 5 | AR32: =AP32+AQ32 -> 5 | AT32: =K32 -> 0 | AU32: =L32 -> 0 | AV32: =M32 -> 0 | AW32: =N32 -> 0 | AX32: =O32 -> 0 | AY32: =VLOOKUP(AT$23,$K$3:$S$17,HLOOKUP(VLOOKUP(B32,B:H,7,0),$3:$4,2,0),0) -> #N/A | AZ32: =MIN(IFERROR((AY32*1000/(PI()*AT32)),0),5000) -> 0 | BA32: =0.03*AX32 -> 0 | BB32: =IFERROR(((AU32+(AT32+10)+IF(AV32<AT32,0,((CEILING(AV32/AT32,1)-1)*AU32)+((CEILING(AV32/AT32,1)-1)*AT32)))/(BA32*AZ32/60)),0)*AW32 -> 0 | BC32: 5 | BD32: =BB32+BC32 -> 5 | BF32: =K32 -> 0 | BG32: =L32 -> 0 | BH32: =N32 -> 0 | BI32: =VLOOKUP(BF$23,$K$3:$S$17,HLOOKUP(VLOOKUP(B32,B:H,7,0),$3:$4,2,0),0) -> #N/A | BJ32: =MIN(IFERROR(BI32*1000/(PI()*BF32),0),5000) -> 0 | BK32: 0.1 | BL32: =IFERROR((BG32+3)/(BJ32*BK32/60),0)*BH32 -> 0 | BM32: 2 | BN32: =BL32+BM32 -> 2 | BP32: =K32 -> 0 | BQ32: =L32 -> 0 | BR32: =P32 -> 0 | BS32: =VLOOKUP(BP$23,$K$3:$S$17,HLOOKUP(VLOOKUP(B32,B:H,7,0),$3:$4,2,0),0) -> #N/A | BT32: =MIN(IFERROR(BS32*1000/(PI()*BP32),0),400) -> 0 | BU32: =IFERROR((BQ32+3)/(BT32*BR32/60),0)*2 -> 0 | BV32: 5 | BW32: =BU32+BV32 -> 5 | BY32: =K32 -> 0 | BZ32: =L32 -> 0 | CA32: =N32 -> 0 | CB32: =VLOOKUP(BY$23,$K$3:$S$17,HLOOKUP(VLOOKUP(B32,B:H,7,0),$3:$4,2,0),0) -> #N/A | CC32: =MIN(IFERROR(CB32*1000/(PI()*BY32),0),5000) -> 0 | CD32: 0.05 | CE32: =IFERROR((BZ32+3)/(CC32*CD32/60),0)*CA32 -> 0 | CF32: 5 | CG32: =CE32+CF32 -> 5 | CI32: =K32 -> 0 | CJ32: =L32 -> 0 | CK32: =R32 -> 0 | CL32: =VLOOKUP(CI$23,$K$3:$S$17,HLOOKUP(VLOOKUP(B32,B:H,7,0),$3:$4,2,0),0) -> #N/A | CM32: =MIN(IFERROR(CL32*1000/(PI()*CP32),0),5000) -> 0 | CN32: =Q32 -> 0 | CO32: =S32 -> 0 | CP32: =9.7903*CO32+41.578 -> 41.578 | CQ32: 1.5 | CR32: =IFERROR((((SQRT((CP32*CK32-CK32^2))+CJ32+5)*CN32)/(CM32*CQ32))*60,0) -> 0 | CS32: 5 | CT32: =CR32+CS32 -> 5 | CV32: =K32 -> 0 | CW32: =L32 -> 0 | CX32: =R32 -> 0 | CY32: =VLOOKUP(CV$23,$K$3:$S$17,HLOOKUP(VLOOKUP(B32,B:H,7,0),$3:$4,2,0),0) -> #N/A | CZ32: =MIN(IFERROR(CY32*1000/(PI()*DA32),0),5000) -> 0 | DA32: 300 | DB32: =Q32 -> 0 | DC32: 0.4 | DD32: =IFERROR((((SQRT((DA32*CX32-CX32^2))+CW32+5)*DB32)/(DC32*CZ32))*60,0) -> 0 | DE32: 5 | DF32: =DD32+DE32 -> 5 | DH32: =K32 -> 0 | DI32: =L32 -> 0 | DJ32: 12 | DK32: 30 | DL32: 15 | DM32: =MIN(IFERROR(DL32*1000/(PI()*DH32),0),5000) -> 0 | DN32: =DK32/2 -> 15 | DO32: =IFERROR(((DI32+DK32)*2)/(DM32*DN32/60),0)*DJ32 -> 0 | DP32: 5 | DQ32: =DO32+DP32 -> 5 | DS32: =K32 -> 0 | DT32: =L32 -> 0 | DU32: 12 | DV32: 30 | DW32: 15 | DX32: =MIN(IFERROR(DW32*1000/(PI()*DS32),0),5000) -> 0 | DY32: =DV32/2 -> 15 | DZ32: =IFERROR(((DT32+DV32)*2)/(DX32*DY32/60),0)*DU32 -> 0 | EA32: 5 | EB32: =DZ32+EA32 -> 5 | EE32: =L32 -> 0 | EF32: =M32 -> 0 | EG32: 30 | EH32: =(EE32+30)/500*CEILING((EF32+EG32+3)/(EG32/6),INT(EG32/6))*4+(EE32+30)/500*CEILING((EF32+EG32+3)/(EG32/10),INT(EG32/10)) -> 3.12 | EI32: 3 | EJ32: =EH32+EI32 -> 6.12
B33: =B32 -> 0 | C33: =_xlfn.IFNA(VLOOKUP(B33,BOM!$D$1:$H$10000,5,0),"") | E33: Packing, Storage& Despatch | H33: Manual Process | V33: =IF(F33="","Please enter finished weight in qty column",IF(F33<1,1,F33*1)) -> Please enter finished weight in qty column | X33: =T33*F33 -> 0 | Y33: =K33 -> 0 | Z33: =L33+Y33*0.3 -> 0 | AA33: =VLOOKUP(Y$23,$K$3:$S$17,HLOOKUP(VLOOKUP(B33,B:H,7,0),$3:$4,2,0),0) -> #N/A | AB33: =MIN(IFERROR(AA33*1000/(PI()*Y33),0),5000) -> 0 | AC33: =IF(K33<15,0.05,0.1) -> 0.05 | AD33: =IFERROR((Z33+3)/(AB33*AC33/60),0) -> 0 | AE33: 5 | AF33: =AD33+AE33 -> 5 | AH33: =K33 -> 0 | AI33: =L33 -> 0 | AJ33: =M33 -> 0 | AK33: =N33 -> 0 | AL33: =O33 -> 0 | AM33: =VLOOKUP(AH$23,$K$3:$S$17,HLOOKUP(VLOOKUP(B33,B:H,7,0),$3:$4,2,0),0) -> #N/A | AN33: =MIN(IFERROR((AM33*1000/(PI()*AH33)),0),5000) -> 0 | AO33: =0.05*AL33 -> 0 | AP33: =IFERROR(((AI33+(AH33+10)+IF(AJ33<AH33,0,((CEILING(AJ33/AH33,1)-1)*AI33)+((CEILING(AJ33/AH33,1)-1)*AH33)))/(AO33*AN33/60)),0)*AK33 -> 0 | AQ33: 5 | AR33: =AP33+AQ33 -> 5 | AT33: =K33 -> 0 | AU33: =L33 -> 0 | AV33: =M33 -> 0 | AW33: =N33 -> 0 | AX33: =O33 -> 0 | AY33: =VLOOKUP(AT$23,$K$3:$S$17,HLOOKUP(VLOOKUP(B33,B:H,7,0),$3:$4,2,0),0) -> #N/A | AZ33: =MIN(IFERROR((AY33*1000/(PI()*AT33)),0),5000) -> 0 | BA33: =0.03*AX33 -> 0 | BB33: =IFERROR(((AU33+(AT33+10)+IF(AV33<AT33,0,((CEILING(AV33/AT33,1)-1)*AU33)+((CEILING(AV33/AT33,1)-1)*AT33)))/(BA33*AZ33/60)),0)*AW33 -> 0 | BC33: 5 | BD33: =BB33+BC33 -> 5 | BF33: =K33 -> 0 | BG33: =L33 -> 0 | BH33: =N33 -> 0 | BI33: =VLOOKUP(BF$23,$K$3:$S$17,HLOOKUP(VLOOKUP(B33,B:H,7,0),$3:$4,2,0),0) -> #N/A | BJ33: =MIN(IFERROR(BI33*1000/(PI()*BF33),0),5000) -> 0 | BK33: 0.1 | BL33: =IFERROR((BG33+3)/(BJ33*BK33/60),0)*BH33 -> 0 | BM33: 2 | BN33: =BL33+BM33 -> 2 | BP33: =K33 -> 0 | BQ33: =L33 -> 0 | BR33: =P33 -> 0 | BS33: =VLOOKUP(BP$23,$K$3:$S$17,HLOOKUP(VLOOKUP(B33,B:H,7,0),$3:$4,2,0),0) -> #N/A | BT33: =MIN(IFERROR(BS33*1000/(PI()*BP33),0),400) -> 0 | BU33: =IFERROR((BQ33+3)/(BT33*BR33/60),0)*2 -> 0 | BV33: 5 | BW33: =BU33+BV33 -> 5 | BY33: =K33 -> 0 | BZ33: =L33 -> 0 | CA33: =N33 -> 0 | CB33: =VLOOKUP(BY$23,$K$3:$S$17,HLOOKUP(VLOOKUP(B33,B:H,7,0),$3:$4,2,0),0) -> #N/A | CC33: =MIN(IFERROR(CB33*1000/(PI()*BY33),0),5000) -> 0 | CD33: 0.05 | CE33: =IFERROR((BZ33+3)/(CC33*CD33/60),0)*CA33 -> 0 | CF33: 5 | CG33: =CE33+CF33 -> 5 | CI33: =K33 -> 0 | CJ33: =L33 -> 0 | CK33: =R33 -> 0 | CL33: =VLOOKUP(CI$23,$K$3:$S$17,HLOOKUP(VLOOKUP(B33,B:H,7,0),$3:$4,2,0),0) -> #N/A | CM33: =MIN(IFERROR(CL33*1000/(PI()*CP33),0),5000) -> 0 | CN33: =Q33 -> 0 | CO33: =S33 -> 0 | CP33: =9.7903*CO33+41.578 -> 41.578 | CQ33: 1.5 | CR33: =IFERROR((((SQRT((CP33*CK33-CK33^2))+CJ33+5)*CN33)/(CM33*CQ33))*60,0) -> 0 | CS33: 5 | CT33: =CR33+CS33 -> 5 | CV33: =K33 -> 0 | CW33: =L33 -> 0 | CX33: =R33 -> 0 | CY33: =VLOOKUP(CV$23,$K$3:$S$17,HLOOKUP(VLOOKUP(B33,B:H,7,0),$3:$4,2,0),0) -> #N/A | CZ33: =MIN(IFERROR(CY33*1000/(PI()*DA33),0),5000) -> 0 | DA33: 300 | DB33: =Q33 -> 0 | DC33: 0.4 | DD33: =IFERROR((((SQRT((DA33*CX33-CX33^2))+CW33+5)*DB33)/(DC33*CZ33))*60,0) -> 0 | DE33: 5 | DF33: =DD33+DE33 -> 5 | DH33: =K33 -> 0 | DI33: =L33 -> 0 | DJ33: 12 | DK33: 30 | DL33: 15 | DM33: =MIN(IFERROR(DL33*1000/(PI()*DH33),0),5000) -> 0 | DN33: =DK33/2 -> 15 | DO33: =IFERROR(((DI33+DK33)*2)/(DM33*DN33/60),0)*DJ33 -> 0 | DP33: 5 | DQ33: =DO33+DP33 -> 5 | DS33: =K33 -> 0 | DT33: =L33 -> 0 | DU33: 12 | DV33: 30 | DW33: 15 | DX33: =MIN(IFERROR(DW33*1000/(PI()*DS33),0),5000) -> 0 | DY33: =DV33/2 -> 15 | DZ33: =IFERROR(((DT33+DV33)*2)/(DX33*DY33/60),0)*DU33 -> 0 | EA33: 5 | EB33: =DZ33+EA33 -> 5 | EE33: =L33 -> 0 | EF33: =M33 -> 0 | EG33: 30 | EH33: =(EE33+30)/500*CEILING((EF33+EG33+3)/(EG33/6),INT(EG33/6))*4+(EE33+30)/500*CEILING((EF33+EG33+3)/(EG33/10),INT(EG33/10)) -> 3.12 | EI33: 3 | EJ33: =EH33+EI33 -> 6.12

Sheet SM_Material
A1: 1
S8: Developed Width of Rectangular / Square Tube
F9: Don’t edit Cell Filled with Grey colour | S9: B | T9: D | U9: Thickness | V9: Area of CS (mm2) | W9: Developed width
B10: Material | D10: D | F10: Fill the cell with Blue Colour if manual input done | S10: 50 | T10: 50 | U10: 2 | V10: =2*U10*((S10-4*U10)+(T10-4*U10)+(3/2*3.14*U10)) -> 373.68 | W10: =V10/U10 -> 186.84 | AD10: RM | AE10: =SUMIF($I$12:$I$9994,$AD10,$AE$12:$AE$9994) -> 4201.8736
F11: Cells that don't have any fills are required entries | AD11: BOP | AE11: =SUMIF($I$12:$I$9994,$AD11,$AE$12:$AE$9994) -> 20.5
B12: Parent part No. | C12: Level | D12: Part Number | E12: Rev | F12: Item Description | G12: CSC/Others | H12: Material Grade | I12: RM/BOP | J12: RM Price / Kg (INR) | K12: RM Type | L12: Length (mm) | M12: Width / Ø (mm) | N12: Thick (mm) | O12: RM Length (mm) | P12: RM Width / RM Ø (mm) | Q12: Shearing / Blanking / Laser cutting | R12: RM Weight (kg) | S12: No of Blanks per sheet | T12: Blank weight (Kg) | U12: Input Weight (Kg) | V12: Total Input Weight (Kg) | W12: Finish weight (Kg) | X12: Total Finish weight (Kg) | Y12: Yield | Z12: Surface Area / Part | AB12: Total Scrap wt (kg) | AC12: Scrap mat. Price | AD12: Recovery% | AE12: Price per unit (INR) | AF12: Remarks | AG12: Direct RM Cost | AH12: Allowance cost | AI12: Blank Length Including Scrap Bridge allowance | AJ12: Blank Width Including Scrap Bridge allowance | AK12: Blanks per sheet | AL12: Along Length | AM12: Along Width | AN12: Blank Length | AO12: Blank Width | AP12: No of Blanks along length | AQ12: No of Blanks along width | AR12: No of Blanks along length for BW | AS12: No of Blanks along width for BW | AT12: End bit along length-1250 | AU12: Endbit along width-2500 | AV12: End bit along length for BW-1250 | AW12: Endbit along width for BW-2500 | AX12: No of add blanks case1 | AY12: No of add blanks case2 | AZ12: No of add blanks case3 | BA12: No of add blanks case4 | BB12: No of blanks case1 | BC12: No of blanks case2 | BD12: No of blanks case3 | BE12: No of blanks case4 | BF12: Best No of Blanks | BG12: Min of 1st cut | BH12: Min of 2nd cut | BI12: Total cut for 1st shearing
B13: =_xlfn.IFNA(VLOOKUP(D13,Group!$AM$1:$AO$10000,3,0),"") -> FWR10000 | C13: =_xlfn.IFNA(VLOOKUP(D13,Group!$AM$1:$AO$10000,2,0),"") -> 3 | D13: =Group!K2 -> H 157 01 464 A Top Mounting Brkt LH &RH | E13: =_xlfn.IFNA(VLOOKUP(D13,BOM!$D$1:$F$10000,2,0),"") -> 0 | F13: =_xlfn.IFNA(VLOOKUP(D13,BOM!$D$1:$F$10000,3,0),"") -> Top Mounting Brkt LH &RH | G13: =_xlfn.IFNA(IF(VLOOKUP(D13,BOM!D:J,7,0)="CSC","CSC","Others"),"") -> CSC | H13: IS2062 | I13: =_xlfn.IFNA(IF(OR(VLOOKUP(D13,BOM!$D$1:$I$1000,6,0)="Inhouse",VLOOKUP(D13,BOM!$D$1:$J$1000,7,0)="CSC"),"RM","BOP"),"") -> RM | J13: =_xlfn.IFNA(IF(VLOOKUP(H13,'RM Base'!D:F,3,0)="Kg",VLOOKUP(H13,'RM Base'!D:E,2,0),IF(VLOOKUP(H13,'RM Base'!D:F,3,0)="Meter",(VLOOKUP(H13,'RM Base'!D:E,2,0)/R13*O13/1000),CONCATENATE("The Price is in ",VLOOKUP(H13,'RM Base'!D:F,3,0)))),"") -> 53 | K13: Sheet Metal | L13: 421 | M13: 90 | N13: 3.2 | O13: =IF(K13<>"",IF(OR(K13="Pipe", K13="Circular Tube", K13="Square/Rectangular Tube"),IF(ISNUMBER(SEARCH("ss", H13)), 5000, 6000),2500),"") -> 2500 | P13: =IF(OR(O13=6000,O13=5000,O13=""),M13,1250) -> 1250 | Q13: Blanking | R13: =IF(K13="Sheet Metal",O13*P13*N13*7.86/10^6,IF(OR(K13="Pipe", K13="Circular Tube"),O13*(P13^2-(P13-2*N13)^2)*3.14/4*7.86*10^-6,IF(K13="Square/Rectangular Tube",O13*P13*N13*7.86*10^-6,""))) -> 78.6 | S13: =IF(L13<>"",IF(OR(K13="Pipe", K13="Circular Tube"),INT(O13/(L13+5)),IF(K13="Square/Rectangular Tube",INT(O13/(L13+5)),IF(Q13="Laser Cutting",AK13,BF13))),"") -> 70 | T13: =IF(OR(K13="Pipe", K13="Circular Tube"),L13*(M13^2-(M13-2*N13)^2)*3.14/4*7.86*10^-6,IF(K13="Square/Rectangular Tube",L13*M13*N13*7.86*10^-6,IF(K13="Sheet Metal",L13*M13*N13*7.86*10^-6,""))) -> 0.95300928 | U13: =IFERROR(R13/S13,"") -> 1.1228571 | V13: =IFERROR(I13*U13,"") | W13: 0.87 | X13: =IF(W13="","",W13) -> 0.87 | Y13: =IF(U13="","",W13/U13) -> 0.77480916 | Z13: =IF(Y13="","",IF(I13="RM",IF(K13="Sheet Metal",W13/N13/7.86*2,IF(OR(K13="Pipe",K13="Circular Tube"),L13*PI()*M13/10^6,IF(K13="Square/Rectangular Tube",W13/N13/7.86,0))))) -> 0.069179389 | AB13: =IF(Z13="","",U13-W13) -> 0.25285714 | AC13: =_xlfn.IFNA(VLOOKUP(H13,'RM Base'!D:K,8,0),"") -> 30.5 | AD13: =IF(K13<>"",IF(K13="Sheet Metal",95%,80%),"") -> 0.95 | AE13: =IF(AD13="","",(J13*U13)-(AB13*AC13*AD13)) -> 52.184893 | AG13: =IFERROR(IF(I13="RM",(W13*J13),AE13),"") -> 46.11 | AH13: =IFERROR(AE13-AG13,"") -> 6.0748929 | AI13: =IF(Q13="Shearing",L13,IF(Q13="Blanking",(L13+N13*1.5),IF(Q13="Laser Cutting",(L13+4)))) -> 425.8 | AJ13: =IF(Q13="Shearing",M13,IF(Q13="Blanking",(M13+N13*3),IF(Q13="Laser Cutting",(M13+4)))) -> 99.6 | AK13: =IF((INT(O13/AI13)*INT(P13/AJ13))>(INT(O13/AJ13)*INT(P13/AI13)),INT(O13/AI13)*INT(P13/AJ13),IF((INT(O13/AI13)*INT(P13/AJ13))=(INT(O13/AJ13)*INT(P13/AI13)),(INT(O13/AI13)*INT(P13/AJ13)),(INT(O13/AJ13)*INT(P13/AI13)))) -> 60 | AL13: =IF((INT(O13/AI13)*INT(P13/AJ13))>(INT(O13/AJ13)*INT(P13/AI13)),INT(O13/AI13),IF((INT(O13/AI13)*INT(P13/AJ13))=(INT(O13/AJ13)*INT(P13/AI13)),(INT(O13/AI13)),(INT(O13/AJ13)))) -> 5 | AM13: =IF((INT(O13/AI13)*INT(P13/AJ13))>(INT(O13/AJ13)*INT(P13/AI13)),INT(P13/AJ13),IF((INT(O13/AI13)*INT(P13/AJ13))=(INT(O13/AJ13)*INT(P13/AI13)),(INT(P13/AJ13)),(INT(P13/AI13)))) -> 12 | AN13: =IF(Q13="Blanking",L13+1.5*N13,L13) -> 425.8 | AO13: =IF(Q13="Blanking",M13+1.5*2*N13,M13) -> 99.6 | AP13: =INT(O13/AN13)*INT(P13/AO13) -> 60 | AQ13: =INT(P13/AN13)*INT(O13/AO13) -> 50 | AR13: =INT(O13/AO13)*INT(P13/AN13) -> 50 | AS13: =INT(P13/AO13)*INT(O13/AN13) -> 60 | AT13: =O13-(INT(O13/AN13)*AN13) -> 371 | AU13: =P13-(INT(P13/AN13)*AN13) -> 398.4 | AV13: =O13-(INT(O13/AO13)*AO13) -> 10 | AW13: =P13-(INT(P13/AO13)*AO13) -> 54.8 | AX13: =INT(AT13/AO13)*INT(P13/AN13) -> 6 | AY13: =INT(AU13/AO13)*INT(O13/AN13) -> 20 | AZ13: =INT(AV13/AN13)*INT(P13/AO13) -> 0 | BA13: =INT(AW13/AN13)*INT(O13/AO13) -> 0 | BB13: =AX13+AP13 -> 66 | BC13: =AY13+AQ13 -> 70 | BD13: =AZ13+AR13 -> 50 | BE13: =BA13+AS13 -> 60 | BF13: =MAX(BB13:BE13) -> 70 | BG13: =IF(BB13=BF13,MIN(INT(O13/AN13),INT(P13/AO13)),IF(BC13=BF13,MIN(INT(P13/AN13),INT(O13/AO13)),IF(BD13=BF13,MIN(INT(O13/AO13),INT(P13/AN13)),MIN(INT(P13/AO13),INT(O13/AN13))))) -> 2 | BH13: =IF(BB13=BF13,MIN(INT(AT13/AO13),INT(1250/AN13)),IF(BC13=BF13,MIN(INT(AU13/AO13),INT(O13/AN13)),IF(BD13=BF13,MIN(INT(AV13/AN13),INT(P13/AO13)),MIN(INT(AW13/AN13),INT(O13/AO13))))) -> 4 | BI13: =IFERROR(BG13+BH13,"") -> 6
B14: =_xlfn.IFNA(VLOOKUP(D14,Group!$AM$1:$AO$10000,3,0),"") -> FWR10000 | C14: =_xlfn.IFNA(VLOOKUP(D14,Group!$AM$1:$AO$10000,2,0),"") -> 3 | D14: =Group!K3 -> H 157 01 464 A M8 weld Nut | E14: =_xlfn.IFNA(VLOOKUP(D14,BOM!$D$1:$F$10000,2,0),"") -> 0 | F14: =_xlfn.IFNA(VLOOKUP(D14,BOM!$D$1:$F$10000,3,0),"") -> M8 weld Nut | G14: =_xlfn.IFNA(IF(VLOOKUP(D14,BOM!D:J,7,0)="CSC","CSC","Others"),"") -> Others | I14: =_xlfn.IFNA(IF(OR(VLOOKUP(D14,BOM!$D$1:$I$1000,6,0)="Inhouse",VLOOKUP(D14,BOM!$D$1:$J$1000,7,0)="CSC"),"RM","BOP"),"") -> BOP | J14: =_xlfn.IFNA(IF(VLOOKUP(H14,'RM Base'!D:F,3,0)="Kg",VLOOKUP(H14,'RM Base'!D:E,2,0),IF(VLOOKUP(H14,'RM Base'!D:F,3,0)="Meter",(VLOOKUP(H14,'RM Base'!D:E,2,0)/R14*O14/1000),CONCATENATE("The Price is in ",VLOOKUP(H14,'RM Base'!D:F,3,0)))),"") | O14: =IF(K14<>"",IF(OR(K14="Pipe", K14="Circular Tube", K14="Square/Rectangular Tube"),IF(ISNUMBER(SEARCH("ss", H14)), 5000, 6000),2500),"") | P14: =IF(OR(O14=6000,O14=5000,O14=""),M14,1250) -> 0 | R14: =IF(K14="Sheet Metal",O14*P14*N14*7.86/10^6,IF(OR(K14="Pipe", K14="Circular Tube"),O14*(P14^2-(P14-2*N14)^2)*3.14/4*7.86*10^-6,IF(K14="Square/Rectangular Tube",O14*P14*N14*7.86*10^-6,""))) | S14: =IF(L14<>"",IF(OR(K14="Pipe", K14="Circular Tube"),INT(O14/(L14+5)),IF(K14="Square/Rectangular Tube",INT(O14/(L14+5)),IF(Q14="Laser Cutting",AK14,BF14))),"") | T14: =IF(OR(K14="Pipe", K14="Circular Tube"),L14*(M14^2-(M14-2*N14)^2)*3.14/4*7.86*10^-6,IF(K14="Square/Rectangular Tube",L14*M14*N14*7.86*10^-6,IF(K14="Sheet Metal",L14*M14*N14*7.86*10^-6,""))) | U14: =IFERROR(R14/S14,"") | V14: =IFERROR(I14*U14,"") | X14: =IF(W14="","",W14) | Y14: =IF(U14="","",W14/U14) | Z14: =IF(Y14="","",IF(I14="RM",IF(K14="Sheet Metal",W14/N14/7.86*2,IF(OR(K14="Pipe",K14="Circular Tube"),L14*PI()*M14/10^6,IF(K14="Square/Rectangular Tube",W14/N14/7.86,0))))) | AB14: =IF(Z14="","",U14-W14) | AC14: =_xlfn.IFNA(VLOOKUP(H14,'RM Base'!D:K,8,0),"") | AD14: =IF(K14<>"",IF(K14="Sheet Metal",95%,80%),"") | AE14: 0.77 | AG14: =IFERROR(IF(I14="RM",(W14*J14),AE14),"") -> 0.77 | AH14: =IFERROR(AE14-AG14,"") -> 0 | AI14: =IF(Q14="Shearing",L14,IF(Q14="Blanking",(L14+N14*1.5),IF(Q14="Laser Cutting",(L14+4)))) -> FALSE | AJ14: =IF(Q14="Shearing",M14,IF(Q14="Blanking",(M14+N14*3),IF(Q14="Laser Cutting",(M14+4)))) -> FALSE | AK14: =IF((INT(O14/AI14)*INT(P14/AJ14))>(INT(O14/AJ14)*INT(P14/AI14)),INT(O14/AI14)*INT(P14/AJ14),IF((INT(O14/AI14)*INT(P14/AJ14))=(INT(O14/AJ14)*INT(P14/AI14)),(INT(O14/AI14)*INT(P14/AJ14)),(INT(O14/AJ14)*INT(P14/AI14)))) -> #VALUE! | AL14: =IF((INT(O14/AI14)*INT(P14/AJ14))>(INT(O14/AJ14)*INT(P14/AI14)),INT(O14/AI14),IF((INT(O14/AI14)*INT(P14/AJ14))=(INT(O14/AJ14)*INT(P14/AI14)),(INT(O14/AI14)),(INT(O14/AJ14)))) -> #VALUE! | AM14: =IF((INT(O14/AI14)*INT(P14/AJ14))>(INT(O14/AJ14)*INT(P14/AI14)),INT(P14/AJ14),IF((INT(O14/AI14)*INT(P14/AJ14))=(INT(O14/AJ14)*INT(P14/AI14)),(INT(P14/AJ14)),(INT(P14/AI14)))) -> #VALUE! | AN14: =IF(Q14="Blanking",L14+1.5*N14,L14) -> 0 | AO14: =IF(Q14="Blanking",M14+1.5*2*N14,M14) -> 0 | AP14: =INT(O14/AN14)*INT(P14/AO14) -> #VALUE! | AQ14: =INT(P14/AN14)*INT(O14/AO14) -> #DIV/0! | AR14: =INT(O14/AO14)*INT(P14/AN14) -> #VALUE! | AS14: =INT(P14/AO14)*INT(O14/AN14) -> #DIV/0! | AT14: =O14-(INT(O14/AN14)*AN14) -> #VALUE! | AU14: =P14-(INT(P14/AN14)*AN14) -> #DIV/0! | AV14: =O14-(INT(O14/AO14)*AO14) -> #VALUE! | AW14: =P14-(INT(P14/AO14)*AO14) -> #DIV/0! | AX14: =INT(AT14/AO14)*INT(P14/AN14) -> #VALUE! | AY14: =INT(AU14/AO14)*INT(O14/AN14) -> #DIV/0! | AZ14: =INT(AV14/AN14)*INT(P14/AO14) -> #VALUE! | BA14: =INT(AW14/AN14)*INT(O14/AO14) -> #DIV/0! | BB14: =AX14+AP14 -> #VALUE! | BC14: =AY14+AQ14 -> #DIV/0! | BD14: =AZ14+AR14 -> #VALUE! | BE14: =BA14+AS14 -> #DIV/0! | BF14: =MAX(BB14:BE14) -> #VALUE! | BG14: =IF(BB14=BF14,MIN(INT(O14/AN14),INT(P14/AO14)),IF(BC14=BF14,MIN(INT(P14/AN14),INT(O14/AO14)),IF(BD14=BF14,MIN(INT(O14/AO14),INT(P14/AN14)),MIN(INT(P14/AO14),INT(O14/AN14))))) -> #VALUE! | BH14: =IF(BB14=BF14,MIN(INT(AT14/AO14),INT(1250/AN14)),IF(BC14=BF14,MIN(INT(AU14/AO14),INT(O14/AN14)),IF(BD14=BF14,MIN(INT(AV14/AN14),INT(P14/AO14)),MIN(INT(AW14/AN14),INT(O14/AO14))))) -> #VALUE! | BI14: =IFERROR(BG14+BH14,"")
B15: =_xlfn.IFNA(VLOOKUP(D15,Group!$AM$1:$AO$10000,3,0),"") -> FWR10000 | C15: =_xlfn.IFNA(VLOOKUP(D15,Group!$AM$1:$AO$10000,2,0),"") -> 3 | D15: =Group!K4 -> H 157 01 464 A Rear Stopper LH &RH | E15: =_xlfn.IFNA(VLOOKUP(D15,BOM!$D$1:$F$10000,2,0),"") -> 0 | F15: =_xlfn.IFNA(VLOOKUP(D15,BOM!$D$1:$F$10000,3,0),"") -> Rear Stopper LH &RH | G15: =_xlfn.IFNA(IF(VLOOKUP(D15,BOM!D:J,7,0)="CSC","CSC","Others"),"") -> CSC | H15: IS2062 | I15: =_xlfn.IFNA(IF(OR(VLOOKUP(D15,BOM!$D$1:$I$1000,6,0)="Inhouse",VLOOKUP(D15,BOM!$D$1:$J$1000,7,0)="CSC"),"RM","BOP"),"") -> RM | J15: =_xlfn.IFNA(IF(VLOOKUP(H15,'RM Base'!D:F,3,0)="Kg",VLOOKUP(H15,'RM Base'!D:E,2,0),IF(VLOOKUP(H15,'RM Base'!D:F,3,0)="Meter",(VLOOKUP(H15,'RM Base'!D:E,2,0)/R15*O15/1000),CONCATENATE("The Price is in ",VLOOKUP(H15,'RM Base'!D:F,3,0)))),"") -> 53 | K15: Sheet Metal | L15: =46+28.5 -> 74.5 | M15: 55 | N15: 2 | O15: =IF(K15<>"",IF(OR(K15="Pipe", K15="Circular Tube", K15="Square/Rectangular Tube"),IF(ISNUMBER(SEARCH("ss", H15)), 5000, 6000),2500),"") -> 2500 | P15: =IF(OR(O15=6000,O15=5000,O15=""),M15,1250) -> 1250 | Q15: Blanking | R15: =IF(K15="Sheet Metal",O15*P15*N15*7.86/10^6,IF(OR(K15="Pipe", K15="Circular Tube"),O15*(P15^2-(P15-2*N15)^2)*3.14/4*7.86*10^-6,IF(K15="Square/Rectangular Tube",O15*P15*N15*7.86*10^-6,""))) -> 49.125 | S15: =IF(L15<>"",IF(OR(K15="Pipe", K15="Circular Tube"),INT(O15/(L15+5)),IF(K15="Square/Rectangular Tube",INT(O15/(L15+5)),IF(Q15="Laser Cutting",AK15,BF15))),"") -> 640 | T15: =IF(OR(K15="Pipe", K15="Circular Tube"),L15*(M15^2-(M15-2*N15)^2)*3.14/4*7.86*10^-6,IF(K15="Square/Rectangular Tube",L15*M15*N15*7.86*10^-6,IF(K15="Sheet Metal",L15*M15*N15*7.86*10^-6,""))) -> 0.0644127 | U15: =IFERROR(R15/S15,"") -> 0.076757812 | V15: =IFERROR(I15*U15,"") | W15: 0.063 | X15: =IF(W15="","",W15) -> 0.063 | Y15: =IF(U15="","",W15/U15) -> 0.82076336 | Z15: =IF(Y15="","",IF(I15="RM",IF(K15="Sheet Metal",W15/N15/7.86*2,IF(OR(K15="Pipe",K15="Circular Tube"),L15*PI()*M15/10^6,IF(K15="Square/Rectangular Tube",W15/N15/7.86,0))))) -> 0.0080152672 | AB15: =IF(Z15="","",U15-W15) -> 0.013757812 | AC15: =_xlfn.IFNA(VLOOKUP(H15,'RM Base'!D:K,8,0),"") -> 30.5 | AD15: =IF(K15<>"",IF(K15="Sheet Metal",95%,80%),"") -> 0.95 | AE15: =IF(AD15="","",(J15*U15)-(AB15*AC15*AD15)) -> 3.6695314 | AG15: =IFERROR(IF(I15="RM",(W15*J15),AE15),"") -> 3.339 | AH15: =IFERROR(AE15-AG15,"") -> 0.33053145 | AI15: =IF(Q15="Shearing",L15,IF(Q15="Blanking",(L15+N15*1.5),IF(Q15="Laser Cutting",(L15+4)))) -> 77.5 | AJ15: =IF(Q15="Shearing",M15,IF(Q15="Blanking",(M15+N15*3),IF(Q15="Laser Cutting",(M15+4)))) -> 61 | AK15: =IF((INT(O15/AI15)*INT(P15/AJ15))>(INT(O15/AJ15)*INT(P15/AI15)),INT(O15/AI15)*INT(P15/AJ15),IF((INT(O15/AI15)*INT(P15/AJ15))=(INT(O15/AJ15)*INT(P15/AI15)),(INT(O15/AI15)*INT(P15/AJ15)),(INT(O15/AJ15)*INT(P15/AI15)))) -> 640 | AL15: =IF((INT(O15/AI15)*INT(P15/AJ15))>(INT(O15/AJ15)*INT(P15/AI15)),INT(O15/AI15),IF((INT(O15/AI15)*INT(P15/AJ15))=(INT(O15/AJ15)*INT(P15/AI15)),(INT(O15/AI15)),(INT(O15/AJ15)))) -> 32 | AM15: =IF((INT(O15/AI15)*INT(P15/AJ15))>(INT(O15/AJ15)*INT(P15/AI15)),INT(P15/AJ15),IF((INT(O15/AI15)*INT(P15/AJ15))=(INT(O15/AJ15)*INT(P15/AI15)),(INT(P15/AJ15)),(INT(P15/AI15)))) -> 20 | AN15: =IF(Q15="Blanking",L15+1.5*N15,L15) -> 77.5 | AO15: =IF(Q15="Blanking",M15+1.5*2*N15,M15) -> 61 | AP15: =INT(O15/AN15)*INT(P15/AO15) -> 640 | AQ15: =INT(P15/AN15)*INT(O15/AO15) -> 640 | AR15: =INT(O15/AO15)*INT(P15/AN15) -> 640 | AS15: =INT(P15/AO15)*INT(O15/AN15) -> 640 | AT15: =O15-(INT(O15/AN15)*AN15) -> 20 | AU15: =P15-(INT(P15/AN15)*AN15) -> 10 | AV15: =O15-(INT(O15/AO15)*AO15) -> 60 | AW15: =P15-(INT(P15/AO15)*AO15) -> 30 | AX15: =INT(AT15/AO15)*INT(P15/AN15) -> 0 | AY15: =INT(AU15/AO15)*INT(O15/AN15) -> 0 | AZ15: =INT(AV15/AN15)*INT(P15/AO15) -> 0 | BA15: =INT(AW15/AN15)*INT(O15/AO15) -> 0 | BB15: =AX15+AP15 -> 640 | BC15: =AY15+AQ15 -> 640 | BD15: =AZ15+AR15 -> 640 | BE15: =BA15+AS15 -> 640 | BF15: =MAX(BB15:BE15) -> 640 | BG15: =IF(BB15=BF15,MIN(INT(O15/AN15),INT(P15/AO15)),IF(BC15=BF15,MIN(INT(P15/AN15),INT(O15/AO15)),IF(BD15=BF15,MIN(INT(O15/AO15),INT(P15/AN15)),MIN(INT(P15/AO15),INT(O15/AN15))))) -> 20 | BH15: =IF(BB15=BF15,MIN(INT(AT15/AO15),INT(1250/AN15)),IF(BC15=BF15,MIN(INT(AU15/AO15),INT(O15/AN15)),IF(BD15=BF15,MIN(INT(AV15/AN15),INT(P15/AO15)),MIN(INT(AW15/AN15),INT(O15/AO15))))) -> 0 | BI15: =IFERROR(BG15+BH15,"") -> 20
B16: =_xlfn.IFNA(VLOOKUP(D16,Group!$AM$1:$AO$10000,3,0),"") -> FWR10000 | C16: =_xlfn.IFNA(VLOOKUP(D16,Group!$AM$1:$AO$10000,2,0),"") -> 3 | D16: =Group!K5 -> H 157 01 464 A Bottom MTG BRKT RH | E16: =_xlfn.IFNA(VLOOKUP(D16,BOM!$D$1:$F$10000,2,0),"") -> 0 | F16: =_xlfn.IFNA(VLOOKUP(D16,BOM!$D$1:$F$10000,3,0),"") -> Bottom MTG BRKT RH | G16: =_xlfn.IFNA(IF(VLOOKUP(D16,BOM!D:J,7,0)="CSC","CSC","Others"),"") -> CSC | H16: IS2062 | I16: =_xlfn.IFNA(IF(OR(VLOOKUP(D16,BOM!$D$1:$I$1000,6,0)="Inhouse",VLOOKUP(D16,BOM!$D$1:$J$1000,7,0)="CSC"),"RM","BOP"),"") -> RM | J16: =_xlfn.IFNA(IF(VLOOKUP(H16,'RM Base'!D:F,3,0)="Kg",VLOOKUP(H16,'RM Base'!D:E,2,0),IF(VLOOKUP(H16,'RM Base'!D:F,3,0)="Meter",(VLOOKUP(H16,'RM Base'!D:E,2,0)/R16*O16/1000),CONCATENATE("The Price is in ",VLOOKUP(H16,'RM Base'!D:F,3,0)))),"") -> 53 | K16: Sheet Metal | L16: 427 | M16: 120 | N16: 3.2 | O16: =IF(K16<>"",IF(OR(K16="Pipe", K16="Circular Tube", K16="Square/Rectangular Tube"),IF(ISNUMBER(SEARCH("ss", H16)), 5000, 6000),2500),"") -> 2500 | P16: =IF(OR(O16=6000,O16=5000,O16=""),M16,1250) -> 1250 | Q16: Blanking | R16: =IF(K16="Sheet Metal",O16*P16*N16*7.86/10^6,IF(OR(K16="Pipe", K16="Circular Tube"),O16*(P16^2-(P16-2*N16)^2)*3.14/4*7.86*10^-6,IF(K16="Square/Rectangular Tube",O16*P16*N16*7.86*10^-6,""))) -> 78.6 | S16: =IF(L16<>"",IF(OR(K16="Pipe", K16="Circular Tube"),INT(O16/(L16+5)),IF(K16="Square/Rectangular Tube",INT(O16/(L16+5)),IF(Q16="Laser Cutting",AK16,BF16))),"") -> 49 | T16: =IF(OR(K16="Pipe", K16="Circular Tube"),L16*(M16^2-(M16-2*N16)^2)*3.14/4*7.86*10^-6,IF(K16="Square/Rectangular Tube",L16*M16*N16*7.86*10^-6,IF(K16="Sheet Metal",L16*M16*N16*7.86*10^-6,""))) -> 1.2887885 | U16: =IFERROR(R16/S16,"") -> 1.6040816 | V16: =IFERROR(I16*U16,"") | W16: 1.256 | X16: =IF(W16="","",W16) -> 1.256 | Y16: =IF(U16="","",W16/U16) -> 0.78300254 | Z16: =IF(Y16="","",IF(I16="RM",IF(K16="Sheet Metal",W16/N16/7.86*2,IF(OR(K16="Pipe",K16="Circular Tube"),L16*PI()*M16/10^6,IF(K16="Square/Rectangular Tube",W16/N16/7.86,0))))) -> 0.099872774 | AB16: =IF(Z16="","",U16-W16) -> 0.34808163 | AC16: =_xlfn.IFNA(VLOOKUP(H16,'RM Base'!D:K,8,0),"") -> 30.5 | AD16: =IF(K16<>"",IF(K16="Sheet Metal",95%,80%),"") -> 0.95 | AE16: =IF(AD16="","",(J16*U16)-(AB16*AC16*AD16)) -> 74.930661 | AG16: =IFERROR(IF(I16="RM",(W16*J16),AE16),"") -> 66.568 | AH16: =IFERROR(AE16-AG16,"") -> 8.3626612 | AI16: =IF(Q16="Shearing",L16,IF(Q16="Blanking",(L16+N16*1.5),IF(Q16="Laser Cutting",(L16+4)))) -> 431.8 | AJ16: =IF(Q16="Shearing",M16,IF(Q16="Blanking",(M16+N16*3),IF(Q16="Laser Cutting",(M16+4)))) -> 129.6 | AK16: =IF((INT(O16/AI16)*INT(P16/AJ16))>(INT(O16/AJ16)*INT(P16/AI16)),INT(O16/AI16)*INT(P16/AJ16),IF((INT(O16/AI16)*INT(P16/AJ16))=(INT(O16/AJ16)*INT(P16/AI16)),(INT(O16/AI16)*INT(P16/AJ16)),(INT(O16/AJ16)*INT(P16/AI16)))) -> 45 | AL16: =IF((INT(O16/AI16)*INT(P16/AJ16))>(INT(O16/AJ16)*INT(P16/AI16)),INT(O16/AI16),IF((INT(O16/AI16)*INT(P16/AJ16))=(INT(O16/AJ16)*INT(P16/AI16)),(INT(O16/AI16)),(INT(O16/AJ16)))) -> 5 | AM16: =IF((INT(O16/AI16)*INT(P16/AJ16))>(INT(O16/AJ16)*INT(P16/AI16)),INT(P16/AJ16),IF((INT(O16/AI16)*INT(P16/AJ16))=(INT(O16/AJ16)*INT(P16/AI16)),(INT(P16/AJ16)),(INT(P16/AI16)))) -> 9 | AN16: =IF(Q16="Blanking",L16+1.5*N16,L16) -> 431.8 | AO16: =IF(Q16="Blanking",M16+1.5*2*N16,M16) -> 129.6 | AP16: =INT(O16/AN16)*INT(P16/AO16) -> 45 | AQ16: =INT(P16/AN16)*INT(O16/AO16) -> 38 | AR16: =INT(O16/AO16)*INT(P16/AN16) -> 38 | AS16: =INT(P16/AO16)*INT(O16/AN16) -> 45 | AT16: =O16-(INT(O16/AN16)*AN16) -> 341 | AU16: =P16-(INT(P16/AN16)*AN16) -> 386.4 | AV16: =O16-(INT(O16/AO16)*AO16) -> 37.6 | AW16: =P16-(INT(P16/AO16)*AO16) -> 83.6 | AX16: =INT(AT16/AO16)*INT(P16/AN16) -> 4 | AY16: =INT(AU16/AO16)*INT(O16/AN16) -> 10 | AZ16: =INT(AV16/AN16)*INT(P16/AO16) -> 0 | BA16: =INT(AW16/AN16)*INT(O16/AO16) -> 0 | BB16: =AX16+AP16 -> 49 | BC16: =AY16+AQ16 -> 48 | BD16: =AZ16+AR16 -> 38 | BE16: =BA16+AS16 -> 45 | BF16: =MAX(BB16:BE16) -> 49 | BG16: =IF(BB16=BF16,MIN(INT(O16/AN16),INT(P16/AO16)),IF(BC16=BF16,MIN(INT(P16/AN16),INT(O16/AO16)),IF(BD16=BF16,MIN(INT(O16/AO16),INT(P16/AN16)),MIN(INT(P16/AO16),INT(O16/AN16))))) -> 5 | BH16: =IF(BB16=BF16,MIN(INT(AT16/AO16),INT(1250/AN16)),IF(BC16=BF16,MIN(INT(AU16/AO16),INT(O16/AN16)),IF(BD16=BF16,MIN(INT(AV16/AN16),INT(P16/AO16)),MIN(INT(AW16/AN16),INT(O16/AO16))))) -> 2 | BI16: =IFERROR(BG16+BH16,"") -> 7
B17: =_xlfn.IFNA(VLOOKUP(D17,Group!$AM$1:$AO$10000,3,0),"") -> FWR10000 | C17: =_xlfn.IFNA(VLOOKUP(D17,Group!$AM$1:$AO$10000,2,0),"") -> 3 | D17: =Group!K6 -> H 157 01 464 A Bottom MTG BRKT REINF | E17: =_xlfn.IFNA(VLOOKUP(D17,BOM!$D$1:$F$10000,2,0),"") -> 0 | F17: =_xlfn.IFNA(VLOOKUP(D17,BOM!$D$1:$F$10000,3,0),"") -> Bottom MTG BRKT REINF | G17: =_xlfn.IFNA(IF(VLOOKUP(D17,BOM!D:J,7,0)="CSC","CSC","Others"),"") -> CSC | H17: IS2062 | I17: =_xlfn.IFNA(IF(OR(VLOOKUP(D17,BOM!$D$1:$I$1000,6,0)="Inhouse",VLOOKUP(D17,BOM!$D$1:$J$1000,7,0)="CSC"),"RM","BOP"),"") -> RM | J17: =_xlfn.IFNA(IF(VLOOKUP(H17,'RM Base'!D:F,3,0)="Kg",VLOOKUP(H17,'RM Base'!D:E,2,0),IF(VLOOKUP(H17,'RM Base'!D:F,3,0)="Meter",(VLOOKUP(H17,'RM Base'!D:E,2,0)/R17*O17/1000),CONCATENATE("The Price is in ",VLOOKUP(H17,'RM Base'!D:F,3,0)))),"") -> 53 | K17: Sheet Metal | L17: 48 | M17: 38 | N17: 4 | O17: =IF(K17<>"",IF(OR(K17="Pipe", K17="Circular Tube", K17="Square/Rectangular Tube"),IF(ISNUMBER(SEARCH("ss", H17)), 5000, 6000),2500),"") -> 2500 | P17: =IF(OR(O17=6000,O17=5000,O17=""),M17,1250) -> 1250 | Q17: Blanking | R17: =IF(K17="Sheet Metal",O17*P17*N17*7.86/10^6,IF(OR(K17="Pipe", K17="Circular Tube"),O17*(P17^2-(P17-2*N17)^2)*3.14/4*7.86*10^-6,IF(K17="Square/Rectangular Tube",O17*P17*N17*7.86*10^-6,""))) -> 98.25 | S17: =IF(L17<>"",IF(OR(K17="Pipe", K17="Circular Tube"),INT(O17/(L17+5)),IF(K17="Square/Rectangular Tube",INT(O17/(L17+5)),IF(Q17="Laser Cutting",AK17,BF17))),"") -> 1150 | T17: =IF(OR(K17="Pipe", K17="Circular Tube"),L17*(M17^2-(M17-2*N17)^2)*3.14/4*7.86*10^-6,IF(K17="Square/Rectangular Tube",L17*M17*N17*7.86*10^-6,IF(K17="Sheet Metal",L17*M17*N17*7.86*10^-6,""))) -> 0.05734656 | U17: =IFERROR(R17/S17,"") -> 0.085434783 | V17: =IFERROR(I17*U17,"") | W17: 0.044 | X17: =IF(W17="","",W17) -> 0.044 | Y17: =IF(U17="","",W17/U17) -> 0.51501272 | Z17: =IF(Y17="","",IF(I17="RM",IF(K17="Sheet Metal",W17/N17/7.86*2,IF(OR(K17="Pipe",K17="Circular Tube"),L17*PI()*M17/10^6,IF(K17="Square/Rectangular Tube",W17/N17/7.86,0))))) -> 0.0027989822 | AB17: =IF(Z17="","",U17-W17) -> 0.041434783 | AC17: =_xlfn.IFNA(VLOOKUP(H17,'RM Base'!D:K,8,0),"") -> 30.5 | AD17: =IF(K17<>"",IF(K17="Sheet Metal",95%,80%),"") -> 0.95 | AE17: =IF(AD17="","",(J17*U17)-(AB17*AC17*AD17)) -> 3.3274707 | AG17: =IFERROR(IF(I17="RM",(W17*J17),AE17),"") -> 2.332 | AH17: =IFERROR(AE17-AG17,"") -> 0.99547065 | AI17: =IF(Q17="Shearing",L17,IF(Q17="Blanking",(L17+N17*1.5),IF(Q17="Laser Cutting",(L17+4)))) -> 54 | AJ17: =IF(Q17="Shearing",M17,IF(Q17="Blanking",(M17+N17*3),IF(Q17="Laser Cutting",(M17+4)))) -> 50 | AK17: =IF((INT(O17/AI17)*INT(P17/AJ17))>(INT(O17/AJ17)*INT(P17/AI17)),INT(O17/AI17)*INT(P17/AJ17),IF((INT(O17/AI17)*INT(P17/AJ17))=(INT(O17/AJ17)*INT(P17/AI17)),(INT(O17/AI17)*INT(P17/AJ17)),(INT(O17/AJ17)*INT(P17/AI17)))) -> 1150 | AL17: =IF((INT(O17/AI17)*INT(P17/AJ17))>(INT(O17/AJ17)*INT(P17/AI17)),INT(O17/AI17),IF((INT(O17/AI17)*INT(P17/AJ17))=(INT(O17/AJ17)*INT(P17/AI17)),(INT(O17/AI17)),(INT(O17/AJ17)))) -> 46 | AM17: =IF((INT(O17/AI17)*INT(P17/AJ17))>(INT(O17/AJ17)*INT(P17/AI17)),INT(P17/AJ17),IF((INT(O17/AI17)*INT(P17/AJ17))=(INT(O17/AJ17)*INT(P17/AI17)),(INT(P17/AJ17)),(INT(P17/AI17)))) -> 25 | AN17: =IF(Q17="Blanking",L17+1.5*N17,L17) -> 54 | AO17: =IF(Q17="Blanking",M17+1.5*2*N17,M17) -> 50 | AP17: =INT(O17/AN17)*INT(P17/AO17) -> 1150 | AQ17: =INT(P17/AN17)*INT(O17/AO17) -> 1150 | AR17: =INT(O17/AO17)*INT(P17/AN17) -> 1150 | AS17: =INT(P17/AO17)*INT(O17/AN17) -> 1150 | AT17: =O17-(INT(O17/AN17)*AN17) -> 16 | AU17: =P17-(INT(P17/AN17)*AN17) -> 8 | AV17: =O17-(INT(O17/AO17)*AO17) -> 0 | AW17: =P17-(INT(P17/AO17)*AO17) -> 0 | AX17: =INT(AT17/AO17)*INT(P17/AN17) -> 0 | AY17: =INT(AU17/AO17)*INT(O17/AN17) -> 0 | AZ17: =INT(AV17/AN17)*INT(P17/AO17) -> 0 | BA17: =INT(AW17/AN17)*INT(O17/AO17) -> 0 | BB17: =AX17+AP17 -> 1150 | BC17: =AY17+AQ17 -> 1150 | BD17: =AZ17+AR17 -> 1150 | BE17: =BA17+AS17 -> 1150 | BF17: =MAX(BB17:BE17) -> 1150 | BG17: =IF(BB17=BF17,MIN(INT(O17/AN17),INT(P17/AO17)),IF(BC17=BF17,MIN(INT(P17/AN17),INT(O17/AO17)),IF(BD17=BF17,MIN(INT(O17/AO17),INT(P17/AN17)),MIN(INT(P17/AO17),INT(O17/AN17))))) -> 25 | BH17: =IF(BB17=BF17,MIN(INT(AT17/AO17),INT(1250/AN17)),IF(BC17=BF17,MIN(INT(AU17/AO17),INT(O17/AN17)),IF(BD17=BF17,MIN(INT(AV17/AN17),INT(P17/AO17)),MIN(INT(AW17/AN17),INT(O17/AO17))))) -> 0 | BI17: =IFERROR(BG17+BH17,"") -> 25
B18: =_xlfn.IFNA(VLOOKUP(D18,Group!$AM$1:$AO$10000,3,0),"") -> FWR10000 | C18: =_xlfn.IFNA(VLOOKUP(D18,Group!$AM$1:$AO$10000,2,0),"") -> 3 | D18: =Group!K7 -> H 157 01 464 A Bottom MTG BRKT Spacer | E18: =_xlfn.IFNA(VLOOKUP(D18,BOM!$D$1:$F$10000,2,0),"") -> 0 | F18: =_xlfn.IFNA(VLOOKUP(D18,BOM!$D$1:$F$10000,3,0),"") -> Bottom MTG BRKT Spacer | G18: =_xlfn.IFNA(IF(VLOOKUP(D18,BOM!D:J,7,0)="CSC","CSC","Others"),"") -> CSC | H18: IS2062 | I18: =_xlfn.IFNA(IF(OR(VLOOKUP(D18,BOM!$D$1:$I$1000,6,0)="Inhouse",VLOOKUP(D18,BOM!$D$1:$J$1000,7,0)="CSC"),"RM","BOP"),"") -> RM | J18: =_xlfn.IFNA(IF(VLOOKUP(H18,'RM Base'!D:F,3,0)="Kg",VLOOKUP(H18,'RM Base'!D:E,2,0),IF(VLOOKUP(H18,'RM Base'!D:F,3,0)="Meter",(VLOOKUP(H18,'RM Base'!D:E,2,0)/R18*O18/1000),CONCATENATE("The Price is in ",VLOOKUP(H18,'RM Base'!D:F,3,0)))),"") -> 53 | K18: Sheet Metal | L18: 23 | M18: 23 | N18: 6 | O18: =IF(K18<>"",IF(OR(K18="Pipe", K18="Circular Tube", K18="Square/Rectangular Tube"),IF(ISNUMBER(SEARCH("ss", H18)), 5000, 6000),2500),"") -> 2500 | P18: =IF(OR(O18=6000,O18=5000,O18=""),M18,1250) -> 1250 | Q18: Laser Cutting | R18: =IF(K18="Sheet Metal",O18*P18*N18*7.86/10^6,IF(OR(K18="Pipe", K18="Circular Tube"),O18*(P18^2-(P18-2*N18)^2)*3.14/4*7.86*10^-6,IF(K18="Square/Rectangular Tube",O18*P18*N18*7.86*10^-6,""))) -> 147.375 | S18: =IF(L18<>"",IF(OR(K18="Pipe", K18="Circular Tube"),INT(O18/(L18+5)),IF(K18="Square/Rectangular Tube",INT(O18/(L18+5)),IF(Q18="Laser Cutting",AK18,BF18))),"") -> 4232 | T18: =IF(OR(K18="Pipe", K18="Circular Tube"),L18*(M18^2-(M18-2*N18)^2)*3.14/4*7.86*10^-6,IF(K18="Square/Rectangular Tube",L18*M18*N18*7.86*10^-6,IF(K18="Sheet Metal",L18*M18*N18*7.86*10^-6,""))) -> 0.02494764 | U18: =IFERROR(R18/S18,"") -> 0.03482396 | V18: =IFERROR(I18*U18,"") | W18: 0.014 | X18: =IF(W18="","",W18) -> 0.014 | Y18: =IF(U18="","",W18/U18) -> 0.40202205 | Z18: =IF(Y18="","",IF(I18="RM",IF(K18="Sheet Metal",W18/N18/7.86*2,IF(OR(K18="Pipe",K18="Circular Tube"),L18*PI()*M18/10^6,IF(K18="Square/Rectangular Tube",W18/N18/7.86,0))))) -> 0.00059372349 | AB18: =IF(Z18="","",U18-W18) -> 0.02082396 | AC18: =_xlfn.IFNA(VLOOKUP(H18,'RM Base'!D:K,8,0),"") -> 30.5 | AD18: =IF(K18<>"",IF(K18="Sheet Metal",95%,80%),"") -> 0.95 | AE18: =IF(AD18="","",(J18*U18)-(AB18*AC18*AD18)) -> 1.2422956 | AG18: =IFERROR(IF(I18="RM",(W18*J18),AE18),"") -> 0.742 | AH18: =IFERROR(AE18-AG18,"") -> 0.50029565 | AI18: =IF(Q18="Shearing",L18,IF(Q18="Blanking",(L18+N18*1.5),IF(Q18="Laser Cutting",(L18+4)))) -> 27 | AJ18: =IF(Q18="Shearing",M18,IF(Q18="Blanking",(M18+N18*3),IF(Q18="Laser Cutting",(M18+4)))) -> 27 | AK18: =IF((INT(O18/AI18)*INT(P18/AJ18))>(INT(O18/AJ18)*INT(P18/AI18)),INT(O18/AI18)*INT(P18/AJ18),IF((INT(O18/AI18)*INT(P18/AJ18))=(INT(O18/AJ18)*INT(P18/AI18)),(INT(O18/AI18)*INT(P18/AJ18)),(INT(O18/AJ18)*INT(P18/AI18)))) -> 4232 | AL18: =IF((INT(O18/AI18)*INT(P18/AJ18))>(INT(O18/AJ18)*INT(P18/AI18)),INT(O18/AI18),IF((INT(O18/AI18)*INT(P18/AJ18))=(INT(O18/AJ18)*INT(P18/AI18)),(INT(O18/AI18)),(INT(O18/AJ18)))) -> 92 | AM18: =IF((INT(O18/AI18)*INT(P18/AJ18))>(INT(O18/AJ18)*INT(P18/AI18)),INT(P18/AJ18),IF((INT(O18/AI18)*INT(P18/AJ18))=(INT(O18/AJ18)*INT(P18/AI18)),(INT(P18/AJ18)),(INT(P18/AI18)))) -> 46 | AN18: =IF(Q18="Blanking",L18+1.5*N18,L18) -> 23 | AO18: =IF(Q18="Blanking",M18+1.5*2*N18,M18) -> 23 | AP18: =INT(O18/AN18)*INT(P18/AO18) -> 5832 | AQ18: =INT(P18/AN18)*INT(O18/AO18) -> 5832 | AR18: =INT(O18/AO18)*INT(P18/AN18) -> 5832 | AS18: =INT(P18/AO18)*INT(O18/AN18) -> 5832 | AT18: =O18-(INT(O18/AN18)*AN18) -> 16 | AU18: =P18-(INT(P18/AN18)*AN18) -> 8 | AV18: =O18-(INT(O18/AO18)*AO18) -> 16 | AW18: =P18-(INT(P18/AO18)*AO18) -> 8 | AX18: =INT(AT18/AO18)*INT(P18/AN18) -> 0 | AY18: =INT(AU18/AO18)*INT(O18/AN18) -> 0 | AZ18: =INT(AV18/AN18)*INT(P18/AO18) -> 0 | BA18: =INT(AW18/AN18)*INT(O18/AO18) -> 0 | BB18: =AX18+AP18 -> 5832 | BC18: =AY18+AQ18 -> 5832 | BD18: =AZ18+AR18 -> 5832 | BE18: =BA18+AS18 -> 5832 | BF18: =MAX(BB18:BE18) -> 5832 | BG18: =IF(BB18=BF18,MIN(INT(O18/AN18),INT(P18/AO18)),IF(BC18=BF18,MIN(INT(P18/AN18),INT(O18/AO18)),IF(BD18=BF18,MIN(INT(O18/AO18),INT(P18/AN18)),MIN(INT(P18/AO18),INT(O18/AN18))))) -> 54 | BH18: =IF(BB18=BF18,MIN(INT(AT18/AO18),INT(1250/AN18)),IF(BC18=BF18,MIN(INT(AU18/AO18),INT(O18/AN18)),IF(BD18=BF18,MIN(INT(AV18/AN18),INT(P18/AO18)),MIN(INT(AW18/AN18),INT(O18/AO18))))) -> 0 | BI18: =IFERROR(BG18+BH18,"") -> 54
B19: =_xlfn.IFNA(VLOOKUP(D19,Group!$AM$1:$AO$10000,3,0),"") -> FWR10000 | C19: =_xlfn.IFNA(VLOOKUP(D19,Group!$AM$1:$AO$10000,2,0),"") -> 3 | D19: =Group!K8 -> H 157 01 464 A Bottom MTG BRKT LH 1 | E19: =_xlfn.IFNA(VLOOKUP(D19,BOM!$D$1:$F$10000,2,0),"") -> 0 | F19: =_xlfn.IFNA(VLOOKUP(D19,BOM!$D$1:$F$10000,3,0),"") -> Bottom MTG BRKT LH 1 | G19: =_xlfn.IFNA(IF(VLOOKUP(D19,BOM!D:J,7,0)="CSC","CSC","Others"),"") -> CSC | H19: IS2062 | I19: =_xlfn.IFNA(IF(OR(VLOOKUP(D19,BOM!$D$1:$I$1000,6,0)="Inhouse",VLOOKUP(D19,BOM!$D$1:$J$1000,7,0)="CSC"),"RM","BOP"),"") -> RM | J19: =_xlfn.IFNA(IF(VLOOKUP(H19,'RM Base'!D:F,3,0)="Kg",VLOOKUP(H19,'RM Base'!D:E,2,0),IF(VLOOKUP(H19,'RM Base'!D:F,3,0)="Meter",(VLOOKUP(H19,'RM Base'!D:E,2,0)/R19*O19/1000),CONCATENATE("The Price is in ",VLOOKUP(H19,'RM Base'!D:F,3,0)))),"") -> 53 | K19: Sheet Metal | L19: 100 | M19: 100 | N19: 3.2 | O19: =IF(K19<>"",IF(OR(K19="Pipe", K19="Circular Tube", K19="Square/Rectangular Tube"),IF(ISNUMBER(SEARCH("ss", H19)), 5000, 6000),2500),"") -> 2500 | P19: =IF(OR(O19=6000,O19=5000,O19=""),M19,1250) -> 1250 | Q19: Blanking | R19: =IF(K19="Sheet Metal",O19*P19*N19*7.86/10^6,IF(OR(K19="Pipe", K19="Circular Tube"),O19*(P19^2-(P19-2*N19)^2)*3.14/4*7.86*10^-6,IF(K19="Square/Rectangular Tube",O19*P19*N19*7.86*10^-6,""))) -> 78.6 | S19: =IF(L19<>"",IF(OR(K19="Pipe", K19="Circular Tube"),INT(O19/(L19+5)),IF(K19="Square/Rectangular Tube",INT(O19/(L19+5)),IF(Q19="Laser Cutting",AK19,BF19))),"") -> 253 | T19: =IF(OR(K19="Pipe", K19="Circular Tube"),L19*(M19^2-(M19-2*N19)^2)*3.14/4*7.86*10^-6,IF(K19="Square/Rectangular Tube",L19*M19*N19*7.86*10^-6,IF(K19="Sheet Metal",L19*M19*N19*7.86*10^-6,""))) -> 0.25152 | U19: =IFERROR(R19/S19,"") -> 0.31067194 | V19: =IFERROR(I19*U19,"") | W19: 0.222 | X19: =IF(W19="","",W19) -> 0.222 | Y19: =IF(U19="","",W19/U19) -> 0.71458015 | Z19: =IF(Y19="","",IF(I19="RM",IF(K19="Sheet Metal",W19/N19/7.86*2,IF(OR(K19="Pipe",K19="Circular Tube"),L19*PI()*M19/10^6,IF(K19="Square/Rectangular Tube",W19/N19/7.86,0))))) -> 0.017652672 | AB19: =IF(Z19="","",U19-W19) -> 0.088671937 | AC19: =_xlfn.IFNA(VLOOKUP(H19,'RM Base'!D:K,8,0),"") -> 30.5 | AD19: =IF(K19<>"",IF(K19="Sheet Metal",95%,80%),"") -> 0.95 | AE19: =IF(AD19="","",(J19*U19)-(AB19*AC19*AD19)) -> 13.896343 | AG19: =IFERROR(IF(I19="RM",(W19*J19),AE19),"") -> 11.766 | AH19: =IFERROR(AE19-AG19,"") -> 2.1303433 | AI19: =IF(Q19="Shearing",L19,IF(Q19="Blanking",(L19+N19*1.5),IF(Q19="Laser Cutting",(L19+4)))) -> 104.8 | AJ19: =IF(Q19="Shearing",M19,IF(Q19="Blanking",(M19+N19*3),IF(Q19="Laser Cutting",(M19+4)))) -> 109.6 | AK19: =IF((INT(O19/AI19)*INT(P19/AJ19))>(INT(O19/AJ19)*INT(P19/AI19)),INT(O19/AI19)*INT(P19/AJ19),IF((INT(O19/AI19)*INT(P19/AJ19))=(INT(O19/AJ19)*INT(P19/AI19)),(INT(O19/AI19)*INT(P19/AJ19)),(INT(O19/AJ19)*INT(P19/AI19)))) -> 253 | AL19: =IF((INT(O19/AI19)*INT(P19/AJ19))>(INT(O19/AJ19)*INT(P19/AI19)),INT(O19/AI19),IF((INT(O19/AI19)*INT(P19/AJ19))=(INT(O19/AJ19)*INT(P19/AI19)),(INT(O19/AI19)),(INT(O19/AJ19)))) -> 23 | AM19: =IF((INT(O19/AI19)*INT(P19/AJ19))>(INT(O19/AJ19)*INT(P19/AI19)),INT(P19/AJ19),IF((INT(O19/AI19)*INT(P19/AJ19))=(INT(O19/AJ19)*INT(P19/AI19)),(INT(P19/AJ19)),(INT(P19/AI19)))) -> 11 | AN19: =IF(Q19="Blanking",L19+1.5*N19,L19) -> 104.8 | AO19: =IF(Q19="Blanking",M19+1.5*2*N19,M19) -> 109.6 | AP19: =INT(O19/AN19)*INT(P19/AO19) -> 253 | AQ19: =INT(P19/AN19)*INT(O19/AO19) -> 242 | AR19: =INT(O19/AO19)*INT(P19/AN19) -> 242 | AS19: =INT(P19/AO19)*INT(O19/AN19) -> 253 | AT19: =O19-(INT(O19/AN19)*AN19) -> 89.6 | AU19: =P19-(INT(P19/AN19)*AN19) -> 97.2 | AV19: =O19-(INT(O19/AO19)*AO19) -> 88.8 | AW19: =P19-(INT(P19/AO19)*AO19) -> 44.4 | AX19: =INT(AT19/AO19)*INT(P19/AN19) -> 0 | AY19: =INT(AU19/AO19)*INT(O19/AN19) -> 0 | AZ19: =INT(AV19/AN19)*INT(P19/AO19) -> 0 | BA19: =INT(AW19/AN19)*INT(O19/AO19) -> 0 | BB19: =AX19+AP19 -> 253 | BC19: =AY19+AQ19 -> 242 | BD19: =AZ19+AR19 -> 242 | BE19: =BA19+AS19 -> 253 | BF19: =MAX(BB19:BE19) -> 253 | BG19: =IF(BB19=BF19,MIN(INT(O19/AN19),INT(P19/AO19)),IF(BC19=BF19,MIN(INT(P19/AN19),INT(O19/AO19)),IF(BD19=BF19,MIN(INT(O19/AO19),INT(P19/AN19)),MIN(INT(P19/AO19),INT(O19/AN19))))) -> 11 | BH19: =IF(BB19=BF19,MIN(INT(AT19/AO19),INT(1250/AN19)),IF(BC19=BF19,MIN(INT(AU19/AO19),INT(O19/AN19)),IF(BD19=BF19,MIN(INT(AV19/AN19),INT(P19/AO19)),MIN(INT(AW19/AN19),INT(O19/AO19))))) -> 0 | BI19: =IFERROR(BG19+BH19,"") -> 11
B20: =_xlfn.IFNA(VLOOKUP(D20,Group!$AM$1:$AO$10000,3,0),"") -> FWR10000 | C20: =_xlfn.IFNA(VLOOKUP(D20,Group!$AM$1:$AO$10000,2,0),"") -> 3 | D20: =Group!K9 -> H 157 01 464 A Bottom MTG BRKT LH 2 | E20: =_xlfn.IFNA(VLOOKUP(D20,BOM!$D$1:$F$10000,2,0),"") -> 0 | F20: =_xlfn.IFNA(VLOOKUP(D20,BOM!$D$1:$F$10000,3,0),"") -> Bottom MTG BRKT LH 2 | G20: =_xlfn.IFNA(IF(VLOOKUP(D20,BOM!D:J,7,0)="CSC","CSC","Others"),"") -> CSC | H20: IS2062 | I20: =_xlfn.IFNA(IF(OR(VLOOKUP(D20,BOM!$D$1:$I$1000,6,0)="Inhouse",VLOOKUP(D20,BOM!$D$1:$J$1000,7,0)="CSC"),"RM","BOP"),"") -> RM | J20: =_xlfn.IFNA(IF(VLOOKUP(H20,'RM Base'!D:F,3,0)="Kg",VLOOKUP(H20,'RM Base'!D:E,2,0),IF(VLOOKUP(H20,'RM Base'!D:F,3,0)="Meter",(VLOOKUP(H20,'RM Base'!D:E,2,0)/R20*O20/1000),CONCATENATE("The Price is in ",VLOOKUP(H20,'RM Base'!D:F,3,0)))),"") -> 53 | K20: Sheet Metal | L20: =76+39 -> 115 | M20: 100 | N20: 3.2 | O20: =IF(K20<>"",IF(OR(K20="Pipe", K20="Circular Tube", K20="Square/Rectangular Tube"),IF(ISNUMBER(SEARCH("ss", H20)), 5000, 6000),2500),"") -> 2500 | P20: =IF(OR(O20=6000,O20=5000,O20=""),M20,1250) -> 1250 | Q20: Blanking | R20: =IF(K20="Sheet Metal",O20*P20*N20*7.86/10^6,IF(OR(K20="Pipe", K20="Circular Tube"),O20*(P20^2-(P20-2*N20)^2)*3.14/4*7.86*10^-6,IF(K20="Square/Rectangular Tube",O20*P20*N20*7.86*10^-6,""))) -> 78.6 | S20: =IF(L20<>"",IF(OR(K20="Pipe", K20="Circular Tube"),INT(O20/(L20+5)),IF(K20="Square/Rectangular Tube",INT(O20/(L20+5)),IF(Q20="Laser Cutting",AK20,BF20))),"") -> 220 | T20: =IF(OR(K20="Pipe", K20="Circular Tube"),L20*(M20^2-(M20-2*N20)^2)*3.14/4*7.86*10^-6,IF(K20="Square/Rectangular Tube",L20*M20*N20*7.86*10^-6,IF(K20="Sheet Metal",L20*M20*N20*7.86*10^-6,""))) -> 0.289248 | U20: =IFERROR(R20/S20,"") -> 0.35727273 | V20: =IFERROR(I20*U20,"") | W20: 0.28 | X20: =IF(W20="","",W20) -> 0.28 | Y20: =IF(U20="","",W20/U20) -> 0.78371501 | Z20: =IF(Y20="","",IF(I20="RM",IF(K20="Sheet Metal",W20/N20/7.86*2,IF(OR(K20="Pipe",K20="Circular Tube"),L20*PI()*M20/10^6,IF(K20="Square/Rectangular Tube",W20/N20/7.86,0))))) -> 0.022264631 | AB20: =IF(Z20="","",U20-W20) -> 0.077272727 | AC20: =_xlfn.IFNA(VLOOKUP(H20,'RM Base'!D:K,8,0),"") -> 30.5 | AD20: =IF(K20<>"",IF(K20="Sheet Metal",95%,80%),"") -> 0.95 | AE20: =IF(AD20="","",(J20*U20)-(AB20*AC20*AD20)) -> 16.696477 | AG20: =IFERROR(IF(I20="RM",(W20*J20),AE20),"") -> 14.84 | AH20: =IFERROR(AE20-AG20,"") -> 1.8564773 | AI20: =IF(Q20="Shearing",L20,IF(Q20="Blanking",(L20+N20*1.5),IF(Q20="Laser Cutting",(L20+4)))) -> 119.8 | AJ20: =IF(Q20="Shearing",M20,IF(Q20="Blanking",(M20+N20*3),IF(Q20="Laser Cutting",(M20+4)))) -> 109.6 | AK20: =IF((INT(O20/AI20)*INT(P20/AJ20))>(INT(O20/AJ20)*INT(P20/AI20)),INT(O20/AI20)*INT(P20/AJ20),IF((INT(O20/AI20)*INT(P20/AJ20))=(INT(O20/AJ20)*INT(P20/AI20)),(INT(O20/AI20)*INT(P20/AJ20)),(INT(O20/AJ20)*INT(P20/AI20)))) -> 220 | AL20: =IF((INT(O20/AI20)*INT(P20/AJ20))>(INT(O20/AJ20)*INT(P20/AI20)),INT(O20/AI20),IF((INT(O20/AI20)*INT(P20/AJ20))=(INT(O20/AJ20)*INT(P20/AI20)),(INT(O20/AI20)),(INT(O20/AJ20)))) -> 20 | AM20: =IF((INT(O20/AI20)*INT(P20/AJ20))>(INT(O20/AJ20)*INT(P20/AI20)),INT(P20/AJ20),IF((INT(O20/AI20)*INT(P20/AJ20))=(INT(O20/AJ20)*INT(P20/AI20)),(INT(P20/AJ20)),(INT(P20/AI20)))) -> 11 | AN20: =IF(Q20="Blanking",L20+1.5*N20,L20) -> 119.8 | AO20: =IF(Q20="Blanking",M20+1.5*2*N20,M20) -> 109.6 | AP20: =INT(O20/AN20)*INT(P20/AO20) -> 220 | AQ20: =INT(P20/AN20)*INT(O20/AO20) -> 220 | AR20: =INT(O20/AO20)*INT(P20/AN20) -> 220 | AS20: =INT(P20/AO20)*INT(O20/AN20) -> 220 | AT20: =O20-(INT(O20/AN20)*AN20) -> 104 | AU20: =P20-(INT(P20/AN20)*AN20) -> 52 | AV20: =O20-(INT(O20/AO20)*AO20) -> 88.8 | AW20: =P20-(INT(P20/AO20)*AO20) -> 44.4 | AX20: =INT(AT20/AO20)*INT(P20/AN20) -> 0 | AY20: =INT(AU20/AO20)*INT(O20/AN20) -> 0 | AZ20: =INT(AV20/AN20)*INT(P20/AO20) -> 0 | BA20: =INT(AW20/AN20)*INT(O20/AO20) -> 0 | BB20: =AX20+AP20 -> 220 | BC20: =AY20+AQ20 -> 220 | BD20: =AZ20+AR20 -> 220 | BE20: =BA20+AS20 -> 220 | BF20: =MAX(BB20:BE20) -> 220 | BG20: =IF(BB20=BF20,MIN(INT(O20/AN20),INT(P20/AO20)),IF(BC20=BF20,MIN(INT(P20/AN20),INT(O20/AO20)),IF(BD20=BF20,MIN(INT(O20/AO20),INT(P20/AN20)),MIN(INT(P20/AO20),INT(O20/AN20))))) -> 11 | BH20: =IF(BB20=BF20,MIN(INT(AT20/AO20),INT(1250/AN20)),IF(BC20=BF20,MIN(INT(AU20/AO20),INT(O20/AN20)),IF(BD20=BF20,MIN(INT(AV20/AN20),INT(P20/AO20)),MIN(INT(AW20/AN20),INT(O20/AO20))))) -> 0 | BI20: =IFERROR(BG20+BH20,"") -> 11
B21: =_xlfn.IFNA(VLOOKUP(D21,Group!$AM$1:$AO$10000,3,0),"") -> FWR10000 | C21: =_xlfn.IFNA(VLOOKUP(D21,Group!$AM$1:$AO$10000,2,0),"") -> 3 | D21: =Group!K10 -> H 157 01 464 A Slider Upper Track | E21: =_xlfn.IFNA(VLOOKUP(D21,BOM!$D$1:$F$10000,2,0),"") -> 0 | F21: =_xlfn.IFNA(VLOOKUP(D21,BOM!$D$1:$F$10000,3,0),"") -> Slider Upper Track | G21: =_xlfn.IFNA(IF(VLOOKUP(D21,BOM!D:J,7,0)="CSC","CSC","Others"),"") -> CSC | H21: IS2062 | I21: =_xlfn.IFNA(IF(OR(VLOOKUP(D21,BOM!$D$1:$I$1000,6,0)="Inhouse",VLOOKUP(D21,BOM!$D$1:$J$1000,7,0)="CSC"),"RM","BOP"),"") -> RM | J21: =_xlfn.IFNA(IF(VLOOKUP(H21,'RM Base'!D:F,3,0)="Kg",VLOOKUP(H21,'RM Base'!D:E,2,0),IF(VLOOKUP(H21,'RM Base'!D:F,3,0)="Meter",(VLOOKUP(H21,'RM Base'!D:E,2,0)/R21*O21/1000),CONCATENATE("The Price is in ",VLOOKUP(H21,'RM Base'!D:F,3,0)))),"") -> 53 | K21: Sheet Metal | L21: 396 | M21: 85 | N21: 1.5 | O21: =IF(K21<>"",IF(OR(K21="Pipe", K21="Circular Tube", K21="Square/Rectangular Tube"),IF(ISNUMBER(SEARCH("ss", H21)), 5000, 6000),2500),"") -> 2500 | P21: =IF(OR(O21=6000,O21=5000,O21=""),M21,1250) -> 1250 | Q21: Shearing | R21: =IF(K21="Sheet Metal",O21*P21*N21*7.86/10^6,IF(OR(K21="Pipe", K21="Circular Tube"),O21*(P21^2-(P21-2*N21)^2)*3.14/4*7.86*10^-6,IF(K21="Square/Rectangular Tube",O21*P21*N21*7.86*10^-6,""))) -> 36.84375 | S21: =IF(L21<>"",IF(OR(K21="Pipe", K21="Circular Tube"),INT(O21/(L21+5)),IF(K21="Square/Rectangular Tube",INT(O21/(L21+5)),IF(Q21="Laser Cutting",AK21,BF21))),"") -> 87 | T21: =IF(OR(K21="Pipe", K21="Circular Tube"),L21*(M21^2-(M21-2*N21)^2)*3.14/4*7.86*10^-6,IF(K21="Square/Rectangular Tube",L21*M21*N21*7.86*10^-6,IF(K21="Sheet Metal",L21*M21*N21*7.86*10^-6,""))) -> 0.3968514 | U21: =IFERROR(R21/S21,"") -> 0.42349138 | V21: =IFERROR(I21*U21,"") | W21: 0.385 | X21: =IF(W21="","",W21) -> 0.385 | Y21: =IF(U21="","",W21/U21) -> 0.90910941 | Z21: =IF(Y21="","",IF(I21="RM",IF(K21="Sheet Metal",W21/N21/7.86*2,IF(OR(K21="Pipe",K21="Circular Tube"),L21*PI()*M21/10^6,IF(K21="Square/Rectangular Tube",W21/N21/7.86,0))))) -> 0.065309584 | AB21: =IF(Z21="","",U21-W21) -> 0.038491379 | AC21: =_xlfn.IFNA(VLOOKUP(H21,'RM Base'!D:K,8,0),"") -> 30.5 | AD21: =IF(K21<>"",IF(K21="Sheet Metal",95%,80%),"") -> 0.95 | AE21: =IF(AD21="","",(J21*U21)-(AB21*AC21*AD21)) -> 21.329755 | AG21: =IFERROR(IF(I21="RM",(W21*J21),AE21),"") -> 20.405 | AH21: =IFERROR(AE21-AG21,"") -> 0.92475539 | AI21: =IF(Q21="Shearing",L21,IF(Q21="Blanking",(L21+N21*1.5),IF(Q21="Laser Cutting",(L21+4)))) -> 396 | AJ21: =IF(Q21="Shearing",M21,IF(Q21="Blanking",(M21+N21*3),IF(Q21="Laser Cutting",(M21+4)))) -> 85 | AK21: =IF((INT(O21/AI21)*INT(P21/AJ21))>(INT(O21/AJ21)*INT(P21/AI21)),INT(O21/AI21)*INT(P21/AJ21),IF((INT(O21/AI21)*INT(P21/AJ21))=(INT(O21/AJ21)*INT(P21/AI21)),(INT(O21/AI21)*INT(P21/AJ21)),(INT(O21/AJ21)*INT(P21/AI21)))) -> 87 | AL21: =IF((INT(O21/AI21)*INT(P21/AJ21))>(INT(O21/AJ21)*INT(P21/AI21)),INT(O21/AI21),IF((INT(O21/AI21)*INT(P21/AJ21))=(INT(O21/AJ21)*INT(P21/AI21)),(INT(O21/AI21)),(INT(O21/AJ21)))) -> 29 | AM21: =IF((INT(O21/AI21)*INT(P21/AJ21))>(INT(O21/AJ21)*INT(P21/AI21)),INT(P21/AJ21),IF((INT(O21/AI21)*INT(P21/AJ21))=(INT(O21/AJ21)*INT(P21/AI21)),(INT(P21/AJ21)),(INT(P21/AI21)))) -> 3 | AN21: =IF(Q21="Blanking",L21+1.5*N21,L21) -> 396 | AO21: =IF(Q21="Blanking",M21+1.5*2*N21,M21) -> 85 | AP21: =INT(O21/AN21)*INT(P21/AO21) -> 84 | AQ21: =INT(P21/AN21)*INT(O21/AO21) -> 87 | AR21: =INT(O21/AO21)*INT(P21/AN21) -> 87 | AS21: =INT(P21/AO21)*INT(O21/AN21) -> 84 | AT21: =O21-(INT(O21/AN21)*AN21) -> 124 | AU21: =P21-(INT(P21/AN21)*AN21) -> 62 | AV21: =O21-(INT(O21/AO21)*AO21) -> 35 | AW21: =P21-(INT(P21/AO21)*AO21) -> 60 | AX21: =INT(AT21/AO21)*INT(P21/AN21) -> 3 | AY21: =INT(AU21/AO21)*INT(O21/AN21) -> 0 | AZ21: =INT(AV21/AN21)*INT(P21/AO21) -> 0 | BA21: =INT(AW21/AN21)*INT(O21/AO21) -> 0 | BB21: =AX21+AP21 -> 87 | BC21: =AY21+AQ21 -> 87 | BD21: =AZ21+AR21 -> 87 | BE21: =BA21+AS21 -> 84 | BF21: =MAX(BB21:BE21) -> 87 | BG21: =IF(BB21=BF21,MIN(INT(O21/AN21),INT(P21/AO21)),IF(BC21=BF21,MIN(INT(P21/AN21),INT(O21/AO21)),IF(BD21=BF21,MIN(INT(O21/AO21),INT(P21/AN21)),MIN(INT(P21/AO21),INT(O21/AN21))))) -> 6 | BH21: =IF(BB21=BF21,MIN(INT(AT21/AO21),INT(1250/AN21)),IF(BC21=BF21,MIN(INT(AU21/AO21),INT(O21/AN21)),IF(BD21=BF21,MIN(INT(AV21/AN21),INT(P21/AO21)),MIN(INT(AW21/AN21),INT(O21/AO21))))) -> 1 | BI21: =IFERROR(BG21+BH21,"") -> 7
B22: =_xlfn.IFNA(VLOOKUP(D22,Group!$AM$1:$AO$10000,3,0),"") -> FWR10000 | C22: =_xlfn.IFNA(VLOOKUP(D22,Group!$AM$1:$AO$10000,2,0),"") -> 3 | D22: =Group!K11 -> H 157 01 464 A Slider Lower Track | E22: =_xlfn.IFNA(VLOOKUP(D22,BOM!$D$1:$F$10000,2,0),"") -> 0 | F22: =_xlfn.IFNA(VLOOKUP(D22,BOM!$D$1:$F$10000,3,0),"") -> Slider Lower Track | G22: =_xlfn.IFNA(IF(VLOOKUP(D22,BOM!D:J,7,0)="CSC","CSC","Others"),"") -> CSC | H22: IS2062 | I22: =_xlfn.IFNA(IF(OR(VLOOKUP(D22,BOM!$D$1:$I$1000,6,0)="Inhouse",VLOOKUP(D22,BOM!$D$1:$J$1000,7,0)="CSC"),"RM","BOP"),"") -> RM | J22: =_xlfn.IFNA(IF(VLOOKUP(H22,'RM Base'!D:F,3,0)="Kg",VLOOKUP(H22,'RM Base'!D:E,2,0),IF(VLOOKUP(H22,'RM Base'!D:F,3,0)="Meter",(VLOOKUP(H22,'RM Base'!D:E,2,0)/R22*O22/1000),CONCATENATE("The Price is in ",VLOOKUP(H22,'RM Base'!D:F,3,0)))),"") -> 53 | K22: Sheet Metal | L22: 102 | M22: 380.5 | N22: 1.5 | O22: =IF(K22<>"",IF(OR(K22="Pipe", K22="Circular Tube", K22="Square/Rectangular Tube"),IF(ISNUMBER(SEARCH("ss", H22)), 5000, 6000),2500),"") -> 2500 | P22: =IF(OR(O22=6000,O22=5000,O22=""),M22,1250) -> 1250 | Q22: Shearing | R22: =IF(K22="Sheet Metal",O22*P22*N22*7.86/10^6,IF(OR(K22="Pipe", K22="Circular Tube"),O22*(P22^2-(P22-2*N22)^2)*3.14/4*7.86*10^-6,IF(K22="Square/Rectangular Tube",O22*P22*N22*7.86*10^-6,""))) -> 36.84375 | S22: =IF(L22<>"",IF(OR(K22="Pipe", K22="Circular Tube"),INT(O22/(L22+5)),IF(K22="Square/Rectangular Tube",INT(O22/(L22+5)),IF(Q22="Laser Cutting",AK22,BF22))),"") -> 78 | T22: =IF(OR(K22="Pipe", K22="Circular Tube"),L22*(M22^2-(M22-2*N22)^2)*3.14/4*7.86*10^-6,IF(K22="Square/Rectangular Tube",L22*M22*N22*7.86*10^-6,IF(K22="Sheet Metal",L22*M22*N22*7.86*10^-6,""))) -> 0.45758169 | U22: =IFERROR(R22/S22,"") -> 0.47235577 | V22: =IFERROR(I22*U22,"") | W22: 0.451 | X22: =IF(W22="","",W22) -> 0.451 | Y22: =IF(U22="","",W22/U22) -> 0.9547888 | Z22: =IF(Y22="","",IF(I22="RM",IF(K22="Sheet Metal",W22/N22/7.86*2,IF(OR(K22="Pipe",K22="Circular Tube"),L22*PI()*M22/10^6,IF(K22="Square/Rectangular Tube",W22/N22/7.86,0))))) -> 0.076505513 | AB22: =IF(Z22="","",U22-W22) -> 0.021355769 | AC22: =_xlfn.IFNA(VLOOKUP(H22,'RM Base'!D:K,8,0),"") -> 30.5 | AD22: =IF(K22<>"",IF(K22="Sheet Metal",95%,80%),"") -> 0.95 | AE22: =IF(AD22="","",(J22*U22)-(AB22*AC22*AD22)) -> 24.416072 | AG22: =IFERROR(IF(I22="RM",(W22*J22),AE22),"") -> 23.903 | AH22: =IFERROR(AE22-AG22,"") -> 0.51307236 | AI22: =IF(Q22="Shearing",L22,IF(Q22="Blanking",(L22+N22*1.5),IF(Q22="Laser Cutting",(L22+4)))) -> 102 | AJ22: =IF(Q22="Shearing",M22,IF(Q22="Blanking",(M22+N22*3),IF(Q22="Laser Cutting",(M22+4)))) -> 380.5 | AK22: =IF((INT(O22/AI22)*INT(P22/AJ22))>(INT(O22/AJ22)*INT(P22/AI22)),INT(O22/AI22)*INT(P22/AJ22),IF((INT(O22/AI22)*INT(P22/AJ22))=(INT(O22/AJ22)*INT(P22/AI22)),(INT(O22/AI22)*INT(P22/AJ22)),(INT(O22/AJ22)*INT(P22/AI22)))) -> 72 | AL22: =IF((INT(O22/AI22)*INT(P22/AJ22))>(INT(O22/AJ22)*INT(P22/AI22)),INT(O22/AI22),IF((INT(O22/AI22)*INT(P22/AJ22))=(INT(O22/AJ22)*INT(P22/AI22)),(INT(O22/AI22)),(INT(O22/AJ22)))) -> 24 | AM22: =IF((INT(O22/AI22)*INT(P22/AJ22))>(INT(O22/AJ22)*INT(P22/AI22)),INT(P22/AJ22),IF((INT(O22/AI22)*INT(P22/AJ22))=(INT(O22/AJ22)*INT(P22/AI22)),(INT(P22/AJ22)),(INT(P22/AI22)))) -> 3 | AN22: =IF(Q22="Blanking",L22+1.5*N22,L22) -> 102 | AO22: =IF(Q22="Blanking",M22+1.5*2*N22,M22) -> 380.5 | AP22: =INT(O22/AN22)*INT(P22/AO22) -> 72 | AQ22: =INT(P22/AN22)*INT(O22/AO22) -> 72 | AR22: =INT(O22/AO22)*INT(P22/AN22) -> 72 | AS22: =INT(P22/AO22)*INT(O22/AN22) -> 72 | AT22: =O22-(INT(O22/AN22)*AN22) -> 52 | AU22: =P22-(INT(P22/AN22)*AN22) -> 26 | AV22: =O22-(INT(O22/AO22)*AO22) -> 217 | AW22: =P22-(INT(P22/AO22)*AO22) -> 108.5 | AX22: =INT(AT22/AO22)*INT(P22/AN22) -> 0 | AY22: =INT(AU22/AO22)*INT(O22/AN22) -> 0 | AZ22: =INT(AV22/AN22)*INT(P22/AO22) -> 6 | BA22: =INT(AW22/AN22)*INT(O22/AO22) -> 6 | BB22: =AX22+AP22 -> 72 | BC22: =AY22+AQ22 -> 72 | BD22: =AZ22+AR22 -> 78 | BE22: =BA22+AS22 -> 78 | BF22: =MAX(BB22:BE22) -> 78 | BG22: =IF(BB22=BF22,MIN(INT(O22/AN22),INT(P22/AO22)),IF(BC22=BF22,MIN(INT(P22/AN22),INT(O22/AO22)),IF(BD22=BF22,MIN(INT(O22/AO22),INT(P22/AN22)),MIN(INT(P22/AO22),INT(O22/AN22))))) -> 6 | BH22: =IF(BB22=BF22,MIN(INT(AT22/AO22),INT(1250/AN22)),IF(BC22=BF22,MIN(INT(AU22/AO22),INT(O22/AN22)),IF(BD22=BF22,MIN(INT(AV22/AN22),INT(P22/AO22)),MIN(INT(AW22/AN22),INT(O22/AO22))))) -> 2 | BI22: =IFERROR(BG22+BH22,"") -> 8
B23: =_xlfn.IFNA(VLOOKUP(D23,Group!$AM$1:$AO$10000,3,0),"") -> FWR10000 | C23: =_xlfn.IFNA(VLOOKUP(D23,Group!$AM$1:$AO$10000,2,0),"") -> 3 | D23: =Group!K12 -> H 157 01 464 A Slider Upper Track plate | E23: =_xlfn.IFNA(VLOOKUP(D23,BOM!$D$1:$F$10000,2,0),"") -> 0 | F23: =_xlfn.IFNA(VLOOKUP(D23,BOM!$D$1:$F$10000,3,0),"") -> Slider Upper Track plate | G23: =_xlfn.IFNA(IF(VLOOKUP(D23,BOM!D:J,7,0)="CSC","CSC","Others"),"") -> CSC | H23: IS2062 | I23: =_xlfn.IFNA(IF(OR(VLOOKUP(D23,BOM!$D$1:$I$1000,6,0)="Inhouse",VLOOKUP(D23,BOM!$D$1:$J$1000,7,0)="CSC"),"RM","BOP"),"") -> RM | J23: =_xlfn.IFNA(IF(VLOOKUP(H23,'RM Base'!D:F,3,0)="Kg",VLOOKUP(H23,'RM Base'!D:E,2,0),IF(VLOOKUP(H23,'RM Base'!D:F,3,0)="Meter",(VLOOKUP(H23,'RM Base'!D:E,2,0)/R23*O23/1000),CONCATENATE("The Price is in ",VLOOKUP(H23,'RM Base'!D:F,3,0)))),"") -> 53 | K23: Sheet Metal | L23: 19 | M23: 136.5 | N23: 2 | O23: =IF(K23<>"",IF(OR(K23="Pipe", K23="Circular Tube", K23="Square/Rectangular Tube"),IF(ISNUMBER(SEARCH("ss", H23)), 5000, 6000),2500),"") -> 2500 | P23: =IF(OR(O23=6000,O23=5000,O23=""),M23,1250) -> 1250 | Q23: Blanking | R23: =IF(K23="Sheet Metal",O23*P23*N23*7.86/10^6,IF(OR(K23="Pipe", K23="Circular Tube"),O23*(P23^2-(P23-2*N23)^2)*3.14/4*7.86*10^-6,IF(K23="Square/Rectangular Tube",O23*P23*N23*7.86*10^-6,""))) -> 49.125 | S23: =IF(L23<>"",IF(OR(K23="Pipe", K23="Circular Tube"),INT(O23/(L23+5)),IF(K23="Square/Rectangular Tube",INT(O23/(L23+5)),IF(Q23="Laser Cutting",AK23,BF23))),"") -> 989 | T23: =IF(OR(K23="Pipe", K23="Circular Tube"),L23*(M23^2-(M23-2*N23)^2)*3.14/4*7.86*10^-6,IF(K23="Square/Rectangular Tube",L23*M23*N23*7.86*10^-6,IF(K23="Sheet Metal",L23*M23*N23*7.86*10^-6,""))) -> 0.04076982 | U23: =IFERROR(R23/S23,"") -> 0.049671385 | V23: =IFERROR(I23*U23,"") | W23: 0.036 | X23: =IF(W23="","",W23) -> 0.036 | Y23: =IF(U23="","",W23/U23) -> 0.72476336 | Z23: =IF(Y23="","",IF(I23="RM",IF(K23="Sheet Metal",W23/N23/7.86*2,IF(OR(K23="Pipe",K23="Circular Tube"),L23*PI()*M23/10^6,IF(K23="Square/Rectangular Tube",W23/N23/7.86,0))))) -> 0.0045801527 | AB23: =IF(Z23="","",U23-W23) -> 0.013671385 | AC23: =_xlfn.IFNA(VLOOKUP(H23,'RM Base'!D:K,8,0),"") -> 30.5 | AD23: =IF(K23<>"",IF(K23="Sheet Metal",95%,80%),"") -> 0.95 | AE23: =IF(AD23="","",(J23*U23)-(AB23*AC23*AD23)) -> 2.236455 | AG23: =IFERROR(IF(I23="RM",(W23*J23),AE23),"") -> 1.908 | AH23: =IFERROR(AE23-AG23,"") -> 0.32845503 | AI23: =IF(Q23="Shearing",L23,IF(Q23="Blanking",(L23+N23*1.5),IF(Q23="Laser Cutting",(L23+4)))) -> 22 | AJ23: =IF(Q23="Shearing",M23,IF(Q23="Blanking",(M23+N23*3),IF(Q23="Laser Cutting",(M23+4)))) -> 142.5 | AK23: =IF((INT(O23/AI23)*INT(P23/AJ23))>(INT(O23/AJ23)*INT(P23/AI23)),INT(O23/AI23)*INT(P23/AJ23),IF((INT(O23/AI23)*INT(P23/AJ23))=(INT(O23/AJ23)*INT(P23/AI23)),(INT(O23/AI23)*INT(P23/AJ23)),(INT(O23/AJ23)*INT(P23/AI23)))) -> 952 | AL23: =IF((INT(O23/AI23)*INT(P23/AJ23))>(INT(O23/AJ23)*INT(P23/AI23)),INT(O23/AI23),IF((INT(O23/AI23)*INT(P23/AJ23))=(INT(O23/AJ23)*INT(P23/AI23)),(INT(O23/AI23)),(INT(O23/AJ23)))) -> 17 | AM23: =IF((INT(O23/AI23)*INT(P23/AJ23))>(INT(O23/AJ23)*INT(P23/AI23)),INT(P23/AJ23),IF((INT(O23/AI23)*INT(P23/AJ23))=(INT(O23/AJ23)*INT(P23/AI23)),(INT(P23/AJ23)),(INT(P23/AI23)))) -> 56 | AN23: =IF(Q23="Blanking",L23+1.5*N23,L23) -> 22 | AO23: =IF(Q23="Blanking",M23+1.5*2*N23,M23) -> 142.5 | AP23: =INT(O23/AN23)*INT(P23/AO23) -> 904 | AQ23: =INT(P23/AN23)*INT(O23/AO23) -> 952 | AR23: =INT(O23/AO23)*INT(P23/AN23) -> 952 | AS23: =INT(P23/AO23)*INT(O23/AN23) -> 904 | AT23: =O23-(INT(O23/AN23)*AN23) -> 14 | AU23: =P23-(INT(P23/AN23)*AN23) -> 18 | AV23: =O23-(INT(O23/AO23)*AO23) -> 77.5 | AW23: =P23-(INT(P23/AO23)*AO23) -> 110 | AX23: =INT(AT23/AO23)*INT(P23/AN23) -> 0 | AY23: =INT(AU23/AO23)*INT(O23/AN23) -> 0 | AZ23: =INT(AV23/AN23)*INT(P23/AO23) -> 24 | BA23: =INT(AW23/AN23)*INT(O23/AO23) -> 85 | BB23: =AX23+AP23 -> 904 | BC23: =AY23+AQ23 -> 952 | BD23: =AZ23+AR23 -> 976 | BE23: =BA23+AS23 -> 989 | BF23: =MAX(BB23:BE23) -> 989 | BG23: =IF(BB23=BF23,MIN(INT(O23/AN23),INT(P23/AO23)),IF(BC23=BF23,MIN(INT(P23/AN23),INT(O23/AO23)),IF(BD23=BF23,MIN(INT(O23/AO23),INT(P23/AN23)),MIN(INT(P23/AO23),INT(O23/AN23))))) -> 8 | BH23: =IF(BB23=BF23,MIN(INT(AT23/AO23),INT(1250/AN23)),IF(BC23=BF23,MIN(INT(AU23/AO23),INT(O23/AN23)),IF(BD23=BF23,MIN(INT(AV23/AN23),INT(P23/AO23)),MIN(INT(AW23/AN23),INT(O23/AO23))))) -> 5 | BI23: =IFERROR(BG23+BH23,"") -> 13
B24: =_xlfn.IFNA(VLOOKUP(D24,Group!$AM$1:$AO$10000,3,0),"") -> FWR10000 | C24: =_xlfn.IFNA(VLOOKUP(D24,Group!$AM$1:$AO$10000,2,0),"") -> 3 | D24: =Group!K13 -> H 157 01 464 A Slider Lower Track REINF | E24: =_xlfn.IFNA(VLOOKUP(D24,BOM!$D$1:$F$10000,2,0),"") -> 0 | F24: =_xlfn.IFNA(VLOOKUP(D24,BOM!$D$1:$F$10000,3,0),"") -> Slider Lower Track REINF | G24: =_xlfn.IFNA(IF(VLOOKUP(D24,BOM!D:J,7,0)="CSC","CSC","Others"),"") -> CSC | H24: IS2062 | I24: =_xlfn.IFNA(IF(OR(VLOOKUP(D24,BOM!$D$1:$I$1000,6,0)="Inhouse",VLOOKUP(D24,BOM!$D$1:$J$1000,7,0)="CSC"),"RM","BOP"),"") -> RM | J24: =_xlfn.IFNA(IF(VLOOKUP(H24,'RM Base'!D:F,3,0)="Kg",VLOOKUP(H24,'RM Base'!D:E,2,0),IF(VLOOKUP(H24,'RM Base'!D:F,3,0)="Meter",(VLOOKUP(H24,'RM Base'!D:E,2,0)/R24*O24/1000),CONCATENATE("The Price is in ",VLOOKUP(H24,'RM Base'!D:F,3,0)))),"") -> 53 | K24: Sheet Metal | L24: 95 | M24: 54 | N24: 1.5 | O24: =IF(K24<>"",IF(OR(K24="Pipe", K24="Circular Tube", K24="Square/Rectangular Tube"),IF(ISNUMBER(SEARCH("ss", H24)), 5000, 6000),2500),"") -> 2500 | P24: =IF(OR(O24=6000,O24=5000,O24=""),M24,1250) -> 1250 | Q24: Blanking | R24: =IF(K24="Sheet Metal",O24*P24*N24*7.86/10^6,IF(OR(K24="Pipe", K24="Circular Tube"),O24*(P24^2-(P24-2*N24)^2)*3.14/4*7.86*10^-6,IF(K24="Square/Rectangular Tube",O24*P24*N24*7.86*10^-6,""))) -> 36.84375 | S24: =IF(L24<>"",IF(OR(K24="Pipe", K24="Circular Tube"),INT(O24/(L24+5)),IF(K24="Square/Rectangular Tube",INT(O24/(L24+5)),IF(Q24="Laser Cutting",AK24,BF24))),"") -> 537 | T24: =IF(OR(K24="Pipe", K24="Circular Tube"),L24*(M24^2-(M24-2*N24)^2)*3.14/4*7.86*10^-6,IF(K24="Square/Rectangular Tube",L24*M24*N24*7.86*10^-6,IF(K24="Sheet Metal",L24*M24*N24*7.86*10^-6,""))) -> 0.0604827 | U24: =IFERROR(R24/S24,"") -> 0.068610335 | V24: =IFERROR(I24*U24,"") | W24: 0.052 | X24: =IF(W24="","",W24) -> 0.052 | Y24: =IF(U24="","",W24/U24) -> 0.75790331 | Z24: =IF(Y24="","",IF(I24="RM",IF(K24="Sheet Metal",W24/N24/7.86*2,IF(OR(K24="Pipe",K24="Circular Tube"),L24*PI()*M24/10^6,IF(K24="Square/Rectangular Tube",W24/N24/7.86,0))))) -> 0.0088210348 | AB24: =IF(Z24="","",U24-W24) -> 0.016610335 | AC24: =_xlfn.IFNA(VLOOKUP(H24,'RM Base'!D:K,8,0),"") -> 30.5 | AD24: =IF(K24<>"",IF(K24="Sheet Metal",95%,80%),"") -> 0.95 | AE24: =IF(AD24="","",(J24*U24)-(AB24*AC24*AD24)) -> 3.1550633 | AG24: =IFERROR(IF(I24="RM",(W24*J24),AE24),"") -> 2.756 | AH24: =IFERROR(AE24-AG24,"") -> 0.3990633 | AI24: =IF(Q24="Shearing",L24,IF(Q24="Blanking",(L24+N24*1.5),IF(Q24="Laser Cutting",(L24+4)))) -> 97.25 | AJ24: =IF(Q24="Shearing",M24,IF(Q24="Blanking",(M24+N24*3),IF(Q24="Laser Cutting",(M24+4)))) -> 58.5 | AK24: =IF((INT(O24/AI24)*INT(P24/AJ24))>(INT(O24/AJ24)*INT(P24/AI24)),INT(O24/AI24)*INT(P24/AJ24),IF((INT(O24/AI24)*INT(P24/AJ24))=(INT(O24/AJ24)*INT(P24/AI24)),(INT(O24/AI24)*INT(P24/AJ24)),(INT(O24/AJ24)*INT(P24/AI24)))) -> 525 | AL24: =IF((INT(O24/AI24)*INT(P24/AJ24))>(INT(O24/AJ24)*INT(P24/AI24)),INT(O24/AI24),IF((INT(O24/AI24)*INT(P24/AJ24))=(INT(O24/AJ24)*INT(P24/AI24)),(INT(O24/AI24)),(INT(O24/AJ24)))) -> 25 | AM24: =IF((INT(O24/AI24)*INT(P24/AJ24))>(INT(O24/AJ24)*INT(P24/AI24)),INT(P24/AJ24),IF((INT(O24/AI24)*INT(P24/AJ24))=(INT(O24/AJ24)*INT(P24/AI24)),(INT(P24/AJ24)),(INT(P24/AI24)))) -> 21 | AN24: =IF(Q24="Blanking",L24+1.5*N24,L24) -> 97.25 | AO24: =IF(Q24="Blanking",M24+1.5*2*N24,M24) -> 58.5 | AP24: =INT(O24/AN24)*INT(P24/AO24) -> 525 | AQ24: =INT(P24/AN24)*INT(O24/AO24) -> 504 | AR24: =INT(O24/AO24)*INT(P24/AN24) -> 504 | AS24: =INT(P24/AO24)*INT(O24/AN24) -> 525 | AT24: =O24-(INT(O24/AN24)*AN24) -> 68.75 | AU24: =P24-(INT(P24/AN24)*AN24) -> 83 | AV24: =O24-(INT(O24/AO24)*AO24) -> 43 | AW24: =P24-(INT(P24/AO24)*AO24) -> 21.5 | AX24: =INT(AT24/AO24)*INT(P24/AN24) -> 12 | AY24: =INT(AU24/AO24)*INT(O24/AN24) -> 25 | AZ24: =INT(AV24/AN24)*INT(P24/AO24) -> 0 | BA24: =INT(AW24/AN24)*INT(O24/AO24) -> 0 | BB24: =AX24+AP24 -> 537 | BC24: =AY24+AQ24 -> 529 | BD24: =AZ24+AR24 -> 504 | BE24: =BA24+AS24 -> 525 | BF24: =MAX(BB24:BE24) -> 537 | BG24: =IF(BB24=BF24,MIN(INT(O24/AN24),INT(P24/AO24)),IF(BC24=BF24,MIN(INT(P24/AN24),INT(O24/AO24)),IF(BD24=BF24,MIN(INT(O24/AO24),INT(P24/AN24)),MIN(INT(P24/AO24),INT(O24/AN24))))) -> 21 | BH24: =IF(BB24=BF24,MIN(INT(AT24/AO24),INT(1250/AN24)),IF(BC24=BF24,MIN(INT(AU24/AO24),INT(O24/AN24)),IF(BD24=BF24,MIN(INT(AV24/AN24),INT(P24/AO24)),MIN(INT(AW24/AN24),INT(O24/AO24))))) -> 1 | BI24: =IFERROR(BG24+BH24,"") -> 22
B25: =_xlfn.IFNA(VLOOKUP(D25,Group!$AM$1:$AO$10000,3,0),"") -> FWR10000 | C25: =_xlfn.IFNA(VLOOKUP(D25,Group!$AM$1:$AO$10000,2,0),"") -> 3 | D25: =Group!K14 -> H 157 01 464 A Slider Upper Track REINF | E25: =_xlfn.IFNA(VLOOKUP(D25,BOM!$D$1:$F$10000,2,0),"") -> 0 | F25: =_xlfn.IFNA(VLOOKUP(D25,BOM!$D$1:$F$10000,3,0),"") -> Slider Upper Track REINF | G25: =_xlfn.IFNA(IF(VLOOKUP(D25,BOM!D:J,7,0)="CSC","CSC","Others"),"") -> CSC | H25: IS2062 | I25: =_xlfn.IFNA(IF(OR(VLOOKUP(D25,BOM!$D$1:$I$1000,6,0)="Inhouse",VLOOKUP(D25,BOM!$D$1:$J$1000,7,0)="CSC"),"RM","BOP"),"") -> RM | J25: =_xlfn.IFNA(IF(VLOOKUP(H25,'RM Base'!D:F,3,0)="Kg",VLOOKUP(H25,'RM Base'!D:E,2,0),IF(VLOOKUP(H25,'RM Base'!D:F,3,0)="Meter",(VLOOKUP(H25,'RM Base'!D:E,2,0)/R25*O25/1000),CONCATENATE("The Price is in ",VLOOKUP(H25,'RM Base'!D:F,3,0)))),"") -> 53 | K25: Sheet Metal | L25: 120 | M25: 14 | N25: 1.5 | O25: =IF(K25<>"",IF(OR(K25="Pipe", K25="Circular Tube", K25="Square/Rectangular Tube"),IF(ISNUMBER(SEARCH("ss", H25)), 5000, 6000),2500),"") -> 2500 | P25: =IF(OR(O25=6000,O25=5000,O25=""),M25,1250) -> 1250 | Q25: Blanking | R25: =IF(K25="Sheet Metal",O25*P25*N25*7.86/10^6,IF(OR(K25="Pipe", K25="Circular Tube"),O25*(P25^2-(P25-2*N25)^2)*3.14/4*7.86*10^-6,IF(K25="Square/Rectangular Tube",O25*P25*N25*7.86*10^-6,""))) -> 36.84375 | S25: =IF(L25<>"",IF(OR(K25="Pipe", K25="Circular Tube"),INT(O25/(L25+5)),IF(K25="Square/Rectangular Tube",INT(O25/(L25+5)),IF(Q25="Laser Cutting",AK25,BF25))),"") -> 1370 | T25: =IF(OR(K25="Pipe", K25="Circular Tube"),L25*(M25^2-(M25-2*N25)^2)*3.14/4*7.86*10^-6,IF(K25="Square/Rectangular Tube",L25*M25*N25*7.86*10^-6,IF(K25="Sheet Metal",L25*M25*N25*7.86*10^-6,""))) -> 0.0198072 | U25: =IFERROR(R25/S25,"") -> 0.026893248 | V25: =IFERROR(I25*U25,"") | W25: 0.018 | X25: =IF(W25="","",W25) -> 0.018 | Y25: =IF(U25="","",W25/U25) -> 0.66931298 | Z25: =IF(Y25="","",IF(I25="RM",IF(K25="Sheet Metal",W25/N25/7.86*2,IF(OR(K25="Pipe",K25="Circular Tube"),L25*PI()*M25/10^6,IF(K25="Square/Rectangular Tube",W25/N25/7.86,0))))) -> 0.0030534351 | AB25: =IF(Z25="","",U25-W25) -> 0.0088932482 | AC25: =_xlfn.IFNA(VLOOKUP(H25,'RM Base'!D:K,8,0),"") -> 30.5 | AD25: =IF(K25<>"",IF(K25="Sheet Metal",95%,80%),"") -> 0.95 | AE25: =IF(AD25="","",(J25*U25)-(AB25*AC25*AD25)) -> 1.1676603 | AG25: =IFERROR(IF(I25="RM",(W25*J25),AE25),"") -> 0.954 | AH25: =IFERROR(AE25-AG25,"") -> 0.21366029 | AI25: =IF(Q25="Shearing",L25,IF(Q25="Blanking",(L25+N25*1.5),IF(Q25="Laser Cutting",(L25+4)))) -> 122.25 | AJ25: =IF(Q25="Shearing",M25,IF(Q25="Blanking",(M25+N25*3),IF(Q25="Laser Cutting",(M25+4)))) -> 18.5 | AK25: =IF((INT(O25/AI25)*INT(P25/AJ25))>(INT(O25/AJ25)*INT(P25/AI25)),INT(O25/AI25)*INT(P25/AJ25),IF((INT(O25/AI25)*INT(P25/AJ25))=(INT(O25/AJ25)*INT(P25/AI25)),(INT(O25/AI25)*INT(P25/AJ25)),(INT(O25/AJ25)*INT(P25/AI25)))) -> 1350 | AL25: =IF((INT(O25/AI25)*INT(P25/AJ25))>(INT(O25/AJ25)*INT(P25/AI25)),INT(O25/AI25),IF((INT(O25/AI25)*INT(P25/AJ25))=(INT(O25/AJ25)*INT(P25/AI25)),(INT(O25/AI25)),(INT(O25/AJ25)))) -> 135 | AM25: =IF((INT(O25/AI25)*INT(P25/AJ25))>(INT(O25/AJ25)*INT(P25/AI25)),INT(P25/AJ25),IF((INT(O25/AI25)*INT(P25/AJ25))=(INT(O25/AJ25)*INT(P25/AI25)),(INT(P25/AJ25)),(INT(P25/AI25)))) -> 10 | AN25: =IF(Q25="Blanking",L25+1.5*N25,L25) -> 122.25 | AO25: =IF(Q25="Blanking",M25+1.5*2*N25,M25) -> 18.5 | AP25: =INT(O25/AN25)*INT(P25/AO25) -> 1340 | AQ25: =INT(P25/AN25)*INT(O25/AO25) -> 1350 | AR25: =INT(O25/AO25)*INT(P25/AN25) -> 1350 | AS25: =INT(P25/AO25)*INT(O25/AN25) -> 1340 | AT25: =O25-(INT(O25/AN25)*AN25) -> 55 | AU25: =P25-(INT(P25/AN25)*AN25) -> 27.5 | AV25: =O25-(INT(O25/AO25)*AO25) -> 2.5 | AW25: =P25-(INT(P25/AO25)*AO25) -> 10.5 | AX25: =INT(AT25/AO25)*INT(P25/AN25) -> 20 | AY25: =INT(AU25/AO25)*INT(O25/AN25) -> 20 | AZ25: =INT(AV25/AN25)*INT(P25/AO25) -> 0 | BA25: =INT(AW25/AN25)*INT(O25/AO25) -> 0 | BB25: =AX25+AP25 -> 1360 | BC25: =AY25+AQ25 -> 1370 | BD25: =AZ25+AR25 -> 1350 | BE25: =BA25+AS25 -> 1340 | BF25: =MAX(BB25:BE25) -> 1370 | BG25: =IF(BB25=BF25,MIN(INT(O25/AN25),INT(P25/AO25)),IF(BC25=BF25,MIN(INT(P25/AN25),INT(O25/AO25)),IF(BD25=BF25,MIN(INT(O25/AO25),INT(P25/AN25)),MIN(INT(P25/AO25),INT(O25/AN25))))) -> 10 | BH25: =IF(BB25=BF25,MIN(INT(AT25/AO25),INT(1250/AN25)),IF(BC25=BF25,MIN(INT(AU25/AO25),INT(O25/AN25)),IF(BD25=BF25,MIN(INT(AV25/AN25),INT(P25/AO25)),MIN(INT(AW25/AN25),INT(O25/AO25))))) -> 1 | BI25: =IFERROR(BG25+BH25,"") -> 11
B26: =_xlfn.IFNA(VLOOKUP(D26,Group!$AM$1:$AO$10000,3,0),"") -> FWR10000 | C26: =_xlfn.IFNA(VLOOKUP(D26,Group!$AM$1:$AO$10000,2,0),"") -> 3 | D26: =Group!K15 -> H 157 01 464 A Screw M8*20 steel Hexagon socket head cap | E26: =_xlfn.IFNA(VLOOKUP(D26,BOM!$D$1:$F$10000,2,0),"") -> 0 | F26: =_xlfn.IFNA(VLOOKUP(D26,BOM!$D$1:$F$10000,3,0),"") -> Screw M8*20 steel Hexagon socket head cap | G26: =_xlfn.IFNA(IF(VLOOKUP(D26,BOM!D:J,7,0)="CSC","CSC","Others"),"") -> Others | I26: =_xlfn.IFNA(IF(OR(VLOOKUP(D26,BOM!$D$1:$I$1000,6,0)="Inhouse",VLOOKUP(D26,BOM!$D$1:$J$1000,7,0)="CSC"),"RM","BOP"),"") -> BOP | J26: =_xlfn.IFNA(IF(VLOOKUP(H26,'RM Base'!D:F,3,0)="Kg",VLOOKUP(H26,'RM Base'!D:E,2,0),IF(VLOOKUP(H26,'RM Base'!D:F,3,0)="Meter",(VLOOKUP(H26,'RM Base'!D:E,2,0)/R26*O26/1000),CONCATENATE("The Price is in ",VLOOKUP(H26,'RM Base'!D:F,3,0)))),"") | O26: =IF(K26<>"",IF(OR(K26="Pipe", K26="Circular Tube", K26="Square/Rectangular Tube"),IF(ISNUMBER(SEARCH("ss", H26)), 5000, 6000),2500),"") | P26: =IF(OR(O26=6000,O26=5000,O26=""),M26,1250) -> 0 | R26: =IF(K26="Sheet Metal",O26*P26*N26*7.86/10^6,IF(OR(K26="Pipe", K26="Circular Tube"),O26*(P26^2-(P26-2*N26)^2)*3.14/4*7.86*10^-6,IF(K26="Square/Rectangular Tube",O26*P26*N26*7.86*10^-6,""))) | S26: =IF(L26<>"",IF(OR(K26="Pipe", K26="Circular Tube"),INT(O26/(L26+5)),IF(K26="Square/Rectangular Tube",INT(O26/(L26+5)),IF(Q26="Laser Cutting",AK26,BF26))),"") | T26: =IF(OR(K26="Pipe", K26="Circular Tube"),L26*(M26^2-(M26-2*N26)^2)*3.14/4*7.86*10^-6,IF(K26="Square/Rectangular Tube",L26*M26*N26*7.86*10^-6,IF(K26="Sheet Metal",L26*M26*N26*7.86*10^-6,""))) | U26: =IFERROR(R26/S26,"") | V26: =IFERROR(I26*U26,"") | X26: =IF(W26="","",W26) | Y26: =IF(U26="","",W26/U26) | Z26: =IF(Y26="","",IF(I26="RM",IF(K26="Sheet Metal",W26/N26/7.86*2,IF(OR(K26="Pipe",K26="Circular Tube"),L26*PI()*M26/10^6,IF(K26="Square/Rectangular Tube",W26/N26/7.86,0))))) | AB26: =IF(Z26="","",U26-W26) | AC26: =_xlfn.IFNA(VLOOKUP(H26,'RM Base'!D:K,8,0),"") | AD26: =IF(K26<>"",IF(K26="Sheet Metal",95%,80%),"") | AE26: 3.42 | AG26: =IFERROR(IF(I26="RM",(W26*J26),AE26),"") -> 3.42 | AH26: =IFERROR(AE26-AG26,"") -> 0 | AI26: =IF(Q26="Shearing",L26,IF(Q26="Blanking",(L26+N26*1.5),IF(Q26="Laser Cutting",(L26+4)))) -> FALSE | AJ26: =IF(Q26="Shearing",M26,IF(Q26="Blanking",(M26+N26*3),IF(Q26="Laser Cutting",(M26+4)))) -> FALSE | AK26: =IF((INT(O26/AI26)*INT(P26/AJ26))>(INT(O26/AJ26)*INT(P26/AI26)),INT(O26/AI26)*INT(P26/AJ26),IF((INT(O26/AI26)*INT(P26/AJ26))=(INT(O26/AJ26)*INT(P26/AI26)),(INT(O26/AI26)*INT(P26/AJ26)),(INT(O26/AJ26)*INT(P26/AI26)))) -> #VALUE! | AL26: =IF((INT(O26/AI26)*INT(P26/AJ26))>(INT(O26/AJ26)*INT(P26/AI26)),INT(O26/AI26),IF((INT(O26/AI26)*INT(P26/AJ26))=(INT(O26/AJ26)*INT(P26/AI26)),(INT(O26/AI26)),(INT(O26/AJ26)))) -> #VALUE! | AM26: =IF((INT(O26/AI26)*INT(P26/AJ26))>(INT(O26/AJ26)*INT(P26/AI26)),INT(P26/AJ26),IF((INT(O26/AI26)*INT(P26/AJ26))=(INT(O26/AJ26)*INT(P26/AI26)),(INT(P26/AJ26)),(INT(P26/AI26)))) -> #VALUE! | AN26: =IF(Q26="Blanking",L26+1.5*N26,L26) -> 0 | AO26: =IF(Q26="Blanking",M26+1.5*2*N26,M26) -> 0 | AP26: =INT(O26/AN26)*INT(P26/AO26) -> #VALUE! | AQ26: =INT(P26/AN26)*INT(O26/AO26) -> #DIV/0! | AR26: =INT(O26/AO26)*INT(P26/AN26) -> #VALUE! | AS26: =INT(P26/AO26)*INT(O26/AN26) -> #DIV/0! | AT26: =O26-(INT(O26/AN26)*AN26) -> #VALUE! | AU26: =P26-(INT(P26/AN26)*AN26) -> #DIV/0! | AV26: =O26-(INT(O26/AO26)*AO26) -> #VALUE! | AW26: =P26-(INT(P26/AO26)*AO26) -> #DIV/0! | AX26: =INT(AT26/AO26)*INT(P26/AN26) -> #VALUE! | AY26: =INT(AU26/AO26)*INT(O26/AN26) -> #DIV/0! | AZ26: =INT(AV26/AN26)*INT(P26/AO26) -> #VALUE! | BA26: =INT(AW26/AN26)*INT(O26/AO26) -> #DIV/0! | BB26: =AX26+AP26 -> #VALUE! | BC26: =AY26+AQ26 -> #DIV/0! | BD26: =AZ26+AR26 -> #VALUE! | BE26: =BA26+AS26 -> #DIV/0! | BF26: =MAX(BB26:BE26) -> #VALUE! | BG26: =IF(BB26=BF26,MIN(INT(O26/AN26),INT(P26/AO26)),IF(BC26=BF26,MIN(INT(P26/AN26),INT(O26/AO26)),IF(BD26=BF26,MIN(INT(O26/AO26),INT(P26/AN26)),MIN(INT(P26/AO26),INT(O26/AN26))))) -> #VALUE! | BH26: =IF(BB26=BF26,MIN(INT(AT26/AO26),INT(1250/AN26)),IF(BC26=BF26,MIN(INT(AU26/AO26),INT(O26/AN26)),IF(BD26=BF26,MIN(INT(AV26/AN26),INT(P26/AO26)),MIN(INT(AW26/AN26),INT(O26/AO26))))) -> #VALUE! | BI26: =IFERROR(BG26+BH26,"")
B27: =_xlfn.IFNA(VLOOKUP(D27,Group!$AM$1:$AO$10000,3,0),"") -> FWR10000 | C27: =_xlfn.IFNA(VLOOKUP(D27,Group!$AM$1:$AO$10000,2,0),"") -> 3 | D27: =Group!K16 -> H 157 01 464 A Nut M8 Privailing torque type - hexagon thin | E27: =_xlfn.IFNA(VLOOKUP(D27,BOM!$D$1:$F$10000,2,0),"") -> 0 | F27: =_xlfn.IFNA(VLOOKUP(D27,BOM!$D$1:$F$10000,3,0),"") -> Nut M8 Privailing torque type - hexagon thin | G27: =_xlfn.IFNA(IF(VLOOKUP(D27,BOM!D:J,7,0)="CSC","CSC","Others"),"") -> Others | I27: =_xlfn.IFNA(IF(OR(VLOOKUP(D27,BOM!$D$1:$I$1000,6,0)="Inhouse",VLOOKUP(D27,BOM!$D$1:$J$1000,7,0)="CSC"),"RM","BOP"),"") -> BOP | J27: =_xlfn.IFNA(IF(VLOOKUP(H27,'RM Base'!D:F,3,0)="Kg",VLOOKUP(H27,'RM Base'!D:E,2,0),IF(VLOOKUP(H27,'RM Base'!D:F,3,0)="Meter",(VLOOKUP(H27,'RM Base'!D:E,2,0)/R27*O27/1000),CONCATENATE("The Price is in ",VLOOKUP(H27,'RM Base'!D:F,3,0)))),"") | O27: =IF(K27<>"",IF(OR(K27="Pipe", K27="Circular Tube", K27="Square/Rectangular Tube"),IF(ISNUMBER(SEARCH("ss", H27)), 5000, 6000),2500),"") | P27: =IF(OR(O27=6000,O27=5000,O27=""),M27,1250) -> 0 | R27: =IF(K27="Sheet Metal",O27*P27*N27*7.86/10^6,IF(OR(K27="Pipe", K27="Circular Tube"),O27*(P27^2-(P27-2*N27)^2)*3.14/4*7.86*10^-6,IF(K27="Square/Rectangular Tube",O27*P27*N27*7.86*10^-6,""))) | S27: =IF(L27<>"",IF(OR(K27="Pipe", K27="Circular Tube"),INT(O27/(L27+5)),IF(K27="Square/Rectangular Tube",INT(O27/(L27+5)),IF(Q27="Laser Cutting",AK27,BF27))),"") | T27: =IF(OR(K27="Pipe", K27="Circular Tube"),L27*(M27^2-(M27-2*N27)^2)*3.14/4*7.86*10^-6,IF(K27="Square/Rectangular Tube",L27*M27*N27*7.86*10^-6,IF(K27="Sheet Metal",L27*M27*N27*7.86*10^-6,""))) | U27: =IFERROR(R27/S27,"") | V27: =IFERROR(I27*U27,"") | X27: =IF(W27="","",W27) | Y27: =IF(U27="","",W27/U27) | Z27: =IF(Y27="","",IF(I27="RM",IF(K27="Sheet Metal",W27/N27/7.86*2,IF(OR(K27="Pipe",K27="Circular Tube"),L27*PI()*M27/10^6,IF(K27="Square/Rectangular Tube",W27/N27/7.86,0))))) | AB27: =IF(Z27="","",U27-W27) | AC27: =_xlfn.IFNA(VLOOKUP(H27,'RM Base'!D:K,8,0),"") | AD27: =IF(K27<>"",IF(K27="Sheet Metal",95%,80%),"") | AE27: 0.77 | AG27: =IFERROR(IF(I27="RM",(W27*J27),AE27),"") -> 0.77 | AH27: =IFERROR(AE27-AG27,"") -> 0 | AI27: =IF(Q27="Shearing",L27,IF(Q27="Blanking",(L27+N27*1.5),IF(Q27="Laser Cutting",(L27+4)))) -> FALSE | AJ27: =IF(Q27="Shearing",M27,IF(Q27="Blanking",(M27+N27*3),IF(Q27="Laser Cutting",(M27+4)))) -> FALSE | AK27: =IF((INT(O27/AI27)*INT(P27/AJ27))>(INT(O27/AJ27)*INT(P27/AI27)),INT(O27/AI27)*INT(P27/AJ27),IF((INT(O27/AI27)*INT(P27/AJ27))=(INT(O27/AJ27)*INT(P27/AI27)),(INT(O27/AI27)*INT(P27/AJ27)),(INT(O27/AJ27)*INT(P27/AI27)))) -> #VALUE! | AL27: =IF((INT(O27/AI27)*INT(P27/AJ27))>(INT(O27/AJ27)*INT(P27/AI27)),INT(O27/AI27),IF((INT(O27/AI27)*INT(P27/AJ27))=(INT(O27/AJ27)*INT(P27/AI27)),(INT(O27/AI27)),(INT(O27/AJ27)))) -> #VALUE! | AM27: =IF((INT(O27/AI27)*INT(P27/AJ27))>(INT(O27/AJ27)*INT(P27/AI27)),INT(P27/AJ27),IF((INT(O27/AI27)*INT(P27/AJ27))=(INT(O27/AJ27)*INT(P27/AI27)),(INT(P27/AJ27)),(INT(P27/AI27)))) -> #VALUE! | AN27: =IF(Q27="Blanking",L27+1.5*N27,L27) -> 0 | AO27: =IF(Q27="Blanking",M27+1.5*2*N27,M27) -> 0 | AP27: =INT(O27/AN27)*INT(P27/AO27) -> #VALUE! | AQ27: =INT(P27/AN27)*INT(O27/AO27) -> #DIV/0! | AR27: =INT(O27/AO27)*INT(P27/AN27) -> #VALUE! | AS27: =INT(P27/AO27)*INT(O27/AN27) -> #DIV/0! | AT27: =O27-(INT(O27/AN27)*AN27) -> #VALUE! | AU27: =P27-(INT(P27/AN27)*AN27) -> #DIV/0! | AV27: =O27-(INT(O27/AO27)*AO27) -> #VALUE! | AW27: =P27-(INT(P27/AO27)*AO27) -> #DIV/0! | AX27: =INT(AT27/AO27)*INT(P27/AN27) -> #VALUE! | AY27: =INT(AU27/AO27)*INT(O27/AN27) -> #DIV/0! | AZ27: =INT(AV27/AN27)*INT(P27/AO27) -> #VALUE! | BA27: =INT(AW27/AN27)*INT(O27/AO27) -> #DIV/0! | BB27: =AX27+AP27 -> #VALUE! | BC27: =AY27+AQ27 -> #DIV/0! | BD27: =AZ27+AR27 -> #VALUE! | BE27: =BA27+AS27 -> #DIV/0! | BF27: =MAX(BB27:BE27) -> #VALUE! | BG27: =IF(BB27=BF27,MIN(INT(O27/AN27),INT(P27/AO27)),IF(BC27=BF27,MIN(INT(P27/AN27),INT(O27/AO27)),IF(BD27=BF27,MIN(INT(O27/AO27),INT(P27/AN27)),MIN(INT(P27/AO27),INT(O27/AN27))))) -> #VALUE! | BH27: =IF(BB27=BF27,MIN(INT(AT27/AO27),INT(1250/AN27)),IF(BC27=BF27,MIN(INT(AU27/AO27),INT(O27/AN27)),IF(BD27=BF27,MIN(INT(AV27/AN27),INT(P27/AO27)),MIN(INT(AW27/AN27),INT(O27/AO27))))) -> #VALUE! | BI27: =IFERROR(BG27+BH27,"")
B28: =_xlfn.IFNA(VLOOKUP(D28,Group!$AM$1:$AO$10000,3,0),"") -> FWR10000 | C28: =_xlfn.IFNA(VLOOKUP(D28,Group!$AM$1:$AO$10000,2,0),"") -> 3 | D28: =Group!K17 -> H 157 01 464 A Towel Bar | E28: =_xlfn.IFNA(VLOOKUP(D28,BOM!$D$1:$F$10000,2,0),"") -> 0 | F28: =_xlfn.IFNA(VLOOKUP(D28,BOM!$D$1:$F$10000,3,0),"") -> Adjust Bar | G28: =_xlfn.IFNA(IF(VLOOKUP(D28,BOM!D:J,7,0)="CSC","CSC","Others"),"") -> Others | I28: =_xlfn.IFNA(IF(OR(VLOOKUP(D28,BOM!$D$1:$I$1000,6,0)="Inhouse",VLOOKUP(D28,BOM!$D$1:$J$1000,7,0)="CSC"),"RM","BOP"),"") -> RM | J28: =_xlfn.IFNA(IF(VLOOKUP(H28,'RM Base'!D:F,3,0)="Kg",VLOOKUP(H28,'RM Base'!D:E,2,0),IF(VLOOKUP(H28,'RM Base'!D:F,3,0)="Meter",(VLOOKUP(H28,'RM Base'!D:E,2,0)/R28*O28/1000),CONCATENATE("The Price is in ",VLOOKUP(H28,'RM Base'!D:F,3,0)))),"") | O28: =IF(K28<>"",IF(OR(K28="Pipe", K28="Circular Tube", K28="Square/Rectangular Tube"),IF(ISNUMBER(SEARCH("ss", H28)), 5000, 6000),2500),"") | P28: =IF(OR(O28=6000,O28=5000,O28=""),M28,1250) -> 0 | R28: =IF(K28="Sheet Metal",O28*P28*N28*7.86/10^6,IF(OR(K28="Pipe", K28="Circular Tube"),O28*(P28^2-(P28-2*N28)^2)*3.14/4*7.86*10^-6,IF(K28="Square/Rectangular Tube",O28*P28*N28*7.86*10^-6,""))) | S28: =IF(L28<>"",IF(OR(K28="Pipe", K28="Circular Tube"),INT(O28/(L28+5)),IF(K28="Square/Rectangular Tube",INT(O28/(L28+5)),IF(Q28="Laser Cutting",AK28,BF28))),"") | T28: =IF(OR(K28="Pipe", K28="Circular Tube"),L28*(M28^2-(M28-2*N28)^2)*3.14/4*7.86*10^-6,IF(K28="Square/Rectangular Tube",L28*M28*N28*7.86*10^-6,IF(K28="Sheet Metal",L28*M28*N28*7.86*10^-6,""))) | U28: =IFERROR(R28/S28,"") | V28: =IFERROR(I28*U28,"") | X28: =IF(W28="","",W28) | Y28: =IF(U28="","",W28/U28) | Z28: =IF(Y28="","",IF(I28="RM",IF(K28="Sheet Metal",W28/N28/7.86*2,IF(OR(K28="Pipe",K28="Circular Tube"),L28*PI()*M28/10^6,IF(K28="Square/Rectangular Tube",W28/N28/7.86,0))))) | AB28: =IF(Z28="","",U28-W28) | AC28: =_xlfn.IFNA(VLOOKUP(H28,'RM Base'!D:K,8,0),"") | AD28: =IF(K28<>"",IF(K28="Sheet Metal",95%,80%),"") | AE28: =0.237*250 -> 59.25 | AG28: =IFERROR(IF(I28="RM",(W28*J28),AE28),"") | AH28: =IFERROR(AE28-AG28,"") | AI28: =IF(Q28="Shearing",L28,IF(Q28="Blanking",(L28+N28*1.5),IF(Q28="Laser Cutting",(L28+4)))) -> FALSE | AJ28: =IF(Q28="Shearing",M28,IF(Q28="Blanking",(M28+N28*3),IF(Q28="Laser Cutting",(M28+4)))) -> FALSE | AK28: =IF((INT(O28/AI28)*INT(P28/AJ28))>(INT(O28/AJ28)*INT(P28/AI28)),INT(O28/AI28)*INT(P28/AJ28),IF((INT(O28/AI28)*INT(P28/AJ28))=(INT(O28/AJ28)*INT(P28/AI28)),(INT(O28/AI28)*INT(P28/AJ28)),(INT(O28/AJ28)*INT(P28/AI28)))) -> #VALUE! | AL28: =IF((INT(O28/AI28)*INT(P28/AJ28))>(INT(O28/AJ28)*INT(P28/AI28)),INT(O28/AI28),IF((INT(O28/AI28)*INT(P28/AJ28))=(INT(O28/AJ28)*INT(P28/AI28)),(INT(O28/AI28)),(INT(O28/AJ28)))) -> #VALUE! | AM28: =IF((INT(O28/AI28)*INT(P28/AJ28))>(INT(O28/AJ28)*INT(P28/AI28)),INT(P28/AJ28),IF((INT(O28/AI28)*INT(P28/AJ28))=(INT(O28/AJ28)*INT(P28/AI28)),(INT(P28/AJ28)),(INT(P28/AI28)))) -> #VALUE! | AN28: =IF(Q28="Blanking",L28+1.5*N28,L28) -> 0 | AO28: =IF(Q28="Blanking",M28+1.5*2*N28,M28) -> 0 | AP28: =INT(O28/AN28)*INT(P28/AO28) -> #VALUE! | AQ28: =INT(P28/AN28)*INT(O28/AO28) -> #DIV/0! | AR28: =INT(O28/AO28)*INT(P28/AN28) -> #VALUE! | AS28: =INT(P28/AO28)*INT(O28/AN28) -> #DIV/0! | AT28: =O28-(INT(O28/AN28)*AN28) -> #VALUE! | AU28: =P28-(INT(P28/AN28)*AN28) -> #DIV/0! | AV28: =O28-(INT(O28/AO28)*AO28) -> #VALUE! | AW28: =P28-(INT(P28/AO28)*AO28) -> #DIV/0! | AX28: =INT(AT28/AO28)*INT(P28/AN28) -> #VALUE! | AY28: =INT(AU28/AO28)*INT(O28/AN28) -> #DIV/0! | AZ28: =INT(AV28/AN28)*INT(P28/AO28) -> #VALUE! | BA28: =INT(AW28/AN28)*INT(O28/AO28) -> #DIV/0! | BB28: =AX28+AP28 -> #VALUE! | BC28: =AY28+AQ28 -> #DIV/0! | BD28: =AZ28+AR28 -> #VALUE! | BE28: =BA28+AS28 -> #DIV/0! | BF28: =MAX(BB28:BE28) -> #VALUE! | BG28: =IF(BB28=BF28,MIN(INT(O28/AN28),INT(P28/AO28)),IF(BC28=BF28,MIN(INT(P28/AN28),INT(O28/AO28)),IF(BD28=BF28,MIN(INT(O28/AO28),INT(P28/AN28)),MIN(INT(P28/AO28),INT(O28/AN28))))) -> #VALUE! | BH28: =IF(BB28=BF28,MIN(INT(AT28/AO28),INT(1250/AN28)),IF(BC28=BF28,MIN(INT(AU28/AO28),INT(O28/AN28)),IF(BD28=BF28,MIN(INT(AV28/AN28),INT(P28/AO28)),MIN(INT(AW28/AN28),INT(O28/AO28))))) -> #VALUE! | BI28: =IFERROR(BG28+BH28,"")
B29: =_xlfn.IFNA(VLOOKUP(D29,Group!$AM$1:$AO$10000,3,0),"") -> FWR10000 | C29: =_xlfn.IFNA(VLOOKUP(D29,Group!$AM$1:$AO$10000,2,0),"") -> 3 | D29: =Group!K18 -> H 157 01 464 A Towel Bar Brkt | E29: =_xlfn.IFNA(VLOOKUP(D29,BOM!$D$1:$F$10000,2,0),"") -> 0 | F29: =_xlfn.IFNA(VLOOKUP(D29,BOM!$D$1:$F$10000,3,0),"") -> Towel Bar Brkt | G29: =_xlfn.IFNA(IF(VLOOKUP(D29,BOM!D:J,7,0)="CSC","CSC","Others"),"") -> CSC | H29: IS2062 | I29: =_xlfn.IFNA(IF(OR(VLOOKUP(D29,BOM!$D$1:$I$1000,6,0)="Inhouse",VLOOKUP(D29,BOM!$D$1:$J$1000,7,0)="CSC"),"RM","BOP"),"") -> RM | J29: =_xlfn.IFNA(IF(VLOOKUP(H29,'RM Base'!D:F,3,0)="Kg",VLOOKUP(H29,'RM Base'!D:E,2,0),IF(VLOOKUP(H29,'RM Base'!D:F,3,0)="Meter",(VLOOKUP(H29,'RM Base'!D:E,2,0)/R29*O29/1000),CONCATENATE("The Price is in ",VLOOKUP(H29,'RM Base'!D:F,3,0)))),"") -> 53 | K29: Sheet Metal | L29: 33 | M29: 24 | N29: 3 | O29: =IF(K29<>"",IF(OR(K29="Pipe", K29="Circular Tube", K29="Square/Rectangular Tube"),IF(ISNUMBER(SEARCH("ss", H29)), 5000, 6000),2500),"") -> 2500 | P29: =IF(OR(O29=6000,O29=5000,O29=""),M29,1250) -> 1250 | Q29: Blanking | R29: =IF(K29="Sheet Metal",O29*P29*N29*7.86/10^6,IF(OR(K29="Pipe", K29="Circular Tube"),O29*(P29^2-(P29-2*N29)^2)*3.14/4*7.86*10^-6,IF(K29="Square/Rectangular Tube",O29*P29*N29*7.86*10^-6,""))) -> 73.6875 | S29: =IF(L29<>"",IF(OR(K29="Pipe", K29="Circular Tube"),INT(O29/(L29+5)),IF(K29="Square/Rectangular Tube",INT(O29/(L29+5)),IF(Q29="Laser Cutting",AK29,BF29))),"") -> 2475 | T29: =IF(OR(K29="Pipe", K29="Circular Tube"),L29*(M29^2-(M29-2*N29)^2)*3.14/4*7.86*10^-6,IF(K29="Square/Rectangular Tube",L29*M29*N29*7.86*10^-6,IF(K29="Sheet Metal",L29*M29*N29*7.86*10^-6,""))) -> 0.01867536 | U29: =IFERROR(R29/S29,"") -> 0.029772727 | V29: =IFERROR(I29*U29,"") | W29: 0.014 | X29: =IF(W29="","",W29) -> 0.014 | Y29: =IF(U29="","",W29/U29) -> 0.47022901 | Z29: =IF(Y29="","",IF(I29="RM",IF(K29="Sheet Metal",W29/N29/7.86*2,IF(OR(K29="Pipe",K29="Circular Tube"),L29*PI()*M29/10^6,IF(K29="Square/Rectangular Tube",W29/N29/7.86,0))))) -> 0.001187447 | AB29: =IF(Z29="","",U29-W29) -> 0.015772727 | AC29: =_xlfn.IFNA(VLOOKUP(H29,'RM Base'!D:K,8,0),"") -> 30.5 | AD29: =IF(K29<>"",IF(K29="Sheet Metal",95%,80%),"") -> 0.95 | AE29: =IF(AD29="","",(J29*U29)-(AB29*AC29*AD29)) -> 1.1209398 | AG29: =IFERROR(IF(I29="RM",(W29*J29),AE29),"") -> 0.742 | AH29: =IFERROR(AE29-AG29,"") -> 0.37893977 | AI29: =IF(Q29="Shearing",L29,IF(Q29="Blanking",(L29+N29*1.5),IF(Q29="Laser Cutting",(L29+4)))) -> 37.5 | AJ29: =IF(Q29="Shearing",M29,IF(Q29="Blanking",(M29+N29*3),IF(Q29="Laser Cutting",(M29+4)))) -> 33 | AK29: =IF((INT(O29/AI29)*INT(P29/AJ29))>(INT(O29/AJ29)*INT(P29/AI29)),INT(O29/AI29)*INT(P29/AJ29),IF((INT(O29/AI29)*INT(P29/AJ29))=(INT(O29/AJ29)*INT(P29/AI29)),(INT(O29/AI29)*INT(P29/AJ29)),(INT(O29/AJ29)*INT(P29/AI29)))) -> 2475 | AL29: =IF((INT(O29/AI29)*INT(P29/AJ29))>(INT(O29/AJ29)*INT(P29/AI29)),INT(O29/AI29),IF((INT(O29/AI29)*INT(P29/AJ29))=(INT(O29/AJ29)*INT(P29/AI29)),(INT(O29/AI29)),(INT(O29/AJ29)))) -> 75 | AM29: =IF((INT(O29/AI29)*INT(P29/AJ29))>(INT(O29/AJ29)*INT(P29/AI29)),INT(P29/AJ29),IF((INT(O29/AI29)*INT(P29/AJ29))=(INT(O29/AJ29)*INT(P29/AI29)),(INT(P29/AJ29)),(INT(P29/AI29)))) -> 33 | AN29: =IF(Q29="Blanking",L29+1.5*N29,L29) -> 37.5 | AO29: =IF(Q29="Blanking",M29+1.5*2*N29,M29) -> 33 | AP29: =INT(O29/AN29)*INT(P29/AO29) -> 2442 | AQ29: =INT(P29/AN29)*INT(O29/AO29) -> 2475 | AR29: =INT(O29/AO29)*INT(P29/AN29) -> 2475 | AS29: =INT(P29/AO29)*INT(O29/AN29) -> 2442 | AT29: =O29-(INT(O29/AN29)*AN29) -> 25 | AU29: =P29-(INT(P29/AN29)*AN29) -> 12.5 | AV29: =O29-(INT(O29/AO29)*AO29) -> 25 | AW29: =P29-(INT(P29/AO29)*AO29) -> 29 | AX29: =INT(AT29/AO29)*INT(P29/AN29) -> 0 | AY29: =INT(AU29/AO29)*INT(O29/AN29) -> 0 | AZ29: =INT(AV29/AN29)*INT(P29/AO29) -> 0 | BA29: =INT(AW29/AN29)*INT(O29/AO29) -> 0 | BB29: =AX29+AP29 -> 2442 | BC29: =AY29+AQ29 -> 2475 | BD29: =AZ29+AR29 -> 2475 | BE29: =BA29+AS29 -> 2442 | BF29: =MAX(BB29:BE29) -> 2475 | BG29: =IF(BB29=BF29,MIN(INT(O29/AN29),INT(P29/AO29)),IF(BC29=BF29,MIN(INT(P29/AN29),INT(O29/AO29)),IF(BD29=BF29,MIN(INT(O29/AO29),INT(P29/AN29)),MIN(INT(P29/AO29),INT(O29/AN29))))) -> 33 | BH29: =IF(BB29=BF29,MIN(INT(AT29/AO29),INT(1250/AN29)),IF(BC29=BF29,MIN(INT(AU29/AO29),INT(O29/AN29)),IF(BD29=BF29,MIN(INT(AV29/AN29),INT(P29/AO29)),MIN(INT(AW29/AN29),INT(O29/AO29))))) -> 0 | BI29: =IFERROR(BG29+BH29,"") -> 33
B30: =_xlfn.IFNA(VLOOKUP(D30,Group!$AM$1:$AO$10000,3,0),"") -> FWR10000 | C30: =_xlfn.IFNA(VLOOKUP(D30,Group!$AM$1:$AO$10000,2,0),"") -> 3 | D30: =Group!K19 -> H 157 01 464 A adjust bar | E30: =_xlfn.IFNA(VLOOKUP(D30,BOM!$D$1:$F$10000,2,0),"") -> 0 | F30: =_xlfn.IFNA(VLOOKUP(D30,BOM!$D$1:$F$10000,3,0),"") -> Towel Bar | G30: =_xlfn.IFNA(IF(VLOOKUP(D30,BOM!D:J,7,0)="CSC","CSC","Others"),"") -> CSC | H30: CEW | I30: =_xlfn.IFNA(IF(OR(VLOOKUP(D30,BOM!$D$1:$I$1000,6,0)="Inhouse",VLOOKUP(D30,BOM!$D$1:$J$1000,7,0)="CSC"),"RM","BOP"),"") -> RM | J30: =_xlfn.IFNA(IF(VLOOKUP(H30,'RM Base'!D:F,3,0)="Kg",VLOOKUP(H30,'RM Base'!D:E,2,0),IF(VLOOKUP(H30,'RM Base'!D:F,3,0)="Meter",(VLOOKUP(H30,'RM Base'!D:E,2,0)/R30*O30/1000),CONCATENATE("The Price is in ",VLOOKUP(H30,'RM Base'!D:F,3,0)))),"") -> 97.25 | K30: Pipe | L30: 360 | M30: 12.7 | N30: 3 | O30: =IF(K30<>"",IF(OR(K30="Pipe", K30="Circular Tube", K30="Square/Rectangular Tube"),IF(ISNUMBER(SEARCH("ss", H30)), 5000, 6000),2500),"") -> 6000 | P30: =IF(OR(O30=6000,O30=5000,O30=""),M30,1250) -> 12.7 | R30: =IF(K30="Sheet Metal",O30*P30*N30*7.86/10^6,IF(OR(K30="Pipe", K30="Circular Tube"),O30*(P30^2-(P30-2*N30)^2)*3.14/4*7.86*10^-6,IF(K30="Square/Rectangular Tube",O30*P30*N30*7.86*10^-6,""))) -> 4.3091978 | S30: =IF(L30<>"",IF(OR(K30="Pipe", K30="Circular Tube"),INT(O30/(L30+5)),IF(K30="Square/Rectangular Tube",INT(O30/(L30+5)),IF(Q30="Laser Cutting",AK30,BF30))),"") -> 16 | T30: =IF(OR(K30="Pipe", K30="Circular Tube"),L30*(M30^2-(M30-2*N30)^2)*3.14/4*7.86*10^-6,IF(K30="Square/Rectangular Tube",L30*M30*N30*7.86*10^-6,IF(K30="Sheet Metal",L30*M30*N30*7.86*10^-6,""))) -> 0.25855187 | U30: =IFERROR(R30/S30,"") -> 0.26932486 | V30: =IFERROR(I30*U30,"") | W30: 0.19 | X30: =IF(W30="","",W30) -> 0.19 | Y30: =IF(U30="","",W30/U30) -> 0.70546773 | Z30: =IF(Y30="","",IF(I30="RM",IF(K30="Sheet Metal",W30/N30/7.86*2,IF(OR(K30="Pipe",K30="Circular Tube"),L30*PI()*M30/10^6,IF(K30="Square/Rectangular Tube",W30/N30/7.86,0))))) -> 0.014363362 | AB30: =IF(Z30="","",U30-W30) -> 0.079324865 | AC30: =_xlfn.IFNA(VLOOKUP(H30,'RM Base'!D:K,8,0),"") -> 32 | AD30: =IF(K30<>"",IF(K30="Sheet Metal",95%,80%),"") -> 0.8 | AE30: =IF(AD30="","",(J30*U30)-(AB30*AC30*AD30)) -> 24.161127 | AG30: =IFERROR(IF(I30="RM",(W30*J30),AE30),"") -> 18.4775 | AH30: =IFERROR(AE30-AG30,"") -> 5.6836266 | AI30: =IF(Q30="Shearing",L30,IF(Q30="Blanking",(L30+N30*1.5),IF(Q30="Laser Cutting",(L30+4)))) -> FALSE | AJ30: =IF(Q30="Shearing",M30,IF(Q30="Blanking",(M30+N30*3),IF(Q30="Laser Cutting",(M30+4)))) -> FALSE | AK30: =IF((INT(O30/AI30)*INT(P30/AJ30))>(INT(O30/AJ30)*INT(P30/AI30)),INT(O30/AI30)*INT(P30/AJ30),IF((INT(O30/AI30)*INT(P30/AJ30))=(INT(O30/AJ30)*INT(P30/AI30)),(INT(O30/AI30)*INT(P30/AJ30)),(INT(O30/AJ30)*INT(P30/AI30)))) -> #DIV/0! | AL30: =IF((INT(O30/AI30)*INT(P30/AJ30))>(INT(O30/AJ30)*INT(P30/AI30)),INT(O30/AI30),IF((INT(O30/AI30)*INT(P30/AJ30))=(INT(O30/AJ30)*INT(P30/AI30)),(INT(O30/AI30)),(INT(O30/AJ30)))) -> #DIV/0! | AM30: =IF((INT(O30/AI30)*INT(P30/AJ30))>(INT(O30/AJ30)*INT(P30/AI30)),INT(P30/AJ30),IF((INT(O30/AI30)*INT(P30/AJ30))=(INT(O30/AJ30)*INT(P30/AI30)),(INT(P30/AJ30)),(INT(P30/AI30)))) -> #DIV/0! | AN30: =IF(Q30="Blanking",L30+1.5*N30,L30) -> 360 | AO30: =IF(Q30="Blanking",M30+1.5*2*N30,M30) -> 12.7 | AP30: =INT(O30/AN30)*INT(P30/AO30) -> 16 | AQ30: =INT(P30/AN30)*INT(O30/AO30) -> 0 | AR30: =INT(O30/AO30)*INT(P30/AN30) -> 0 | AS30: =INT(P30/AO30)*INT(O30/AN30) -> 16 | AT30: =O30-(INT(O30/AN30)*AN30) -> 240 | AU30: =P30-(INT(P30/AN30)*AN30) -> 12.7 | AV30: =O30-(INT(O30/AO30)*AO30) -> 5.6 | AW30: =P30-(INT(P30/AO30)*AO30) -> 0 | AX30: =INT(AT30/AO30)*INT(P30/AN30) -> 0 | AY30: =INT(AU30/AO30)*INT(O30/AN30) -> 16 | AZ30: =INT(AV30/AN30)*INT(P30/AO30) -> 0 | BA30: =INT(AW30/AN30)*INT(O30/AO30) -> 0 | BB30: =AX30+AP30 -> 16 | BC30: =AY30+AQ30 -> 16 | BD30: =AZ30+AR30 -> 0 | BE30: =BA30+AS30 -> 16 | BF30: =MAX(BB30:BE30) -> 16 | BG30: =IF(BB30=BF30,MIN(INT(O30/AN30),INT(P30/AO30)),IF(BC30=BF30,MIN(INT(P30/AN30),INT(O30/AO30)),IF(BD30=BF30,MIN(INT(O30/AO30),INT(P30/AN30)),MIN(INT(P30/AO30),INT(O30/AN30))))) -> 1 | BH30: =IF(BB30=BF30,MIN(INT(AT30/AO30),INT(1250/AN30)),IF(BC30=BF30,MIN(INT(AU30/AO30),INT(O30/AN30)),IF(BD30=BF30,MIN(INT(AV30/AN30),INT(P30/AO30)),MIN(INT(AW30/AN30),INT(O30/AO30))))) -> 3 | BI30: =IFERROR(BG30+BH30,"") -> 4
B31: =_xlfn.IFNA(VLOOKUP(D31,Group!$AM$1:$AO$10000,3,0),"") -> FWR10000 | C31: =_xlfn.IFNA(VLOOKUP(D31,Group!$AM$1:$AO$10000,2,0),"") -> 3 | D31: =Group!K20 -> H 157 01 464 A Slider Rivet Ø7mm | E31: =_xlfn.IFNA(VLOOKUP(D31,BOM!$D$1:$F$10000,2,0),"") -> 0 | F31: =_xlfn.IFNA(VLOOKUP(D31,BOM!$D$1:$F$10000,3,0),"") -> Slider Rivet Ø7mm | G31: =_xlfn.IFNA(IF(VLOOKUP(D31,BOM!D:J,7,0)="CSC","CSC","Others"),"") -> Others | I31: =_xlfn.IFNA(IF(OR(VLOOKUP(D31,BOM!$D$1:$I$1000,6,0)="Inhouse",VLOOKUP(D31,BOM!$D$1:$J$1000,7,0)="CSC"),"RM","BOP"),"") -> BOP | J31: =_xlfn.IFNA(IF(VLOOKUP(H31,'RM Base'!D:F,3,0)="Kg",VLOOKUP(H31,'RM Base'!D:E,2,0),IF(VLOOKUP(H31,'RM Base'!D:F,3,0)="Meter",(VLOOKUP(H31,'RM Base'!D:E,2,0)/R31*O31/1000),CONCATENATE("The Price is in ",VLOOKUP(H31,'RM Base'!D:F,3,0)))),"") | O31: =IF(K31<>"",IF(OR(K31="Pipe", K31="Circular Tube", K31="Square/Rectangular Tube"),IF(ISNUMBER(SEARCH("ss", H31)), 5000, 6000),2500),"") | P31: =IF(OR(O31=6000,O31=5000,O31=""),M31,1250) -> 0 | R31: =IF(K31="Sheet Metal",O31*P31*N31*7.86/10^6,IF(OR(K31="Pipe", K31="Circular Tube"),O31*(P31^2-(P31-2*N31)^2)*3.14/4*7.86*10^-6,IF(K31="Square/Rectangular Tube",O31*P31*N31*7.86*10^-6,""))) | S31: =IF(L31<>"",IF(OR(K31="Pipe", K31="Circular Tube"),INT(O31/(L31+5)),IF(K31="Square/Rectangular Tube",INT(O31/(L31+5)),IF(Q31="Laser Cutting",AK31,BF31))),"") | T31: =IF(OR(K31="Pipe", K31="Circular Tube"),L31*(M31^2-(M31-2*N31)^2)*3.14/4*7.86*10^-6,IF(K31="Square/Rectangular Tube",L31*M31*N31*7.86*10^-6,IF(K31="Sheet Metal",L31*M31*N31*7.86*10^-6,""))) | U31: =IFERROR(R31/S31,"") | V31: =IFERROR(I31*U31,"") | X31: =IF(W31="","",W31) | Y31: =IF(U31="","",W31/U31) | Z31: =IF(Y31="","",IF(I31="RM",IF(K31="Sheet Metal",W31/N31/7.86*2,IF(OR(K31="Pipe",K31="Circular Tube"),L31*PI()*M31/10^6,IF(K31="Square/Rectangular Tube",W31/N31/7.86,0))))) | AB31: =IF(Z31="","",U31-W31) | AC31: =_xlfn.IFNA(VLOOKUP(H31,'RM Base'!D:K,8,0),"") | AD31: =IF(K31<>"",IF(K31="Sheet Metal",95%,80%),"") | AE31: 1.8 | AG31: =IFERROR(IF(I31="RM",(W31*J31),AE31),"") -> 1.8 | AH31: =IFERROR(AE31-AG31,"") -> 0 | AI31: =IF(Q31="Shearing",L31,IF(Q31="Blanking",(L31+N31*1.5),IF(Q31="Laser Cutting",(L31+4)))) -> FALSE | AJ31: =IF(Q31="Shearing",M31,IF(Q31="Blanking",(M31+N31*3),IF(Q31="Laser Cutting",(M31+4)))) -> FALSE | AK31: =IF((INT(O31/AI31)*INT(P31/AJ31))>(INT(O31/AJ31)*INT(P31/AI31)),INT(O31/AI31)*INT(P31/AJ31),IF((INT(O31/AI31)*INT(P31/AJ31))=(INT(O31/AJ31)*INT(P31/AI31)),(INT(O31/AI31)*INT(P31/AJ31)),(INT(O31/AJ31)*INT(P31/AI31)))) -> #VALUE! | AL31: =IF((INT(O31/AI31)*INT(P31/AJ31))>(INT(O31/AJ31)*INT(P31/AI31)),INT(O31/AI31),IF((INT(O31/AI31)*INT(P31/AJ31))=(INT(O31/AJ31)*INT(P31/AI31)),(INT(O31/AI31)),(INT(O31/AJ31)))) -> #VALUE! | AM31: =IF((INT(O31/AI31)*INT(P31/AJ31))>(INT(O31/AJ31)*INT(P31/AI31)),INT(P31/AJ31),IF((INT(O31/AI31)*INT(P31/AJ31))=(INT(O31/AJ31)*INT(P31/AI31)),(INT(P31/AJ31)),(INT(P31/AI31)))) -> #VALUE! | AN31: =IF(Q31="Blanking",L31+1.5*N31,L31) -> 0 | AO31: =IF(Q31="Blanking",M31+1.5*2*N31,M31) -> 0 | AP31: =INT(O31/AN31)*INT(P31/AO31) -> #VALUE! | AQ31: =INT(P31/AN31)*INT(O31/AO31) -> #DIV/0! | AR31: =INT(O31/AO31)*INT(P31/AN31) -> #VALUE! | AS31: =INT(P31/AO31)*INT(O31/AN31) -> #DIV/0! | AT31: =O31-(INT(O31/AN31)*AN31) -> #VALUE! | AU31: =P31-(INT(P31/AN31)*AN31) -> #DIV/0! | AV31: =O31-(INT(O31/AO31)*AO31) -> #VALUE! | AW31: =P31-(INT(P31/AO31)*AO31) -> #DIV/0! | AX31: =INT(AT31/AO31)*INT(P31/AN31) -> #VALUE! | AY31: =INT(AU31/AO31)*INT(O31/AN31) -> #DIV/0! | AZ31: =INT(AV31/AN31)*INT(P31/AO31) -> #VALUE! | BA31: =INT(AW31/AN31)*INT(O31/AO31) -> #DIV/0! | BB31: =AX31+AP31 -> #VALUE! | BC31: =AY31+AQ31 -> #DIV/0! | BD31: =AZ31+AR31 -> #VALUE! | BE31: =BA31+AS31 -> #DIV/0! | BF31: =MAX(BB31:BE31) -> #VALUE! | BG31: =IF(BB31=BF31,MIN(INT(O31/AN31),INT(P31/AO31)),IF(BC31=BF31,MIN(INT(P31/AN31),INT(O31/AO31)),IF(BD31=BF31,MIN(INT(O31/AO31),INT(P31/AN31)),MIN(INT(P31/AO31),INT(O31/AN31))))) -> #VALUE! | BH31: =IF(BB31=BF31,MIN(INT(AT31/AO31),INT(1250/AN31)),IF(BC31=BF31,MIN(INT(AU31/AO31),INT(O31/AN31)),IF(BD31=BF31,MIN(INT(AV31/AN31),INT(P31/AO31)),MIN(INT(AW31/AN31),INT(O31/AO31))))) -> #VALUE! | BI31: =IFERROR(BG31+BH31,"")
